Workbook
Name mgr: '[1]Employee Information'!$A$2:$P$65

Sheet Currencies
A1: Currency Code | B1: Currency Name | C1: Rounding Method | D1: Exchange Currency Code | E1: Exchange Rate | F1: Exchange Eff Date
A2: USD | B2: US Dollar | E2: 1 | G2: $
A3: CAD | B3: Canadian Dollar | E3: 2 | G3: $
A4: AUD | B4: Australian Dollar | E4: 3 | G4: $
A5: EUR | B5: Euro | E5: 4 | G5: €
A6: BRL | B6: Brazilian Real | E6: 5 | G6: R$
A7: IDR | B7: Indonesian Rupiah | E7: 6 | G7: Rp
A8: AED | B8: U.A.E. Dirham | E8: 7 | G8: د.إ
A9: GBP | B9: British Pound | E9: 8 | G9: £

Sheet Rating Items
A1: Rating Alpha | B1: Rating | C1: Rating Group | D1: Distribution Pct | E1: Rating Name
A2: 1 | B2: 1 | C2: 1 | D2: 0
A3: 2 | B3: 2 | C3: 2 | D3: 0.1
A4: 3 | B4: 3 | C4: 3 | D4: 0.55
A5: 4 | B5: 4 | C5: 4 | D5: 0.25
A6: 5 | B6: 5 | C6: 5 | D6: 0.1

Sheet Guideline Divisions
A1: Guideline Name | B1: Rating Name | C1: Guideline Div Name | D1: Guideline Div Seq | E1: Guideline Div Val
C2: Q1 | D2: 1 | E2: 80
C3: Q2 | D3: 2 | E3: 100
C4: Q3 | D4: 3 | E4: 115
C5: Q4 | D5: 4 | E5: 135
A6: First | C6: Q1 | D6: 1 | E6: 80
A7: First | C7: Q2 | D7: 2 | E7: 100
A8: First | C8: Q3 | D8: 3 | E8: 115
A9: First | C9: Q4 | D9: 4 | E9: 135
A10: Second | C10: Q1 | D10: 1 | E10: 80
A11: Second | C11: Q2 | D11: 2 | E11: 100
A12: Second | C12: Q3 | D12: 3 | E12: 115
A13: Second | C13: Q4 | D13: 4 | E13: 135
A14: Third | C14: Q1 | D14: 1 | E14: 80
A15: Third | C15: Q2 | D15: 2 | E15: 100
A16: Third | C16: Q3 | D16: 3 | E16: 115
A17: Third | C17: Q4 | D17: 4 | E17: 135
... A21: Forth | C21: Q4 | D21: 4 | E21: 100

Sheet Budget Pools
A1: Budget Pool Name | B1: Pct Based? | C1: Budget Pool Pct | D1: Holdback Pct | E1: Currency Code | F1: Budget Pool Amount | G1: Holdback Pool Amount | H1: Spend Range Adj? | I1: Spend Merit? | J1: Spend Lump Sum? | K1: Spend Internal Equity? | L1: Spend Promo? | M1: Spend Market Adj? | N1: Spend Other? | O1: Spend Variable 1? | P1: Spend Variable 2? | Q1: Tgt Plan?
A2: June Budget | B2: y | C2: 40 | D2: 20 | G2: 4000 | H2: yes | I2: y | J2: 0 | K2: 0 | L2: 1 | M2: 1 | N2: 0 | O2: y | P2: n | Q2: yes
A3: july Budget | B3: n | C3: 30 | D3: 10 | E3: USD | F3: 6000 | G3: 2000 | H3: yes | I3: y | J3: 0 | K3: 0 | L3: 1 | M3: 1 | N3: 0 | O3: y | P3: n | Q3: yes
A4: Auguest Budget | C4: 40 | D4: 30 | E4: USD | F4: 7000 | G4: 3000 | H4: yes | I4: y | J4: 0 | K4: 0 | L4: 1 | M4: 1 | N4: 0 | O4: y | P4: n | Q4: yes
A5: September Budget | C5: 50 | D5: 40 | E5: CAD | F5: 20000 | G5: 1000 | H5: yes | I5: y | J5: 0 | K5: 0 | L5: 1 | M5: 1 | N5: 0 | O5: y | P5: n | Q5: yes
A6: oct Budget | B6: 0 | C6: 20 | D6: 50 | E6: USD | F6: 40000 | G6: 100 | H6: yes | I6: y | J6: 0 | K6: 0 | L6: 1 | M6: 1 | N6: 0 | O6: y | P6: n | Q6: yes
A7: November Budget | B7: 1 | C7: 20 | D7: 15 | F7: 50000 | G7: 200 | H7: yes | I7: y | J7: 0 | K7: 0 | L7: 1 | M7: 1 | N7: 0 | O7: y | P7: n | Q7: yes

Sheet Budget Pool Divisions
A1: Budget Pool Name | B1: Pool Div Name | C1: Pool Div Pct | D1: Pool Div Merit | E1: Pool Div Merit Ls | F1: Pool Div Internal Equity | G1: Pool Div Promo | H1: Pool Div Market Adj | I1: Pool Div Other | J1: Pool Div Is Variable 1 | K1: Pool Div Is Variable 2
A2: June Budget | B2: A | C2: 1
A3: july Budget | B3: B
A4: Auguest Budget | B4: C | C4: 1
A5: September Budget | B5: D
A6: oct Budget | B6: E | C6: 2
A7: November Budget | B7: F

Sheet Salary Structure Items
A1: Structure Name | B1: Structure Region | C1: Salary Grade | D1: Salary Gradexx | E1: Structure Item | F1: Structure Min Amt | G1: Structure Mid Amt | H1: Structure Max Amt | I1: Currency Code | J1: Budget Pool Name | K1: Structure seq
A2: Exempt US | C2: E06 | D2: E06 | E2: E06 | F2: 12400 | G2: 15200 | H2: 19100 | I2: USD | K2: 1
A3: Exempt US | C3: E08 | D3: E08 | E3: E08 | F3: 15400 | G3: 19200 | H3: 23100 | I3: USD | K3: 2
A4: Exempt US | C4: E10 | D4: E10 | E4: E10 | F4: 16000 | G4: 20000 | H4: 30000 | I4: USD | K4: 3
A5: Exempt US | C5: E12 | D5: E12 | E5: E12 | F5: 23700 | G5: 31500 | H5: 39400 | I5: USD | K5: 4
A6: Exempt US | C6: E14 | D6: E14 | E6: E14 | F6: 29400 | G6: 42000 | H6: 54600 | I6: USD | K6: 5
A7: Exempt US | C7: E16 | D7: E16 | E7: E16 | F7: 36200 | G7: 51600 | H7: 67100 | I7: USD | K7: 6
A8: Exempt US | C8: E18 | D8: E18 | E8: E18 | F8: 42700 | G8: 61000 | H8: 79300 | I8: USD | K8: 7
A9: Exempt US | C9: E20 | D9: E20 | E9: E20 | F9: 48100 | G9: 74000 | H9: 99900 | I9: USD | K9: 8
A10: Exempt US | C10: E22 | D10: E22 | E10: E22 | F10: 53300 | G10: 82000 | H10: 110700 | I10: USD | K10: 9
A11: Exempt US | C11: E24 | D11: E24 | E11: E24 | F11: 57000 | G11: 95000 | H11: 133000 | I11: USD | K11: 10
A12: Exempt US | C12: E26 | D12: E26 | E12: E26 | F12: 63000 | G12: 105000 | H12: 147000 | I12: USD | K12: 11
A13: Exempt US | C13: E28 | D13: E28 | E13: E28 | F13: 74400 | G13: 124000 | H13: 173600 | I13: USD | K13: 12
... A32: Exempt CAD | C32: E29 | D32: E29 | E32: E29 | F32: 115600 | G32: 196000 | H32: 270400 | I32: CAD | K32: 31
A33: Exempt CAD | C33: E30 | D33: E30 | E33: E30 | F33: 121500 | G33: 202500 | H33: 283500 | K33: 32
A34: Exempt CAD | C34: E32 | D34: E32 | E34: E32 | F34: 141300 | G34: 235500 | H34: 329700 | I34: CAD | K34: 33
A35: Exempt CAD | C35: E34 | D35: E34 | E35: E34 | F35: 169200 | G35: 282000 | H35: 394800 | I35: CAD | K35: 34
A36: Exempt CAD | C36: E36 | D36: E36 | E36: E36 | F36: 199800 | G36: 333000 | H36: 466200 | I36: CAD | K36: 35
A37: Exempt CAD | C37: E38 | D37: E38 | E37: E38 | F37: 239400 | G37: 399000 | H37: 558600 | I37: CAD | K37: 36
A38: Exempt CAD | C38: E40 | D38: E40 | E38: E40 | F38: 288000 | G38: 480000 | H38: 672000 | I38: CAD | K38: 37
B39: Europe | C39: E20 | D39: E20 | E39: E20 | F39: 56000 | G39: 66000 | H39: 76000 | I39: EUR | K39: 38 | O39: Exempt EUR
B40: Australian | C40: E20 | D40: E20 | E40: E20 | F40: 57000 | G40: 67000 | H40: 77000 | I40: AUD | K40: 39 | O40: Exempt AUD
B41: Brazil | C41: E20 | D41: E20 | E41: E20 | F41: 58000 | G41: 68000 | H41: 78000 | I41: BRL | K41: 40 | O41: Exempt BRL
B42: Indonesia | C42: E20 | D42: E20 | E42: E20 | F42: 59000 | G42: 69000 | H42: 79000 | I42: IDR | K42: 41 | O42: Exempt IDR
B43: UAE | C43: E20 | D43: E20 | E43: E20 | F43: 60000 | G43: 70000 | H43: 80000 | I43: AED | K43: 42 | O43: Exempt AED
B44: Australian | C44: E21 | D44: E21 | E44: E21 | F44: 61000 | G44: 71000 | H44: 81000 | I44: AED | K44: 43
B45: Brazil | C45: E21 | D45: E21 | E45: E21 | F45: 63000 | G45: 72000 | H45: 82000 | I45: BRL | K45: 44

Sheet Employee Information
A1: Employee Id | B1: Emp Id | C1: Name | D1: Employee Name | E1: Job Title | F1: Job Family Name | G1: In HR? | H1: Rating Name | I1: Language Preference | J1: Per Pay Type | K1: Per Pay Amt | L1: Emp Status | M1: Hire Date | N1: DOH | O1: Mgr Emp Id | P1: Manager ID | Q1: Hair Color | R1: Manager Name | S1: Mgr Name | T1: HR Rep Emp Id | U1: HR Rep Name | V1: HR Area Rep Emp ID | W1: HR Area Rep Name | X1: Job Code | Y1: Job Titlexxx | Z1: Structure Name | AA1: Structure Region | AB1: Salary Grade | AC1: Structure Item | AD1: Currency Code | AE1: Starting Salary Amt | AF1: Current Annual Salary | AG1: Rating Alpha | AH1: Prior Rating Alpha | AI1: Min Amt | AJ1: Mid Amt | AK1: Max Amt | AL1: Position in Range | AM1: Range Penetration Label | AN1: Variable 1 Basis | AO1: Cur Variable 1 Tgt Val | AP1: Variable 2 Basis | AQ1: Cur Variable 2 Tgt Val | AR1: Hours Baseline | AS1: Hours Worked | AT1: Is Meeting Expectations
A2: 2009 | B2: 2009 | C2: Grimm, Briañ | D2: Grimm, Briañ | E2: Certified Doc Aide | F2: Accounting! | G2: TRUE | J2: Annually | L2: Active | M2: 45767 | N2: 45767 | O2: 2001 | P2: 2001 | Q2: Blond | R2: Ward Jr Lloyd | S2: Ward Jr Lloyd | T2: 80 | U2: Jackson, Charmain | V2: 80 | W2: Jackson, Charmain | X2: J001 | Y2: Programmer | Z2: Exempt CAD | AB2: E18 | AC2: E18 | AD2: AUD | AE2: 100000 | AF2: 100000 | AG2: 1 | AH2: Good | AI2: 42700 | AJ2: 61000 | AK2: 79300 | AL2: Q1 | AM2: Q1 | AO2: 5000 | AQ2: 30 | AR2: 40 | AS2: 40 | AT2: Stage meeting
A3: 2004 | B3: 2004 | C3: Janish Betty | D3: Janish Betty | E3: Certified Nurse Aide | F3: Operations@ | G3: TRUE | J3: Annually (1yr) | L3: Active | M3: 45767 | N3: 45767 | O3: 2001 | P3: 2001 | Q3: Brown | R3: Ward Jr Lloyd | S3: Ward Jr Lloyd | T3: 80 | U3: Jackson, Charmain | V3: 80 | W3: Jackson, Charmain | X3: J002 | Y3: Programmer | Z3: Exempt CAD | AB3: E18 | AC3: E18 | AD3: AUD | AE3: 100000 | AF3: 100000 | AG3: 2 | AH3: Good | AI3: 42700 | AJ3: 61000 | AK3: 79300 | AL3: Q2 | AM3: Q2 | AO3: 5000 | AQ3: 30 | AR3: 40 | AS3: 40 | AT3: Stage meeting
A4: 2002 | B4: 2002 | C4: Keeling, Larry | D4: Keeling, Larry | E4: LVN | F4: Operations# | G4: 0 | J4: Monthly (12) | L4: Active | M4: 45767 | N4: 45767 | O4: 2001 | P4: 2001 | Q4: Grey | R4: Ward Jr Lloyd | S4: Ward Jr Lloyd | T4: 80 | U4: Jackson, Charmain | V4: 80 | W4: Jackson, Charmain | X4: J003 | Y4: Programmer | Z4: Exempt CAD | AB4: E18 | AC4: E18 | AD4: AUD | AE4: 100000 | AF4: 100000 | AG4: 2 | AH4: Good | AI4: 42700 | AJ4: 61000 | AK4: 79300 | AL4: Q3 | AM4: Q3 | AO4: 5000 | AQ4: 30 | AR4: 40 | AS4: 40 | AT4: Stage meeting
A5: 2008 | B5: 2008 | C5: Krendick, Jasoñ | D5: Krendick, Jasoñ | E5: RN | F5: Operations$ | J5: Monthly | L5: Active | M5: 45767 | N5: 45767 | O5: 2001 | P5: 2001 | Q5: Red | R5: Ward Jr Lloyd | S5: Ward Jr Lloyd | T5: 80 | U5: Jackson, Charmain | V5: 80 | W5: Jackson, Charmain | X5: J004 | Y5: Programmer | Z5: Exempt CAD | AB5: E18 | AC5: E18 | AD5: AUD | AE5: 100000 | AF5: 100000 | AG5: 3 | AH5: Good | AI5: 42700 | AJ5: 61000 | AK5: 79300 | AL5: Q4 | AM5: Q4 | AO5: 5000 | AQ5: 30 | AR5: 40 | AS5: 40 | AT5: Stage meeting
A6: 2005 | B6: 2005 | C6: Leonard David | D6: Leonard David | E6: A/P Specialist | F6: Accounting% | G6: TRUE | J6: Hourly Basis | L6: Active | M6: 45767 | N6: 45767 | O6: 2001 | P6: 2001 | Q6: Brown | R6: Ward Jr Lloyd | S6: Ward Jr Lloyd | T6: 80 | U6: Jackson, Charmain | V6: 80 | W6: Jackson, Charmain | X6: J005 | Y6: Programmer | Z6: Exempt CAD | AB6: E18 | AC6: E18 | AD6: AUD | AE6: 100000 | AF6: 100000 | AG6: 1 | AH6: Poor | AI6: 42700 | AJ6: 61000 | AK6: 79300 | AL6: Q1 | AM6: Q1 | AO6: 5000 | AQ6: 30 | AR6: 40 | AS6: 40 | AT6: Stage meeting
A7: 2010 | B7: 2010 | C7: McFadden, Sarah | D7: McFadden, Sarah | E7: A/R Specialist-Billing | F7: Accounting^ | G7: T | J7: Hourly | L7: Active | M7: 45767 | N7: 45767 | O7: 2001 | P7: 2001 | Q7: Black | R7: Ward Jr Lloyd | S7: Ward Jr Lloyd | T7: 80 | U7: Jackson, Charmain | V7: 80 | W7: Jackson, Charmain | X7: J006 | Y7: Programmer | Z7: Exempt CAD | AB7: E18 | AC7: E18 | AD7: AUD | AE7: 100000 | AF7: 100000 | AG7: 5 | AH7: Good | AI7: 42700 | AJ7: 61000 | AK7: 79300 | AL7: Q2 | AM7: Q2 | AO7: 5000 | AQ7: 30 | AR7: 40 | AS7: 20 | AT7: Stage meeting
A8: 2007 | B8: 2007 | C8: Munshausen, Bruce | D8: Munshausen, Bruce | E8: HR Coordinator& | F8: Human\ Resources& | G8: t | J8: Monthly (13) | L8: Active | M8: 45767 | N8: 45767 | O8: 2001 | P8: 2001 | Q8: Brown | R8: Ward Jr Lloyd | S8: Ward Jr Lloyd | T8: 80 | U8: Jackson, Charmain | V8: 80 | W8: Jackson, Charmain | X8: J007 | Y8: Programmer | Z8: Exempt CAD | AB8: E18 | AC8: E18 | AD8: AUD | AE8: 100000 | AF8: 100000 | AG8: 3 | AH8: Good | AI8: 42700 | AJ8: 61000 | AK8: 79300 | AL8: Q3 | AM8: Q3 | AO8: 5000 | AQ8: 30 | AR8: 40 | AS8: 20 | AT8: PNL meeting
A9: 2006 | B9: 2006 | C9: Nelson III, Shawn | D9: Nelson III, Shawn | E9: HR Coordinator/AA | F9: Human Resources* | G9: 101 | J9: 13 Months | L9: Active | M9: 45767 | N9: 45767 | O9: 2001 | P9: 2001 | Q9: Brown | R9: Ward Jr Lloyd | S9: Ward Jr Lloyd | T9: 80 | U9: Jackson, Charmain | V9: 80 | W9: Jackson, Charmain | X9: J008 | Y9: Programmer | Z9: Exempt CAD | AB9: E18 | AC9: E18 | AD9: AUD | AE9: 100000 | AF9: 100000 | AG9: 3 | AH9: Good | AI9: 42700 | AJ9: 61000 | AK9: 79300 | AL9: Q4 | AM9: Q4 | AO9: 5000 | AQ9: 30 | AR9: 40 | AS9: 20 | AT9: PNL meeting
A10: 2003 | B10: 2003 | C10: Thompson, Glenn | D10: Thompson, Glenn | E10: P/R Specialist | F10: Operations( | G10: t | J10: Weekly | L10: Active | M10: 45767 | N10: 45767 | O10: s | P10: s | Q10: Red | R10: Ward Jr Lloyd | S10: Ward Jr Lloyd | T10: 80 | U10: Jackson, Charmain | V10: 80 | W10: Jackson, Charmain | X10: J009 | Y10: Programmer | Z10: Exempt CAD | AB10: E18 | AC10: E18 | AD10: AUD | AE10: 100000 | AF10: 100000 | AG10: 3 | AH10: Superior | AI10: 42700 | AJ10: 61000 | AK10: 79300 | AL10: Q1 | AM10: Q1 | AO10: 5000 | AQ10: 30 | AR10: 40 | AS10: 20 | AT10: PNL meeting
A11: 2011 | B11: 2011 | C11: Van Buskirk, Briañ | D11: Van Buskirk, Briañ | E11: Administrative Assistant I | F11: Administration) | G11: T | J11: Quaterly | L11: Active | M11: 45767 | N11: 45767 | O11: 2001 | P11: 2001 | Q11: Blond | R11: Ward Jr Lloyd | S11: Ward Jr Lloyd | T11: 80 | U11: Jackson, Charmain | V11: 80 | W11: Jackson, Charmain | X11: J010 | Y11: Programmer | Z11: Exempt CAD | AB11: E18 | AC11: E18 | AD11: AUD | AE11: 100000 | AF11: 100000 | AG11: 5 | AH11: Exceptional | AI11: 42700 | AJ11: 61000 | AK11: 79300 | AL11: Q2 | AM11: Q2 | AO11: 5000 | AQ11: 30 | AR11: 40 | AS11: 20 | AT11: PNL meeting
A12: 2012 | B12: 2012 | C12: Waguespack, Briañ | D12: Waguespack, Briañ | E12: Administrative Assistant III_ | F12: Administration_ | G12: T | J12: Half Year | L12: Active | M12: 45767 | N12: 45767 | O12: 2001 | P12: 2001 | Q12: Black | R12: Ward Jr Lloyd | S12: Ward Jr Lloyd | T12: 80 | U12: Jackson, Charmain | V12: 80 | W12: Jackson, Charmain | X12: J011 | Y12: Programmer | Z12: Exempt CAD | AB12: E18 | AC12: E18 | AD12: CAD | AE12: 100000 | AF12: 100000 | AG12: 4 | AH12: Superior | AI12: 42700 | AJ12: 61000 | AK12: 79300 | AL12: Q3 | AM12: Q3 | AO12: 5000 | AQ12: 30 | AR12: 40 | AS12: 20 | AT12: PNL meeting
A13: 2013 | B13: 2013 | C13: Yokay, James | D13: Yokay, James | E13: Director of Nursing- | F13: Operations- | G13: ON | J13: Annually | L13: Active | M13: 45767 | N13: 45767 | O13: 4545 | P13: 4545 | Q13: Grey | R13: Asif Nawaz | S13: Asif Nawaz | T13: 80 | U13: Jackson, Charmain | V13: 80 | W13: Jackson, Charmain | X13: J012 | Y13: Programmer | Z13: Exempt CAD | AB13: E18 | AC13: E18 | AD13: CAD | AE13: 100000 | AF13: 100000 | AG13: 4 | AH13: Superior | AI13: 42700 | AJ13: 61000 | AK13: 79300 | AL13: Q4 | AM13: Q4 | AO13: 5000 | AQ13: 30 | AR13: 40 | AS13: 20 | AT13: PNL meeting
A14: 94 | B14: 94 | C14: Atkinson, Tracey | D14: Atkinson, Tracey | E14: Programmer | F14: Technology+ | G14: ON | J14: Annually (1yr) | L14: Active | M14: 45767 | N14: 45767 | O14: 72 | P14: 72 | Q14: White | R14: Davis Beverly | S14: Davis Beverly | T14: 80 | U14: Jackson, Charmain | V14: 80 | W14: Jackson, Charmain | X14: J013 | Y14: Certified Nurse Aide | Z14: Exempt US | AB14: E06 | AC14: E06 | AD14: USD | AE14: 100000 | AF14: 100000 | AH14: Exceptional | AI14: 14000 | AJ14: 18600 | AK14: 22800 | AL14: Q1 | AM14: Q1 | AO14: 5000 | AQ14: 30 | AR14: 40 | AS14: 20 | AT14: Qasand meeting
A15: 73 | B15: 73 | C15: Bonamy, James | D15: Bonamy, James | E15: Accountant | F15: Accounting= | G15: on | J15: Monthly (12) | L15: Active | M15: 45767 | N15: 45767 | O15: 72 | P15: 72 | Q15: Red | R15: Davis Beverly | S15: Davis Beverly | T15: 80 | U15: Jackson, Charmain | V15: 80 | W15: Jackson, Charmain | X15: J014 | Y15: Sales/Marketing Manager | Z15: Exempt US | AB15: E30 | AC15: E30 | AD15: USD | AE15: 100000 | AF15: 100000 | AH15: Needs Improvement | AI15: 81000 | AJ15: 135000 | AK15: 189000 | AL15: Q2 | AM15: Q2 | AO15: 5000 | AQ15: 30 | AR15: 40 | AS15: 0 | AT15: Qasand meeting
A16: 88 | B16: 88 | C16: Brooks, Wendy | D16: Brooks, Wendy | E16: Bookkeeper | F16: Accounting{ | G16: ON | J16: Monthly | L16: Active | M16: 45767 | N16: 45767 | O16: 72 | P16: 72 | Q16: Red | R16: Davis Beverly | S16: Davis Beverly | T16: 80 | U16: Jackson, Charmain | V16: 80 | W16: Jackson, Charmain | X16: J015 | Y16: RN | Z16: Exempt US | AB16: E12 | AC16: E12 | AD16: USD | AE16: 100000 | AF16: 100000 | AG16: 3 | AH16: Good | AI16: 23700 | AJ16: 31500 | AK16: 39400 | AL16: Q3 | AM16: Q3 | AO16: 5000 | AQ16: 30 | AR16: 40 | AS16: 0 | AT16: Qasand meeting
A17: 91 | B17: 91 | C17: Brown, Leann | D17: Brown, Leann | E17: Development Manager | F17: Technology} | G17: on | J17: Hourly Basis | L17: Active | M17: 45767 | N17: 45767 | O17: 72 | P17: 72 | Q17: s | R17: Davis Beverly | S17: Davis Beverly | T17: 80 | U17: Jackson, Charmain | V17: 80 | W17: Jackson, Charmain | X17: J016 | Y17: LVN | Z17: Exempt US | AB17: E10 | AC17: E10 | AD17: USD | AE17: 100000 | AF17: 100000 | AG17: 3 | AH17: Good | AI17: 8000 | AJ17: 12000 | AK17: 12000 | AL17: Q4 | AM17: Q4 | AO17: 5000 | AQ17: 30 | AR17: 40 | AS17: 0 | AT17: Qasand meeting
A18: 92 | B18: 92 | C18: Craven, Liz | D18: Craven, Liz | E18: Executive Administrative Assistant | F18: Administration[ | G18: on | J18: Hourly | L18: Active | M18: 45767 | N18: 45767 | O18: 72 | P18: 72 | Q18: Brown | R18: Davis Beverly | S18: Davis Beverly | T18: 80 | U18: Jackson, Charmain | V18: 80 | W18: Jackson, Charmain | X18: J017 | Y18: LVN | Z18: Exempt US | AB18: E10 | AC18: E10 | AD18: USD | AE18: 100000 | AF18: 100000 | AG18: 3 | AH18: Good | AI18: 8000 | AJ18: 12000 | AK18: 12000 | AL18: Q1 | AM18: Q1 | AO18: 5000 | AQ18: 30 | AR18: 40 | AS18: 50 | AT18: Qasand meeting
A19: 111 | B19: 111 | C19: Galvan, Dina | D19: Galvan, Dina | E19: Project Manager | F19: Operations] | G19: on | J19: Monthly (13) | L19: Active | M19: 45767 | N19: 45767 | O19: 72 | P19: 72 | Q19: Red | R19: Davis Beverly | S19: Davis Beverly | T19: 80 | U19: Jackson, Charmain | V19: 80 | W19: Jackson, Charmain | X19: J018 | Y19: Certified Nurse Aide | Z19: Exempt US | AB19: E06 | AC19: E06 | AD19: USD | AE19: 100000 | AF19: 100000 | AG19: 1 | AH19: Poor | AI19: 14000 | AJ19: 18600 | AK19: 22800 | AL19: Q2 | AM19: Q2 | AO19: 5000 | AQ19: 30 | AR19: 40 | AS19: 50 | AT19: Qasand meeting
A20: 110 | B20: 110 | C20: Harrison, Cindy | D20: Harrison, Cindy | E20: Sr. Accountant | F20: Accounting| | G20: on | J20: 13 Months | L20: Active | M20: 45767 | N20: 45767 | O20: 72 | P20: 72 | Q20: Blond | R20: Davis Beverly | S20: Davis Beverly | T20: 80 | U20: Jackson, Charmain | V20: 80 | W20: Jackson, Charmain | X20: J019 | Y20: Certified Nurse Aide | Z20: Exempt US | AB20: E06 | AC20: E06 | AD20: USD | AE20: 100000 | AF20: 100000 | AG20: 3 | AH20: Good | AI20: 14000 | AJ20: 18600 | AK20: 22800 | AL20: Q3 | AM20: Q3 | AO20: 5000 | AQ20: 30 | AR20: 40 | AS20: 50 | AT20: Qasand meeting
A21: 95 | B21: 95 | C21: Henshaw, Candice | D21: Henshaw, Candice | E21: Human Resource Manager | F21: Human Resources\ | G21: on | J21: Weekly | L21: Active | M21: 45767 | N21: 45767 | O21: 72 | P21: 72 | Q21: Black | R21: Davis Beverly | S21: Davis Beverly | T21: 80 | U21: Jackson, Charmain | V21: 80 | W21: Jackson, Charmain | X21: J020 | Y21: Certified Nurse Aide | Z21: Exempt US | AB21: E06 | AC21: E06 | AD21: IDR | AE21: 100000 | AF21: 100000 | AG21: 3 | AH21: Good | AI21: 14000 | AJ21: 18600 | AK21: 22800 | AL21: Q4 | AM21: Q4 | AO21: 5000 | AQ21: 30 | AR21: 40 | AS21: 5.5 | AT21: Qasand meeting
A22: 80 | B22: 80 | C22: Jackson, Charmain | D22: Jackson, Charmain | E22: Sales/Marketing Manager | F22: Marketing : | G22: YES | J22: Quaterly | L22: Active | M22: 45767 | N22: 45767 | O22: 1113 | P22: 1113 | Q22: Black | R22: Davis Beverly | S22: Davis Beverly | T22: 80 | U22: Jackson, Charmain | V22: 80 | W22: Jackson, Charmain | X22: J021 | Y22: HR Coordinator | Z22: Exempt US | AB22: E14 | AC22: E14 | AD22: IDR | AE22: 100000 | AF22: 100000 | AG22: 1 | AH22: Poor | AI22: 29400 | AJ22: 42000 | AK22: 54600 | AL22: Q1 | AM22: Q1 | AO22: 5000 | AQ22: 30 | AR22: 40 | AS22: 5.5 | AT22: mikeco staf meeting
A23: 115 | B23: 115 | C23: Mathers, Paula | D23: Mathers, Paula | E23: IT Manager | F23: Technology ; | G23: YES | J23: Half Year | L23: Active | M23: 45767 | N23: 45767 | O23: 72 | P23: 72 | Q23: Brown | R23: Davis Beverly | S23: Davis Beverly | T23: 80 | U23: Jackson, Charmain | V23: 80 | W23: Jackson, Charmain | X23: J022 | Y23: Certified Nurse Aide | Z23: Exempt US | AB23: E06 | AC23: E06 | AD23: IDR | AE23: 100000 | AF23: 100000 | AG23: 3 | AH23: Good | AI23: 14000 | AJ23: 18600 | AK23: 22800 | AL23: Q2 | AM23: Q2 | AO23: 5000 | AQ23: 30 | AR23: 40 | AS23: 5.5 | AT23: mikeco staf meeting
A24: 93 | B24: 93 | C24: Mott, Michael | D24: Mott, Michael | E24: Controller' | F24: Accounting ' | G24: 1 | J24: Annually | L24: Active | M24: 45767 | N24: 45767 | O24: 72 | P24: 72 | Q24: White | R24: Davis Beverly | S24: Davis Beverly | T24: 80 | U24: Jackson, Charmain | V24: 80 | W24: Jackson, Charmain | X24: J023 | Y24: Certified Nurse Aide | Z24: Exempt US | AB24: E06 | AC24: E06 | AD24: IDR | AE24: 100000 | AF24: 100000 | AG24: 4 | AH24: Superior | AI24: 14000 | AJ24: 18600 | AK24: 22800 | AL24: Q3 | AM24: Q3 | AO24: 5000 | AQ24: 30 | AR24: 40 | AS24: 10 | AT24: mikeco staf meeting
A25: 101 | B25: 101 | C25: Napier, Alex | D25: Napier, Alex | E25: Director of HR | F25: Human Resources " | G25: 1 | J25: Annually (1yr) | L25: Active | M25: 45767 | N25: 45767 | O25: 72 | P25: 72 | Q25: Brown | R25: Davis Beverly | S25: Davis Beverly | T25: 80 | U25: Jackson, Charmain | V25: 80 | W25: Jackson, Charmain | X25: J024 | Y25: Certified Nurse Aide | Z25: Exempt US | AB25: E06 | AC25: E06 | AD25: IDR | AE25: 100000 | AF25: 100000 | AG25: 3 | AH25: Good | AI25: 14000 | AJ25: 18600 | AK25: 22800 | AL25: Q4 | AM25: Q4 | AO25: 5000 | AQ25: 30 | AR25: 40 | AS25: 10 | AT25: mikeco staf meeting
A26: 100 | B26: 100 | C26: Rames, Bill | D26: Rames, Bill | E26: Director of Operations | F26: Operations < | G26: 1 | J26: Monthly (12) | L26: Active | M26: 45767 | N26: 45767 | O26: 72 | P26: 72 | Q26: Black | R26: Davis Beverly | S26: Davis Beverly | T26: 80 | U26: Jackson, Charmain | V26: 80 | W26: Jackson, Charmain | X26: J025 | Y26: Certified Nurse Aide | Z26: Exempt US | AB26: E06 | AC26: E06 | AD26: IDR | AE26: 100000 | AF26: 100000 | AG26: 4 | AH26: Superior | AI26: 14000 | AJ26: 18600 | AK26: 22800 | AL26: Q1 | AM26: Q1 | AO26: 5000 | AQ26: 30 | AR26: 40 | AS26: 10 | AT26: mikeco staf meeting
A27: 104 | B27: 104 | C27: Risner, Elizabeth | D27: Risner, Elizabeth | E27: Director of Operations, | F27: Accounting, | G27: 0 | J27: Monthly | L27: Active | M27: 45767 | N27: 45767 | O27: 72 | P27: 72 | Q27: Brown | R27: Davis Beverly | S27: Davis Beverly | T27: 80 | U27: Jackson, Charmain | V27: 80 | W27: Jackson, Charmain | X27: J026 | Y27: Certified Nurse Aide | Z27: Exempt US | AB27: E06 | AC27: E06 | AD27: IDR | AE27: 100000 | AF27: 100000 | AG27: 2 | AH27: Needs Improvement | AI27: 14000 | AJ27: 18600 | AK27: 22800 | AL27: Q2 | AM27: Q2 | AO27: 5000 | AQ27: 30 | AR27: 40 | AS27: 10 | AT27: mikeco staf meeting
A28: 86 | B28: 86 | C28: Rogers, Mary | D28: Rogers, Mary | E28: Director of Operations | F28: Technology> | G28: N | J28: Hourly Basis | L28: Active | M28: 45767 | N28: 45767 | O28: 72 | P28: 72 | Q28: Brown | R28: Davis Beverly | S28: Davis Beverly | T28: 80 | U28: Jackson, Charmain | V28: 80 | W28: Jackson, Charmain | X28: J027 | Y28: Director of Nursing | Z28: Exempt US | AB28: E18 | AC28: E18 | AD28: IDR | AE28: 100000 | AF28: 100000 | AG28: 5 | AH28: Good | AI28: 42700 | AJ28: 61000 | AK28: 79300 | AL28: Q3 | AM28: Q3 | AO28: 5000 | AQ28: 30 | AR28: 40 | AS28: 10 | AT28: mikeco staf meeting
A29: 89 | B29: 89 | C29: White, Gordon | D29: White, Gordon | E29: Director of Operations | F29: Operations? | G29: N | J29: Hourly | L29: Active | M29: 45767 | N29: 45767 | O29: 72 | P29: 72 | Q29: Red | R29: Davis Beverly | S29: Davis Beverly | T29: 80 | U29: Jackson, Charmain | V29: 80 | W29: Jackson, Charmain | X29: J028 | Y29: RN | Z29: Exempt US | AB29: E12 | AC29: E12 | AD29: IDR | AE29: 100000 | AF29: 100000 | AG29: 4 | AH29: Superior | AI29: 23700 | AJ29: 31500 | AK29: 39400 | AL29: Q4 | AM29: Q4 | AO29: 5000 | AQ29: 30 | AR29: 40 | AS29: 10 | AT29: production staf
A30: 72 | B30: 72 | C30: Davis, Beverly | D30: Davis, Beverly | E30: Director of Operations/ | F30: Operations / | G30: n | J30: Monthly (13) | L30: Active | M30: 45767 | N30: 45767 | O30: 1012 | P30: 1012 | Q30: Blond | R30: Sherman Jack | S30: Sherman Jack | T30: 80 | U30: Jackson, Charmain | V30: 80 | W30: Jackson, Charmain | X30: J029 | Y30: Director of Operations | Z30: Exempt US | AB30: E34 | AC30: E34 | AD30: AED | AE30: 100000 | AF30: 100000 | AG30: 3 | AH30: Good | AI30: 112800 | AJ30: 188000 | AK30: 263200 | AL30: Q1 | AM30: Q1 | AO30: 5000 | AQ30: 30 | AR30: 40 | AS30: 10 | AT30: production staf
A31: 162 | B31: 162 | C31: Thompson, Calvin | D31: Thompson, Calvin | E31: Certified Doc Aide | F31: Accounting! | G31: n | J31: 13 Months | L31: Active | M31: 45767 | N31: 45767 | O31: BOD | P31: BOD | Q31: Black | R31: BOD | S31: BOD | T31: 80 | U31: Jackson, Charmain | V31: 80 | W31: Jackson, Charmain | X31: J001 | Y31: President/CEO | Z31: Exempt US | AB31: E40 | AC31: E40 | AD31: AED | AE31: 100000 | AF31: 100000 | AG31: 3 | AH31: Good | AI31: 192000 | AJ31: 320000 | AK31: 448000 | AL31: Q2 | AM31: Q2 | AO31: 5000 | AQ31: 30 | AR31: 40 | AS31: 10 | AT31: production staf
A32: 1121 | B32: 1121 | C32: Masters, Sarah | D32: Masters, Sarah | E32: Certified Nurse Aide | F32: Operations@ | G32: n | J32: Weekly | L32: Active | M32: 45767 | N32: 45767 | O32: 1113 | P32: 1113 | Q32: Black | R32: Duncan Sam | S32: Duncan Sam | T32: 80 | U32: Jackson, Charmain | V32: 80 | W32: Jackson, Charmain | X32: J002 | Y32: Director of Nursing | Z32: Exempt US | AB32: E18 | AC32: E18 | AD32: AED | AE32: 100000 | AF32: 100000 | AG32: 5 | AH32: Exceptional | AI32: 42700 | AJ32: 61000 | AK32: 79300 | AL32: Q3 | AM32: Q3 | AO32: 5000 | AQ32: 30 | AR32: 40 | AS32: 10 | AT32: production staf
A33: 1117 | B33: 1117 | C33: Ramsey, Richele | D33: Ramsey, Richele | E33: LVN | F33: Operations# | G33: NO | J33: Quaterly | L33: Active | M33: 45767 | N33: 45767 | O33: 1113 | P33: 1113 | Q33: Brown | R33: Duncan Sam | S33: Duncan Sam | T33: 80 | U33: Jackson, Charmain | V33: 80 | W33: Jackson, Charmain | X33: J003 | Y33: HR Coordinator/AA | Z33: Exempt US | AB33: E14 | AC33: E14 | AD33: AED | AE33: 100000 | AF33: 100000 | AG33: 5 | AH33: Exceptional | AI33: 29400 | AJ33: 42000 | AK33: 54600 | AL33: Q4 | AM33: Q4 | AO33: 5000 | AQ33: 30 | AR33: 40 | AS33: 10 | AT33: production staf
A34: 1115 | B34: 1115 | C34: Ross, Michael | D34: Ross, Michael | E34: RN | F34: Operations$ | G34: NO | J34: Half Year | L34: Active | M34: 45767 | N34: 45767 | O34: 1113 | P34: 1113 | Q34: Brown | R34: Duncan Sam | S34: Duncan Sam | T34: 80 | U34: Jackson, Charmain | V34: 80 | W34: Jackson, Charmain | X34: J004 | Y34: Sales/Marketing Manager | Z34: Exempt US | AB34: E30 | AC34: E30 | AD34: USD | AE34: 100000 | AF34: 100000 | AG34: 4 | AH34: Superior | AI34: 81000 | AJ34: 135000 | AK34: 189000 | AL34: Q1 | AM34: Q1 | AO34: 5000 | AQ34: 30 | AR34: 40 | AS34: 10 | AT34: production staf
A35: 1128 | B35: 1128 | C35: Hinze, Drea | D35: Hinze, Drea | E35: A/P Specialist | F35: Accounting% | G35: NO | J35: Annually | L35: Active | M35: 45767 | N35: 45767 | O35: 1121 | P35: 1121 | Q35: Black | R35: Masters Sarah | S35: Masters Sarah | T35: 80 | U35: Jackson, Charmain | V35: 80 | W35: Jackson, Charmain | X35: J005 | Y35: Certified Nurse Aide | Z35: Exempt US | AB35: E06 | AC35: E06 | AD35: AED | AE35: 100000 | AF35: 100000 | AG35: 3 | AH35: Good | AI35: 14000 | AJ35: 18600 | AK35: 22800 | AL35: Q2 | AM35: Q2 | AO35: 5000 | AQ35: 30 | AR35: 40 | AS35: 10 | AT35: production staf
A36: 1123 | B36: 1123 | C36: Jackson, Leah | D36: Jackson, Leah | E36: A/R Specialist-Billing | F36: Accounting^ | G36: no | J36: Annually (1yr) | L36: Active | M36: 45767 | N36: 45767 | O36: 1121 | P36: 1121 | Q36: Brown | R36: Masters Sarah | S36: Masters Sarah | T36: 80 | U36: Jackson, Charmain | V36: 80 | W36: Jackson, Charmain | X36: J006 | Y36: LVN | Z36: Exempt US | AB36: E10 | AC36: E10 | AD36: AED | AE36: 100000 | AF36: 100000 | AG36: 2 | AH36: Needs Improvement | AI36: 8000 | AJ36: 12000 | AK36: 12000 | AL36: Q3 | AM36: Q3 | AO36: 5000 | AQ36: 30 | AR36: 40 | AS36: 10 | AT36: production staf
A37: 70 | B37: 70 | C37: Kirklan, Richard | D37: Kirklan, Richard | E37: HR Coordinator& | F37: Human\ Resources& | G37: no | J37: Monthly (12) | L37: Active | M37: 45767 | N37: 45767 | O37: 1121 | P37: 1121 | Q37: Brown | R37: Masters Sarah | S37: Masters Sarah | T37: 1117 | U37: Ramsey, Richele | V37: 80 | W37: Jackson, Charmain | X37: J007 | Y37: Certified Nurse Aide | Z37: Exempt US | AB37: E06 | AC37: E06 | AD37: AED | AE37: 100000 | AF37: 100000 | AG37: 3 | AH37: Good | AI37: 14000 | AJ37: 18600 | AK37: 22800 | AL37: Q4 | AM37: Q4 | AO37: 5000 | AQ37: 30 | AR37: 40 | AS37: 10 | AT37: production staf
A38: 1119 | B38: 1119 | C38: Mills, Gavin | D38: Mills, Gavin | E38: HR Coordinator/AA | F38: Human Resources* | G38: no | J38: Monthly | L38: Active | M38: 45767 | N38: 45767 | O38: 1121 | P38: 1121 | Q38: Red | R38: Masters Sarah | S38: Masters Sarah | T38: 1117 | U38: Ramsey, Richele | V38: 80 | W38: Jackson, Charmain | X38: J008 | Y38: RN | Z38: Exempt US | AB38: E12 | AC38: E12 | AD38: GBP | AE38: 100000 | AF38: 100000 | AG38: 3 | AH38: Good | AI38: 23700 | AJ38: 31500 | AK38: 39400 | AL38: Q1 | AM38: Q1 | AO38: 5000 | AQ38: 30 | AR38: 40 | AS38: 10 | AT38: production staf
A39: 1118 | B39: 1118 | C39: Perez, Leila | D39: Perez, Leila | E39: P/R Specialist | F39: Operations( | G39: OFF | J39: Hourly Basis | L39: Active | M39: 45767 | N39: 45767 | O39: 1121 | P39: 1121 | Q39: Blond | R39: Masters Sarah | S39: Masters Sarah | T39: 1117 | U39: Ramsey, Richele | V39: 80 | W39: Jackson, Charmain | X39: J009 | Y39: RN | Z39: Exempt US | AB39: E12 | AC39: E12 | AD39: GBP | AE39: 100000 | AF39: 100000 | AG39: 3 | AH39: Good | AI39: 23700 | AJ39: 31500 | AK39: 39400 | AL39: Q2 | AM39: Q2 | AO39: 5000 | AQ39: 30 | AR39: 40 | AS39: 10 | AT39: production staf
A40: 59 | B40: 59 | C40: Sanders, Lynn | D40: Sanders, Lynn | E40: Administrative Assistant I | F40: Administration) | G40: OFF | J40: Hourly | L40: Active | M40: 45767 | N40: 45767 | O40: 1121 | P40: 1121 | Q40: Black | R40: Masters Sarah | S40: Masters Sarah | T40: 1117 | U40: Ramsey, Richele | V40: 80 | W40: Jackson, Charmain | X40: J010 | Y40: Certified Nurse Aide | Z40: Exempt US | AB40: E06 | AC40: E06 | AD40: GBP | AE40: 100000 | AF40: 100000 | AG40: 4 | AH40: Superior | AI40: 14000 | AJ40: 18600 | AK40: 22800 | AL40: Q3 | AM40: Q3 | AO40: 5000 | AQ40: 30 | AR40: 40 | AS40: 10 | AT40: production staf
A41: 1127 | B41: 1127 | C41: Tanya, Field | D41: Tanya, Field | E41: Administrative Assistant III_ | F41: Administration_ | G41: OFF | J41: Monthly (13) | L41: Active | M41: 45767 | N41: 45767 | O41: 1121 | P41: 1121 | Q41: Black | R41: Masters Sarah | S41: Masters Sarah | T41: 1117 | U41: Ramsey, Richele | V41: 80 | W41: Jackson, Charmain | X41: J011 | Y41: Certified Nurse Aide | Z41: Exempt US | AB41: E06 | AC41: E06 | AD41: GBP | AE41: 100000 | AF41: 100000 | AG41: 4 | AH41: Superior | AI41: 14000 | AJ41: 18600 | AK41: 22800 | AL41: Q4 | AM41: Q4 | AO41: 5000 | AQ41: 30 | AR41: 40 | AS41: 10 | AT41: production staf
A42: 1132 | B42: 1132 | C42: Tso, Ann | D42: Tso, Ann | E42: Director of Nursing- | F42: Operations- | G42: off | J42: 13 Months | L42: Active | M42: 45767 | N42: 45767 | O42: 1121 | P42: 1121 | Q42: Brown | R42: Masters Sarah | S42: Masters Sarah | T42: 1117 | U42: Ramsey, Richele | V42: 80 | W42: Jackson, Charmain | X42: J012 | Y42: Certified Nurse Aide | Z42: Exempt CAD | AB42: E06 | AC42: E06 | AD42: GBP | AE42: 100000 | AF42: 100000 | AG42: 5 | AH42: Exceptional | AI42: 14000 | AJ42: 18600 | AK42: 22800 | AL42: Q1 | AM42: Q1 | AO42: 5000 | AQ42: 30 | AR42: 40 | AS42: 15 | AT42: production staf
A43: 1126 | B43: 1126 | C43: Ungaba, Naomi | D43: Ungaba, Naomi | E43: Programmer | F43: Technology+ | G43: off | J43: Weekly | L43: Active | M43: 45767 | N43: 45767 | O43: 1121 | P43: 1121 | Q43: Grey | R43: Masters Sarah | S43: Masters Sarah | T43: 1117 | U43: Ramsey, Richele | V43: 80 | W43: Jackson, Charmain | X43: J013 | Y43: Certified Nurse Aide | Z43: Exempt US | AB43: E06 | AC43: E06 | AD43: GBP | AE43: 100000 | AF43: 100000 | AG43: 4 | AH43: Superior | AI43: 14000 | AJ43: 18600 | AK43: 22800 | AL43: Q2 | AM43: Q2 | AO43: 5000 | AQ43: 30 | AR43: 40 | AS43: 15 | AT43: production staf
A44: 1125 | B44: 1125 | C44: Weddle, Valoria | D44: Weddle, Valoria | E44: Accountant | F44: Accounting= | G44: off | J44: Quaterly | L44: Active | M44: 45767 | N44: 45767 | O44: 1121 | P44: 1121 | Q44: Brown | R44: Masters Sarah | S44: Masters Sarah | T44: 1117 | U44: Ramsey, Richele | V44: 80 | W44: Jackson, Charmain | X44: J014 | Y44: LVN | Z44: Exempt US | AB44: E10 | AC44: E10 | AD44: GBP | AE44: 100000 | AF44: 100000 | AG44: 3 | AH44: Good | AI44: 8000 | AJ44: 12000 | AK44: 12000 | AL44: Q3 | AM44: Q3 | AO44: 5000 | AQ44: 30 | AR44: 40 | AS44: 15 | AT44: 1.5
A45: 167 | B45: 167 | C45: Ramos, Amy | D45: Ramos, Amy | E45: Bookkeeper | F45: Accounting{ | G45: F | J45: Half Year | L45: Active | M45: 45767 | N45: 45767 | O45: 166 | P45: 166 | Q45: Black | R45: Montana Joe | S45: Montana Joe | T45: 1117 | U45: Ramsey, Richele | V45: 80 | W45: Jackson, Charmain | X45: J015 | Y45: IT Manager | Z45: Exempt US | AB45: E32 | AC45: E32 | AD45: GBP | AE45: 100000 | AF45: 100000 | AG45: 4 | AH45: Superior | AI45: 94200 | AJ45: 157000 | AK45: 219800 | AL45: Q4 | AM45: Q4 | AO45: 5000 | AQ45: 30 | AR45: 40 | AS45: 15
A46: 168 | B46: 168 | C46: Soles, Nedra | D46: Soles, Nedra | E46: Development Manager | F46: Technology} | G46: F | J46: Annually | L46: Active | M46: 45767 | N46: 45767 | O46: 166 | P46: 166 | Q46: Brown | R46: Montana Joe | S46: Montana Joe | T46: 1117 | U46: Ramsey, Richele | V46: 80 | W46: Jackson, Charmain | X46: J016 | Y46: Controller | Z46: Exempt US | AB46: E34 | AC46: E34 | AD46: GBP | AE46: 100000 | AF46: 100000 | AG46: 3 | AH46: Good | AI46: 112800 | AJ46: 188000 | AK46: 263200 | AL46: Q1 | AM46: Q1 | AO46: 5000 | AQ46: 30 | AR46: 40 | AS46: 15
A47: 1113 | B47: 1113 | C47: Duncan, Sam | D47: Duncan, Sam | E47: Executive Administrative Assistant | F47: Administration[ | G47: F | J47: Annually (1yr) | L47: Active | M47: 45767 | N47: 45767 | O47: 1012 | P47: 1012 | Q47: Brown | R47: Sherman Jack | S47: Sherman Jack | T47: 1117 | U47: Ramsey, Richele | V47: 80 | W47: Jackson, Charmain | X47: J017 | Y47: Director of Operations | Z47: Exempt US | AB47: E34 | AC47: E34 | AD47: BRL | AE47: 100000 | AF47: 100000 | AG47: 3 | AH47: Good | AI47: 112800 | AJ47: 188000 | AK47: 263200 | AL47: Q2 | AM47: Q2 | AO47: 5000 | AQ47: 30 | AR47: 40 | AS47: 15
A48: 1028 | B48: 1028 | C48: Resendez, MiMi | D48: Resendez, MiMi | E48: Project Manager | F48: Operations] | G48: f | J48: Monthly (12) | L48: Active | M48: 45767 | N48: 45767 | O48: 1012 | P48: 1012 | Q48: Red | R48: Sherman Jack | S48: Sherman Jack | T48: 1117 | U48: Ramsey, Richele | V48: 80 | W48: Jackson, Charmain | X48: J018 | Y48: Administrative Assistant | Z48: Exempt US | AB48: E20 | AC48: E20 | AD48: BRL | AE48: 100000 | AF48: 100000 | AG48: 3 | AH48: Good | AI48: 48100 | AJ48: 74000 | AK48: 99900 | AL48: Q3 | AM48: Q3 | AO48: 5000 | AQ48: 30 | AR48: 40 | AS48: 15
A49: 1010 | B49: 1010 | C49: Tucker, Darla | D49: Tucker, Darla | E49: Sr. Accountant | F49: Accounting| | G49: f | J49: Monthly | L49: Active | M49: 45767 | N49: 45767 | O49: 1012 | P49: 1012 | Q49: Blond | R49: Sherman Jack | S49: Sherman Jack | T49: 1117 | U49: Ramsey, Richele | V49: 80 | W49: Jackson, Charmain | X49: J019 | Y49: Director of HR | Z49: Exempt US | AB49: E34 | AC49: E34 | AD49: BRL | AE49: 100000 | AF49: 100000 | AG49: 4 | AH49: Superior | AI49: 112800 | AJ49: 188000 | AK49: 263200 | AL49: Q4 | AM49: Q4 | AO49: 5000 | AQ49: 30 | AR49: 40 | AS49: 15
A50: 175 | B50: 175 | C50: Anderson, Ann | D50: Anderson, Ann | E50: Human Resource Manager | F50: Human Resources\ | G50: f | I50: French | J50: Hourly Basis | M50: 45767 | N50: 45767 | O50: 168 | P50: 168 | Q50: Black | R50: Soles Nedra | S50: Soles Nedra | X50: J020 | Y50: Sr. Accountant | Z50: Exempt US | AB50: E22 | AC50: E22 | AE50: 100000 | AF50: 100000 | AH50: Superior | AI50: 53300 | AJ50: 82000 | AK50: 110700 | AL50: Q1 | AM50: Q1 | AO50: 5000 | AQ50: 30 | AR50: 40 | AS50: 15
A51: 176 | B51: 176 | C51: Bishop, Julie | D51: Bishop, Julie | E51: Sales/Marketing Manager | F51: Marketing : | G51: FALSE | I51: French | J51: Hourly | M51: 45767 | N51: 45767 | O51: 168 | P51: 168 | Q51: Red | R51: Soles Nedra | S51: Soles Nedra | X51: J021 | Y51: Accountant | Z51: Exempt US | AB51: E20 | AC51: E20 | AE51: 100000 | AF51: 100000 | AH51: Superior | AI51: 48100 | AJ51: 74000 | AK51: 99900 | AL51: Q2 | AM51: Q2 | AO51: 5000 | AQ51: 30 | AR51: 40 | AS51: 15
A52: 172 | B52: 172 | C52: Burke, Mia | D52: Burke, Mia | E52: IT Manager | F52: Technology ; | G52: y | J52: Monthly (13) | L52: Active | M52: 45767 | N52: 45767 | O52: 168 | P52: 168 | Q52: Red | R52: Soles Nedra | S52: Soles Nedra | T52: 1117 | U52: Ramsey, Richele | V52: 80 | W52: Jackson, Charmain | X52: J022 | Y52: P/R Specialist | Z52: Exempt US | AB52: E14 | AC52: E14 | AD52: BRL | AE52: 100000 | AF52: 100000 | AG52: 4 | AH52: Superior | AI52: 29400 | AJ52: 42000 | AK52: 54600 | AL52: Q3 | AM52: Q3 | AO52: 5000 | AQ52: 30 | AR52: 40 | AS52: 15
A53: 174 | B53: 174 | C53: Carillo, Frank | D53: Carillo, Frank | E53: Controller' | F53: Accounting ' | G53: Y | J53: 13 Months | L53: Active | M53: 45767 | N53: 45767 | O53: 168 | P53: 168 | Q53: Brown | R53: Soles Nedra | S53: Soles Nedra | T53: 1117 | U53: Ramsey, Richele | V53: 80 | W53: Jackson, Charmain | X53: J023 | Y53: A/R Specialist-Billing | Z53: Exempt US | AB53: E14 | AC53: E14 | AD53: BRL | AE53: 100000 | AF53: 100000 | AG53: 4 | AH53: Superior | AI53: 29400 | AJ53: 42000 | AK53: 54600 | AL53: Q4 | AM53: Q4 | AO53: 5000 | AQ53: 30 | AR53: 40 | AS53: 15
A54: 170 | B54: 170 | C54: Carter, Frank | D54: Carter, Frank | E54: Director of HR | F54: Human Resources " | G54: FALSE | J54: Weekly | L54: Active | M54: 45767 | N54: 45767 | O54: 168 | P54: 168 | Q54: Black | R54: Soles Nedra | S54: Soles Nedra | T54: 1117 | U54: Ramsey, Richele | V54: 80 | W54: Jackson, Charmain | X54: J024 | Y54: A/P Specialist | Z54: Exempt US | AB54: E14 | AC54: E14 | AD54: BRL | AE54: 100000 | AF54: 100000 | AG54: 4 | AH54: Superior | AI54: 29400 | AJ54: 42000 | AK54: 54600 | AL54: Q1 | AM54: Q1 | AO54: 5000 | AQ54: 30 | AR54: 40 | AS54: 15
A55: 177 | B55: 177 | C55: Pope, Ian | D55: Pope, Ian | E55: Director of Operations | F55: Operations < | G55: FALSE | J55: Quaterly | L55: Active | M55: 45767 | N55: 45767 | O55: 168 | P55: 168 | Q55: Brown | R55: Soles Nedra | S55: Soles Nedra | T55: 1117 | U55: Ramsey, Richele | V55: 80 | W55: Jackson, Charmain | X55: J025 | Y55: Bookkeeper | Z55: Exempt US | AB55: E20 | AC55: E20 | AD55: USD | AE55: 100000 | AF55: 100000 | AG55: 4 | AH55: Superior | AI55: 48100 | AJ55: 74000 | AK55: 99900 | AL55: Q2 | AM55: Q2 | AO55: 5000 | AQ55: 30 | AR55: 40 | AS55: 15
A56: 161 | B56: 161 | C56: Butler, Cathy | D56: Butler, Cathy | E56: Director of Operations, | F56: Accounting, | G56: FALSE | J56: Half Year | L56: Active | M56: 45767 | N56: 45767 | O56: 162 | P56: 162 | Q56: Red | R56: Thompson Calvin | S56: Thompson Calvin | T56: 1117 | U56: Ramsey, Richele | V56: 80 | W56: Jackson, Charmain | X56: J026 | Y56: Bookkeeper | Z56: Exempt US | AB56: E20 | AC56: E20 | AD56: USD | AE56: 100000 | AF56: 100000 | AG56: 3 | AH56: Good | AI56: 48100 | AJ56: 74000 | AK56: 99900 | AL56: Q3 | AM56: Q3 | AO56: 5000 | AQ56: 30 | AR56: 40 | AS56: 15
A57: 166 | B57: 166 | C57: Montana, Joe | D57: Montana, Joe | E57: Director of Operations | F57: Technology> | G57: FALSE' | J57: Annually | L57: Active | M57: 45767 | N57: 45767 | O57: 162 | P57: 162 | Q57: Red | R57: Thompson Calvin | S57: Thompson Calvin | T57: 1117 | U57: Ramsey, Richele | V57: 80 | W57: Jackson, Charmain | X57: J027 | Y57: CFO/ Senior VP Finance | Z57: Exempt US | AB57: E38 | AC57: E38 | AD57: USD | AE57: 100000 | AF57: 100000 | AG57: 3 | AH57: Good | AI57: 177000 | AJ57: 288000 | AK57: 391000 | AL57: Q4 | AM57: Q4 | AO57: 5000 | AQ57: 30 | AR57: 40 | AS57: 15
A58: 1012 | B58: 1012 | C58: Sherman, Jack | D58: Sherman, Jack | E58: Director of Operations | F58: Operations? | G58: FALSE@ | J58: Annually (1yr) | L58: Active | M58: 45767 | N58: 45767 | O58: 162 | P58: 162 | Q58: Blond | R58: Thompson Calvin | S58: Thompson Calvin | T58: 1117 | U58: Ramsey, Richele | V58: 80 | W58: Jackson, Charmain | X58: J028 | Y58: Executive VP of Operations | Z58: Exempt US | AB58: E38 | AC58: E38 | AD58: USD | AE58: 100000 | AF58: 100000 | AG58: 3 | AH58: Poor | AI58: 177000 | AJ58: 288000 | AK58: 391000 | AL58: Q1 | AM58: Q1 | AO58: 5000 | AQ58: 30 | AR58: 40 | AS58: 15
A59: 1043 | B59: 1043 | C59: Burke, Michelle | D59: Burke, Michelle | E59: Director of Operations/ | F59: Operations / | G59: 9 | J59: Monthly (12) | L59: Active | M59: 45767 | N59: 45767 | O59: 1010 | P59: 1010 | Q59: Red | R59: Tucker Darla | S59: Tucker Darla | T59: 1117 | U59: Ramsey, Richele | V59: 80 | W59: Jackson, Charmain | X59: J029 | Y59: Administrative Assistant | AA59: Brazil | AB59: E21 | AC59: E21 | AD59: BRL | AE59: 100000 | AF59: 100000 | AG59: 4 | AH59: Superior | AI59: 36200 | AJ59: 51600 | AK59: 67100 | AL59: Q2 | AM59: Q2 | AO59: 5000 | AQ59: 30 | AR59: 40 | AS59: 15
A60: 1114 | B60: 1114 | C60: Sampson, DeDe | D60: Sampson, DeDe | E60: Certified Doc Aide | F60: Accounting! | G60: 8 | J60: Monthly | L60: Active | M60: 45767 | N60: 45767 | O60: 1010 | P60: 1010 | Q60: Black | R60: Tucker Darla | S60: Tucker Darla | T60: 1117 | U60: Ramsey, Richele | V60: 80 | W60: Jackson, Charmain | X60: J001 | Y60: Administrative Assistant | AA60: Australian | AB60: E21 | AC60: E21 | AD60: AUD | AE60: 100000 | AF60: 100000 | AG60: 3 | AH60: Good | AI60: 74400 | AJ60: 124000 | AK60: 173600 | AL60: Q3 | AM60: Q3 | AO60: 5000 | AQ60: 30 | AR60: 40 | AS60: 15
A61: 2168 | B61: 2168 | C61: Citrus, Susan | D61: Citrus, Susan | E61: Certified Nurse Aide | F61: Operations@ | G61: %$ | J61: Hourly Basis | L61: Active | M61: 45767 | N61: 45767 | O61: 2166 | P61: 2166 | Q61: Brown | R61: Tea Green | S61: Tea Green | T61: 1117 | U61: Ramsey, Richele | V61: 80 | W61: Jackson, Charmain | X61: J002 | Y61: Administrative Assistant | AA61: Europe | AB61: E20 | AC61: E20 | AD61: EUR | AE61: 100000 | AF61: 100000 | AG61: 4 | AH61: Superior | AI61: 48100 | AJ61: 74000 | AK61: 99900 | AL61: Q4 | AM61: Q4 | AO61: 5000 | AQ61: 30 | AR61: 40 | AS61: 5.5
A62: 2167 | B62: 2167 | C62: Flavors, Natural | D62: Flavors, Natural | E62: LVN | F62: Operations# | G62: g | J62: Hourly | L62: Active | M62: 45767 | N62: 45767 | O62: 2166 | P62: 2166 | Q62: Black | R62: Tea Green | S62: Tea Green | T62: 1117 | U62: Ramsey, Richele | V62: 80 | W62: Jackson, Charmain | X62: J003 | Y62: Administrative Assistant | AA62: Australian | AB62: E20 | AC62: E20 | AD62: AUD | AE62: 100000 | AF62: 100000 | AG62: 3 | AH62: Good | AI62: 48100 | AJ62: 74000 | AK62: 99900 | AL62: Q1 | AM62: Q1 | AO62: 5000 | AQ62: 30 | AR62: 40 | AS62: 50
A63: 2000 | B63: 2000 | C63: Tompkins, Brian | D63: Tompkins, Brian | E63: RN | F63: Operations$ | G63: s | J63: Monthly (13) | L63: Active | M63: 45767 | N63: 45767 | O63: 2166 | P63: 2166 | Q63: Black | R63: Tea Green | S63: Tea Green | T63: 1117 | U63: Ramsey, Richele | V63: 80 | W63: Jackson, Charmain | X63: J004 | Y63: Project Manager | AA63: Brazil | AB63: E20 | AC63: E20 | AD63: BRL | AE63: 100000 | AF63: 100000 | AG63: 5 | AH63: Exceptional | AI63: 48100 | AJ63: 74000 | AK63: 99900 | AL63: Q2 | AM63: Q2 | AO63: 5000 | AQ63: 30 | AR63: 40 | AS63: 5.5
A64: 2001 | B64: 2001 | C64: Ward Jr, Lloyd | D64: Ward Jr, Lloyd | E64: A/P Specialist | F64: Accounting% | J64: 13 Months | L64: Active | M64: 45767 | N64: 45767 | O64: 2166 | P64: 2166 | Q64: Brown | R64: Tea Green | S64: Tea Green | T64: 1117 | U64: Ramsey, Richele | V64: 80 | W64: Jackson, Charmain | X64: J005 | Y64: Development Manager | AA64: Indonesia | AB64: E20 | AC64: E20 | AD64: IDR | AE64: 100000 | AF64: 100000 | AG64: 4 | AH64: Superior | AI64: 48100 | AJ64: 74000 | AK64: 99900 | AL64: Q3 | AM64: Q3 | AO64: 5000 | AQ64: 30 | AR64: 40 | AS64: 0
A65: 2166 | B65: 2166 | C65: Tea, Green | D65: Tea, Green | E65: A/R Specialist-Billing | F65: Accounting^ | G65: FALSE | J65: Weekly | L65: Active | M65: 45767 | N65: 45767 | O65: 162 | P65: 162 | Q65: Black | R65: Thompson Calvin | S65: Thompson Calvin | T65: 1117 | U65: Ramsey, Richele | V65: 80 | W65: Jackson, Charmain | X65: J006 | Y65: CIO/ Senior VP Information Technology | AA65: UAE | AB65: E20 | AC65: E20 | AD65: AED | AE65: 100000 | AF65: 100000 | AG65: 4 | AH65: Superior | AI65: 42700 | AJ65: 61000 | AK65: 79300 | AL65: Q4 | AM65: Q4 | AO65: 5000 | AQ65: 30 | AR65: 40 | AS65: 20
A66: 2404 | B66: 2404 | C66: Suleman, Muhammad | D66: Suleman, Muhammad | E66: HR Coordinator& | F66: Human\ Resources& | G66: FALSE | J66: Quaterly | L66: Active | M66: 45767 | N66: 45767 | O66: 162 | P66: 162 | Q66: Black | R66: Thompson Calvin | S66: Thompson Calvin | T66: 1117 | U66: Ramsey, Richele | V66: 80 | W66: Jackson, Charmain | X66: J007 | Y66: CIO/ Senior VP Information Technology | AA66: UAE | AB66: E20 | AC66: E20 | AD66: AED | AE66: 100000 | AF66: 100000 | AG66: 4 | AH66: Superior | AI66: 42700 | AJ66: 61000 | AK66: 79300 | AL66: Q4 | AM66: Q4 | AO66: 5000 | AQ66: 30 | AR66: 40 | AS66: 20

Sheet Employee Bonus Plans
A1: Employee Id | B1: Emp Id | C1: Name | D1: Bonus Plan Name | E1: Employee Name | F1: Prorated Bonus Mult Pct | G1: Mgr Emp Id | H1: Manager Name | I1: Plan Mgr Emp Id | J1: Plan Mgr Emp Name | K1: Salary | L1: Eligible Earnings | M1: Base Amount | N1: Bonus Calc Base Amt | O1: Currency Code | P1: Bonus From Date | Q1: Bonus To Date | S1: Proration % | T1: Bonus Target | U1: Tgt Opp Pct | V1: Target % | W1: Tgt Opp Amt | X1: Bonus Guar Min Amt | Y1: Bonus Guideline Min Amt | Z1: Bonus Guideline Tgt Amt | AA1: Bonus Guideline Max Amt | AB1: Prepaid Amt | AC1: Aziz Hair color | AD1: Bonus User Def 1 Amt | AE1: Job Title
A2: 2009 | B2: 2009 | C2: Grimm, Briañ | D2: B1 | E2: Grimm, Briañ | F2: 1 | G2: 72 | H2: Davis, Beverly | K2: 100000 | L2: 100000 | M2: 100000 | N2: 100000 | O2: AED | P2: 45767 | Q2: 46022 | S2: 1 | T2: 0.2 | U2: 0.2 | V2: 0.2 | W2: 40000 | Y2: 15000 | Z2: 30000 | AA2: 45000 | AB2: 5000 | AC2: White | AD2: 10 | AE2: Software engineer/XXXX
A3: 2004 | B3: 2004 | C3: Janish, Betty | D3: B1 | E3: Janish, Betty | F3: 1 | G3: 72 | H3: Davis, Beverly | K3: 100000 | L3: 100000 | M3: 100000 | N3: 100000 | O3: AED | P3: 45767 | Q3: 46022 | S3: 1 | T3: 0.2 | U3: 0.2 | V3: 0.2 | W3: 40000 | X3: 15000 | Y3: 15000 | Z3: 30000 | AA3: 45000 | AB3: 5000 | AC3: White | AD3: 11 | AE3: Software engineer/XXXX
A4: 2002 | B4: 2002 | C4: Keeling, Larry | D4: B1 | E4: Keeling, Larry | F4: 1 | G4: 72 | H4: Davis, Beverly | K4: 100000 | L4: 100000 | M4: 100000 | N4: 100000 | O4: AED | P4: 45767 | Q4: 46022 | S4: 1 | T4: 0.2 | U4: 0.2 | V4: 0.2 | W4: 40000 | Y4: 15000 | Z4: 30000 | AA4: 45000 | AB4: 5000 | AC4: White | AD4: 12 | AE4: Software engineer/XXXX
A5: 2008 | B5: 2008 | C5: Krendick Jasoñ | D5: B1 | E5: Krendick Jasoñ | F5: 1 | G5: 72 | H5: Davis, Beverly | K5: 100000 | L5: 100000 | M5: 100000 | N5: 100000 | O5: AED | P5: 45767 | Q5: 46022 | S5: 1 | T5: 0.2 | U5: 0.2 | V5: 0.2 | W5: 40000 | Y5: 15000 | Z5: 30000 | AA5: 45000 | AB5: 5000 | AC5: White | AD5: 13 | AE5: Software engineer/XXXX
A6: 2005 | B6: 2005 | C6: Leonard, David | D6: B1 | E6: Leonard, David | F6: 1 | G6: 72 | H6: Davis, Beverly | K6: 100000 | L6: 100000 | M6: 100000 | N6: 100000 | O6: AED | P6: 45767 | Q6: 46022 | S6: 1 | T6: 0.2 | U6: 0.2 | V6: 0.2 | W6: 40000 | Y6: 15000 | Z6: 30000 | AA6: 45000 | AB6: 5000 | AC6: White | AD6: 14 | AE6: Software engineer/XXXX
A7: 2010 | B7: 2010 | C7: McFadden, Sarah | D7: B1 | E7: McFadden, Sarah | F7: 1 | G7: 72 | H7: Davis, Beverly | K7: 100000 | L7: 100000 | M7: 100000 | N7: 100000 | O7: AED | P7: 45767 | Q7: 46022 | S7: 1 | T7: 0.2 | U7: 0.2 | V7: 0.2 | W7: 40000 | Y7: 15000 | Z7: 30000 | AA7: 45000 | AB7: 5000 | AC7: White | AD7: 15 | AE7: Software engineer/XXXX
A8: 2007 | B8: 2007 | C8: Munshausen, Bruce | D8: B1 | E8: Munshausen, Bruce | F8: 1 | G8: 72 | H8: Davis, Beverly | K8: 100000 | L8: 100000 | M8: 100000 | N8: 100000 | O8: AED | P8: 45767 | Q8: 46022 | S8: 1 | T8: 0.2 | U8: 0.2 | V8: 0.2 | W8: 40000 | Y8: 15000 | Z8: 30000 | AA8: 45000 | AB8: 5000 | AC8: White | AD8: 16 | AE8: Software engineer/XXXX
A9: 2006 | B9: 2006 | C9: Nelson III, Shawn | D9: B1 | E9: Nelson III, Shawn | F9: 1 | G9: 72 | H9: Davis, Beverly | K9: 100000 | L9: 100000 | M9: 100000 | N9: 100000 | O9: AED | P9: 45767 | Q9: 46022 | S9: 1 | T9: 0.2 | U9: 0.2 | V9: 0.2 | W9: 40000 | X9: 25000 | Y9: 15000 | Z9: 30000 | AA9: 45000 | AB9: 5000 | AC9: White | AD9: 17 | AE9: Software engineer/XXXX
A10: 2003 | B10: 2003 | C10: Thompson, Glenn | D10: B1 | E10: Thompson, Glenn | F10: 1 | G10: 72 | H10: Davis, Beverly | K10: 100000 | L10: 100000 | M10: 100000 | N10: 100000 | O10: USD | P10: 45767 | Q10: 46022 | S10: 1 | T10: 0.2 | U10: 0.2 | V10: 0.2 | W10: 40000 | Y10: 15000 | Z10: 30000 | AA10: 45000 | AB10: 5000 | AC10: White | AD10: 18 | AE10: Software engineer/XXXX
A11: 2011 | B11: 2011 | C11: Van Buskirk, Briañ | D11: B1 | E11: Van Buskirk, Briañ | F11: 1 | G11: 72 | H11: Davis, Beverly | K11: 100000 | L11: 100000 | M11: 100000 | N11: 100000 | O11: USD | P11: 45767 | Q11: 46022 | S11: 1 | T11: 0.2 | U11: 0.2 | V11: 0.2 | W11: 40000 | Y11: 15000 | Z11: 30000 | AA11: 45000 | AB11: 5000 | AC11: White | AD11: 19 | AE11: Software engineer/XXXX
A12: 2012 | B12: 2012 | C12: Waguespack, Briañ | D12: B1 | E12: Waguespack, Briañ | F12: 1 | G12: 72 | H12: Davis, Beverly | K12: 100000 | L12: 100000 | M12: 100000 | N12: 100000 | O12: USD | P12: 45767 | Q12: 46022 | S12: 1 | T12: 0.2 | U12: 0.2 | V12: 0.2 | W12: 40000 | Y12: 15000 | Z12: 30000 | AA12: 45000 | AB12: 5000 | AC12: White | AD12: 20 | AE12: Software engineer/XXXX
A13: 2013 | B13: 2013 | C13: Yokay, James | D13: B1 | E13: Yokay, James | F13: 1 | K13: 100000 | L13: 100000 | M13: 100000 | N13: 100000 | O13: USD | P13: 45767 | Q13: 46022 | S13: 1 | T13: 0.2 | U13: 0.2 | V13: 0.2 | W13: 40000 | Y13: 15000 | Z13: 30000 | AA13: 45000 | AB13: 5000 | AC13: White | AD13: 21 | AE13: Software engineer/XXXX
A14: 94 | B14: 94 | C14: Atkinson, Tracey | D14: B1 | E14: Atkinson, Tracey | K14: 100000 | L14: 100000 | M14: 100000 | N14: 100000 | O14: USD | P14: 45767 | Q14: 46022 | T14: 0.2 | U14: 0.2 | V14: 0.2 | W14: 40000 | X14: 30000 | Y14: 15000 | Z14: 30000 | AA14: 45000 | AB14: 5000 | AC14: Black | AD14: 22 | AE14: Software engineer/XXXX
A15: 73 | B15: 73 | C15: Bonamy, James | D15: B1 | E15: Bonamy, James | F15: 1 | K15: 100000 | L15: 100000 | M15: 100000 | N15: 100000 | O15: USD | P15: 45767 | Q15: 46022 | S15: 1 | T15: 0.2 | U15: 0.2 | V15: 0.2 | W15: 40000 | Y15: 15000 | Z15: 30000 | AA15: 45000 | AB15: 5000 | AC15: Black | AD15: 23 | AE15: QA/xx
A16: 88 | B16: 88 | C16: Brooks, Wendy | D16: B1 | E16: Brooks, Wendy | F16: 1 | K16: 100000 | L16: 100000 | M16: 100000 | N16: 100000 | O16: USD | P16: 45767 | Q16: 46022 | S16: 1 | T16: 0.2 | U16: 0.2 | V16: 0.2 | W16: 40000 | Y16: 15000 | Z16: 30000 | AA16: 45000 | AB16: 5000 | AC16: Black | AD16: 24 | AE16: QA/xx
A17: 91 | B17: 91 | C17: Brown, Leann | D17: B1 | E17: Brown, Leann | F17: 1 | K17: 100000 | L17: 100000 | M17: 100000 | N17: 100000 | O17: USD | P17: 45767 | Q17: 46022 | S17: 1 | T17: 0.2 | U17: 0.2 | V17: 0.2 | W17: 40000 | Y17: 15000 | Z17: 30000 | AA17: 45000 | AB17: 5000 | AC17: Black | AD17: test | AE17: QA/xx
A18: 92 | B18: 92 | C18: Craven, Liz | D18: B1 | E18: Craven, Liz | F18: 1 | K18: 100000 | L18: 100000 | M18: 100000 | N18: 100000 | O18: CAD | P18: 45767 | Q18: 46022 | S18: 1 | T18: 0.2 | U18: 0.2 | V18: 0.2 | W18: 40000 | X18: 45000 | Y18: 15000 | Z18: 30000 | AA18: 45000 | AB18: 5000 | AC18: Black | AD18: ok | AE18: QA/xx
A19: 111 | B19: 111 | C19: Galvan, Dina | D19: B1 | E19: Galvan, Dina | F19: 1 | K19: 100000 | L19: 100000 | M19: 100000 | N19: 100000 | O19: CAD | P19: 45767 | Q19: 46022 | S19: 1 | T19: 0.2 | U19: 0.2 | V19: 0.2 | W19: 40000 | Y19: 15000 | Z19: 30000 | AA19: 45000 | AB19: 5000 | AC19: Black | AD19: "50" | AE19: QA/xx
A20: 110 | B20: 110 | C20: Harrison, Cindy | D20: B1 | E20: Harrison, Cindy | F20: 1 | K20: 100000 | L20: 100000 | M20: 100000 | N20: 100000 | O20: CAD | P20: 45767 | Q20: 46022 | S20: 1 | T20: 0.2 | U20: 0.2 | V20: 0.2 | W20: 40000 | Y20: 15000 | Z20: 30000 | AA20: 45000 | AB20: 5000 | AC20: Black | AD20: "50" | AE20: QA/xx
A21: 95 | B21: 95 | C21: Henshaw, Candice | D21: B1 | E21: Henshaw, Candice | F21: 0.5 | K21: 100000 | L21: 100000 | M21: 100000 | N21: 100000 | O21: CAD | P21: 45767 | Q21: 46022 | S21: 1 | T21: 0.2 | U21: 0.2 | V21: 0.2 | W21: 40000 | X21: 50000 | Y21: 15000 | Z21: 30000 | AA21: 45000 | AB21: 5000 | AC21: Black | AD21: "50" | AE21: QA/xx
A22: 80 | B22: 80 | C22: Jackson, Charmain | D22: B1 | E22: Jackson, Charmain | F22: 1 | K22: 100000 | L22: 100000 | M22: 100000 | N22: 100000 | O22: CAD | P22: 45767 | Q22: 46022 | S22: 1 | T22: 0.2 | U22: 0.2 | V22: 0.2 | W22: 40000 | Y22: 15000 | Z22: 30000 | AA22: 45000 | AB22: 5000 | AC22: Black | AD22: "50" | AE22: QA/xx
A23: 115 | B23: 115 | C23: Mathers, Paula | D23: B1 | E23: Mathers, Paula | F23: 1 | K23: 100000 | L23: 100000 | M23: 100000 | N23: 100000 | O23: CAD | P23: 45767 | Q23: 46022 | S23: 1 | T23: 0.2 | U23: 0.2 | V23: 0.2 | W23: 40000 | Y23: 15000 | Z23: 30000 | AA23: 45000 | AB23: 5000 | AC23: Black | AD23: "50" | AE23: QA/xx
A24: 93 | B24: 93 | C24: Mott, Michael | D24: B1 | E24: Mott, Michael | F24: 1 | K24: 100000 | L24: 100000 | M24: 100000 | N24: 100000 | O24: BRL | P24: 45767 | Q24: 46022 | S24: 1 | T24: 0.2 | U24: 0.2 | V24: 0.2 | W24: 40000 | Y24: 15000 | Z24: 30000 | AA24: 45000 | AB24: 5000 | AC24: Black | AD24: "50" | AE24: QA/xx
A25: 101 | B25: 101 | C25: Napier, Alex | D25: B1 | E25: Napier, Alex | F25: 1 | K25: 100000 | L25: 100000 | M25: 100000 | N25: 100000 | O25: BRL | P25: 45767 | Q25: 46022 | S25: 1 | T25: 0.2 | U25: 0.2 | V25: 0.2 | W25: 40000 | Y25: 15000 | Z25: 30000 | AA25: 45000 | AB25: 5000 | AC25: Black | AD25: "50" | AE25: QA/xx
A26: 100 | B26: 100 | C26: Rames, Bill | D26: B1 | E26: Rames, Bill | F26: 0.7 | K26: 100000 | L26: 100000 | M26: 100000 | N26: 100000 | O26: BRL | P26: 45767 | Q26: 46022 | S26: 0.7 | T26: 0.2 | U26: 0.2 | V26: 0.2 | W26: 40000 | Y26: 15000 | Z26: 30000 | AA26: 45000 | AB26: 5000 | AC26: Black | AD26: 40.5 | AE26: QA/xx
A27: 104 | B27: 104 | C27: Risner, Elizabeth | D27: B1 | E27: Risner, Elizabeth | F27: 1 | K27: 100000 | L27: 100000 | M27: 100000 | N27: 100000 | O27: BRL | P27: 45767 | Q27: 46022 | S27: 1 | T27: 0.2 | U27: 0.2 | V27: 0.2 | W27: 40000 | Y27: 15000 | Z27: 30000 | AA27: 45000 | AB27: 5000 | AC27: Black | AD27: 41.5 | AE27: QA/xx
A28: 86 | B28: 86 | C28: Rogers, Mary | D28: B1 | E28: Rogers, Mary | F28: 1 | K28: 100000 | L28: 100000 | M28: 100000 | N28: 100000 | O28: BRL | P28: 45767 | Q28: 46022 | S28: 1 | T28: 0.2 | U28: 0.2 | V28: 0.2 | W28: 40000 | X28: 40000 | Y28: 15000 | Z28: 30000 | AA28: 45000 | AB28: 5000 | AC28: Black | AD28: 42.5 | AE28: QA/xx
A29: 89 | B29: 89 | C29: White, Gordon | D29: B1 | E29: White, Gordon | F29: 1 | K29: 100000 | L29: 100000 | M29: 100000 | N29: 100000 | O29: IDR | P29: 45767 | Q29: 46022 | S29: 1 | T29: 0.2 | U29: 0.2 | V29: 0.2 | W29: 40000 | Y29: 15000 | Z29: 30000 | AA29: 45000 | AB29: 5000 | AC29: Brown | AD29: 43.5 | AE29: QA/xx
A30: 72 | B30: 72 | C30: Davis, Beverly | D30: B1 | E30: Davis, Beverly | F30: 1 | K30: 100000 | L30: 100000 | M30: 100000 | N30: 100000 | O30: IDR | P30: 45767 | Q30: 46022 | S30: 1 | T30: 0.2 | U30: 0.2 | V30: 0.2 | W30: 40000 | Y30: 15000 | Z30: 30000 | AA30: 45000 | AB30: 5000 | AC30: Brown | AD30: 44.5 | AE30: QA/xx
A31: 162 | B31: 162 | C31: Thompson, Calvin | D31: B1 | E31: Thompson, Calvin | F31: 1 | K31: 100000 | L31: 100000 | M31: 100000 | N31: 100000 | O31: IDR | P31: 45767 | Q31: 46022 | S31: 1 | T31: 0.2 | U31: 0.2 | V31: 0.2 | W31: 40000 | Y31: 15000 | Z31: 30000 | AA31: 45000 | AB31: 5000 | AC31: Brown | AD31: 45.5 | AE31: Accountant/xxx
A32: 1121 | B32: 1121 | C32: Masters, Sarah | D32: B1 | E32: Masters, Sarah | F32: 1 | K32: 100000 | L32: 100000 | M32: 100000 | N32: 100000 | O32: IDR | P32: 45767 | Q32: 46022 | S32: 1 | T32: 0.2 | U32: 0.2 | V32: 0.2 | W32: 40000 | Y32: 15000 | Z32: 30000 | AA32: 45000 | AB32: 5000 | AC32: Brown | AD32: 46.5 | AE32: Accountant/xxx
A33: 1117 | B33: 1117 | C33: Ramsey, Richele | D33: B1 | E33: Ramsey, Richele | F33: 1 | K33: 100000 | L33: 100000 | M33: 100000 | N33: 100000 | O33: IDR | P33: 45767 | Q33: 46022 | S33: 1 | T33: 0.2 | U33: 0.2 | V33: 0.2 | W33: 40000 | Y33: 15000 | Z33: 30000 | AA33: 45000 | AB33: 5000 | AC33: Brown | AD33: 47.5 | AE33: Accountant/xxx
A34: 1115 | B34: 1115 | C34: Ross, Michael | D34: B1 | E34: Ross, Michael | K34: 100000 | L34: 100000 | M34: 100000 | N34: 100000 | O34: IDR | P34: 45767 | Q34: 46022 | S34: 1 | T34: 0.2 | U34: 0.2 | V34: 0.2 | W34: 40000 | X34: 145000 | Y34: 15000 | Z34: 30000 | AA34: 45000 | AB34: 5000 | AC34: Brown | AD34: 48.5 | AE34: Accountant/xxx
A35: 1128 | B35: 1128 | C35: Hinze, Drea | D35: B1 | E35: Hinze, Drea | K35: 100000 | L35: 100000 | M35: 100000 | N35: 100000 | O35: IDR | P35: 45767 | Q35: 46022 | S35: 1 | T35: 0.2 | U35: 0.2 | V35: 0.2 | W35: 40000 | Y35: 15000 | Z35: 30000 | AA35: 45000 | AB35: 5000 | AC35: Brown | AD35: 49.5 | AE35: Accountant/xxx
A36: 1123 | B36: 1123 | C36: Jackson, Leah | D36: B1 | E36: Jackson, Leah | K36: 100000 | L36: 100000 | M36: 100000 | N36: 100000 | O36: IDR | P36: 45767 | Q36: 46022 | S36: 1 | T36: 0.2 | U36: 0.2 | V36: 0.2 | W36: 40000 | Y36: 15000 | Z36: 30000 | AA36: 45000 | AB36: 5000 | AC36: 1 | AD36: 50.5 | AE36: Accountant/xxx
A37: 70 | B37: 70 | C37: Kirklan, Richard | D37: B1 | E37: Kirklan, Richard | K37: 100000 | L37: 100000 | M37: 100000 | N37: 100000 | O37: USD | P37: 45767 | Q37: 46022 | S37: 1 | T37: 0.2 | U37: 0.2 | V37: 0.2 | W37: 40000 | Y37: 15000 | Z37: 30000 | AA37: 45000 | AB37: 5000 | AC37: 2 | AD37: 51.5 | AE37: Accountant/xxx
A38: 1119 | B38: 1119 | C38: Mills, Gavin | D38: B1 | E38: Mills, Gavin | K38: 100000 | L38: 100000 | M38: 100000 | N38: 100000 | O38: USD | P38: 45767 | Q38: 46022 | S38: 1 | T38: 0.2 | U38: 0.2 | V38: 0.2 | W38: 40000 | Y38: 15000 | Z38: 30000 | AA38: 45000 | AB38: 5000 | AC38: Brown | AD38: 52.5 | AE38: Accountant/xxx
A39: 1118 | B39: 1118 | C39: Perez, Leila | D39: B1 | E39: Perez, Leila | K39: 100000 | L39: 100000 | M39: 100000 | N39: 100000 | O39: USD | P39: 45767 | Q39: 46022 | S39: 1 | T39: 0.2 | U39: 0.2 | V39: 0.2 | W39: 40000 | Y39: 15000 | Z39: 30000 | AA39: 45000 | AB39: 5000 | AC39: Brown | AD39: 53.5 | AE39: Accountant/xxx
A40: 59 | B40: 59 | C40: Sanders, Lynn | D40: B1 | E40: Sanders, Lynn | K40: 100000 | L40: 100000 | M40: 100000 | N40: 100000 | O40: USD | P40: 45767 | Q40: 46022 | S40: 1 | T40: 0.2 | U40: 0.2 | V40: 0.2 | W40: 40000 | X40: 50000 | Y40: 15000 | Z40: 30000 | AA40: 45000 | AB40: 5000 | AC40: Brown | AD40: 54.5 | AE40: Accountant/xxx
A41: 1127 | B41: 1127 | C41: Tanya, Field | D41: B1 | E41: Tanya, Field | F41: 1 | K41: 100000 | L41: 100000 | M41: 100000 | N41: 100000 | O41: USD | P41: 45767 | Q41: 46022 | S41: 1 | T41: 0.2 | U41: 0.2 | V41: 0.2 | W41: 40000 | Y41: 15000 | Z41: 30000 | AA41: 45000 | AB41: 5000 | AC41: Brown | AD41: 55.5 | AE41: Accountant/xxx
A42: 1132 | B42: 1132 | C42: Tso, Ann | D42: B1 | E42: Tso, Ann | F42: 1 | K42: 100000 | L42: 100000 | M42: 100000 | N42: 100000 | O42: USD | P42: 45767 | Q42: 46022 | S42: 1 | T42: 0.2 | U42: 0.2 | V42: 0.2 | W42: 40000 | Y42: 15000 | Z42: 30000 | AA42: 45000 | AB42: 5000 | AC42: Brown | AD42: 56.5 | AE42: Accountant/xxx
A43: 1126 | B43: 1126 | C43: Ungaba, Naomi | D43: B1 | E43: Ungaba, Naomi | F43: 1 | K43: 100000 | L43: 100000 | M43: 100000 | N43: 100000 | O43: USD | P43: 45767 | Q43: 46022 | S43: 1 | T43: 0.2 | U43: 0.2 | V43: 0.2 | W43: 40000 | Y43: 15000 | Z43: 30000 | AA43: 45000 | AB43: 5000 | AC43: Brown | AD43: 57.5 | AE43: Accountant/xxx
A44: 1125 | B44: 1125 | C44: Weddle, Valoria | D44: B1 | E44: Weddle, Valoria | F44: 1 | K44: 100000 | L44: 100000 | M44: 100000 | N44: 100000 | O44: USD | P44: 45767 | Q44: 46022 | S44: 1 | T44: 0.2 | U44: 0.2 | V44: 0.2 | W44: 40000 | Y44: 15000 | Z44: 30000 | AA44: 45000 | AB44: 5000 | AC44: Brown | AD44: 58.5 | AE44: Accountant/xxx
A45: 167 | B45: 167 | C45: Ramos, Amy | D45: B1 | E45: Ramos, Amy | F45: 1 | K45: 100000 | L45: 100000 | M45: 100000 | N45: 100000 | O45: USD | P45: 45767 | Q45: 46022 | S45: 1 | T45: 0.2 | U45: 0.2 | V45: 0.2 | W45: 40000 | Y45: 15000 | Z45: 30000 | AA45: 45000 | AB45: 5000 | AC45: Brown | AD45: 0.98 | AE45: Accountant/xxx
A46: 168 | B46: 168 | C46: Soles, Nedra | D46: B1 | E46: Soles, Nedra | F46: 1 | K46: 100000 | L46: 100000 | M46: 100000 | N46: 100000 | O46: USD | P46: 45767 | Q46: 46022 | S46: 1 | T46: 0.2 | U46: 0.2 | V46: 0.2 | W46: 40000 | Y46: 15000 | Z46: 30000 | AA46: 45000 | AB46: 5000 | AC46: Brown | AD46: 0.66 | AE46: Accountant/xxx
A47: 1113 | B47: 1113 | C47: Duncan, Sam | D47: B1 | E47: Duncan, Sam | F47: 1 | K47: 100000 | L47: 100000 | M47: 100000 | N47: 100000 | O47: USD | P47: 45767 | Q47: 46022 | S47: 1 | T47: 0.2 | U47: 0.2 | V47: 0.2 | W47: 40000 | Y47: 15000 | Z47: 30000 | AA47: 45000 | AB47: 5000 | AC47: Brown' | AD47: 22.89 | AE47: Accountant/xxx
A48: 1028 | B48: 1028 | C48: Resendez, MiMi | D48: B1 | E48: Resendez, MiMi | F48: 1 | K48: 100000 | L48: 100000 | M48: 100000 | N48: 100000 | O48: USD | P48: 45767 | Q48: 46022 | S48: 1 | T48: 0.2 | U48: 0.2 | V48: 0.2 | W48: 40000 | X48: 60000 | Y48: 15000 | Z48: 30000 | AA48: 45000 | AB48: 5000 | AC48: "Gray" | AD48: 23.89 | AE48: Accountant/xxx
A49: 1010 | B49: 1010 | C49: Tucker, Darla | D49: B1 | E49: Tucker, Darla | F49: 1 | K49: 100000 | L49: 100000 | M49: 100000 | N49: 100000 | O49: USD | P49: 45767 | Q49: 46022 | S49: 1 | T49: 0.2 | U49: 0.2 | V49: 0.2 | W49: 40000 | Y49: 15000 | Z49: 30000 | AA49: 45000 | AB49: 5000 | AC49: "Gray" | AD49: 24.89 | AE49: Accountant/xxx
A50: 175 | B50: 175 | C50: Anderson, Ann | D50: B1 | E50: Anderson, Ann | K50: 100000 | L50: 100000 | M50: 100000 | N50: 100000 | O50: USD | P50: 45767 | Q50: 46022 | T50: 0.2 | U50: 0.2 | V50: 0.2 | W50: 40000 | Y50: 15000 | Z50: 30000 | AA50: 45000 | AB50: 5000 | AC50: "Gray" | AD50: 25.89 | AE50: Accountant/xxx
A51: 176 | B51: 176 | C51: Bishop, Julie | D51: B1 | E51: Bishop, Julie | K51: 100000 | L51: 100000 | M51: 100000 | N51: 100000 | O51: USD | P51: 45767 | Q51: 46022 | T51: 0.2 | U51: 0.2 | V51: 0.2 | W51: 40000 | AB51: 5000 | AC51: "Gray" | AD51: 26.89 | AE51: Accountant/xxx
A52: 172 | B52: 172 | C52: Burke, Mia | D52: B1 | E52: Burke, Mia | K52: 100000 | L52: 100000 | M52: 100000 | N52: 100000 | O52: USD | P52: 45767 | Q52: 46022 | T52: 0.2 | U52: 0.2 | V52: 0.2 | W52: 40000 | AB52: 5000 | AC52: "Gray" | AD52: 27.89 | AE52: Accountant/xxx
A53: 174 | B53: 174 | C53: Carillo, Frank | D53: B1 | E53: Carillo, Frank | F53: 0.8 | K53: 100000 | L53: 100000 | M53: 100000 | N53: 100000 | O53: USD | P53: 45767 | Q53: 46022 | S53: 1 | T53: 0.2 | U53: 0.2 | V53: 0.2 | W53: 40000 | X53: 65000 | AB53: 5000 | AC53: "Gray" | AD53: 28.89 | AE53: Accountant/xxx
A54: 170 | B54: 170 | C54: Carter, Frank | D54: B1 | E54: Carter, Frank | F54: 1 | K54: 100000 | L54: 100000 | M54: 100000 | N54: 100000 | O54: USD | P54: 45767 | Q54: 46022 | S54: 1 | T54: 0.2 | U54: 0.2 | V54: 0.2 | W54: 40000 | AB54: 5000 | AC54: "Gray" | AD54: 29.89 | AE54: Accountant/xxx
A55: 177 | B55: 177 | C55: Pope, Ian | D55: B1 | E55: Pope, Ian | F55: 1 | K55: 100000 | L55: 100000 | M55: 100000 | N55: 100000 | O55: USD | P55: 45767 | Q55: 46022 | S55: 1 | T55: 0.2 | U55: 0.2 | V55: 0.2 | W55: 40000 | AB55: 5000 | AC55: "Gray" | AD55: 30.89 | AE55: Accountant/xxx
A56: 161 | B56: 161 | C56: Butler, Cathy | D56: B1 | E56: Butler, Cathy | F56: 1 | K56: 100000 | L56: 100000 | M56: 100000 | N56: 100000 | O56: USD | P56: 45767 | Q56: 46022 | S56: 1 | T56: 0.2 | U56: 0.2 | V56: 0.2 | W56: 40000 | AB56: 5000 | AC56: "Gray" | AD56: 31.89 | AE56: Accountant/xxx
A57: 166 | B57: 166 | C57: Montana, Joe | D57: B1 | E57: Montana, Joe | F57: 1 | K57: 100000 | L57: 100000 | M57: 100000 | N57: 100000 | O57: USD | P57: 45767 | Q57: 46022 | S57: 1 | T57: 0.2 | U57: 0.2 | V57: 0.2 | W57: 40000 | AB57: 5000 | AC57: "Gray" | AD57: 32.89 | AE57: Accountant/xxx
A58: 1012 | B58: 1012 | C58: Sherman, Jack | D58: B1 | E58: Sherman, Jack | F58: 1 | K58: 100000 | L58: 100000 | M58: 100000 | N58: 100000 | O58: USD | P58: 45767 | Q58: 46022 | S58: 1 | T58: 0.2 | U58: 0.2 | V58: 0.2 | W58: 40000 | X58: 75000 | AB58: 5000 | AC58: Blue* | AD58: 33.89 | AE58: Accountant/xxx
A59: 1043 | B59: 1043 | C59: Burke, Michelle | D59: B1 | E59: Burke, Michelle | F59: 0.5 | K59: 100000 | L59: 100000 | M59: 100000 | N59: 100000 | O59: USD | P59: 45767 | Q59: 46022 | S59: 0.5 | T59: 0.2 | U59: 0.2 | V59: 0.2 | W59: 40000 | AB59: 5000 | AC59: Blue | AD59: 34.89 | AE59: Accountant/xxx
A60: 1114 | B60: 1114 | C60: Sampson, DeDe | D60: B1 | E60: Sampson, DeDe | F60: 0.5 | K60: 100000 | L60: 100000 | M60: 100000 | N60: 100000 | O60: USD | P60: 45767 | Q60: 46022 | S60: 0.5 | T60: 0.2 | U60: 0.2 | V60: 0.2 | W60: 40000 | AB60: 5000 | AC60: Blue | AD60: 35.89 | AE60: Accountant/xxx | AF60: s
A61: 2168 | B61: 2168 | C61: Citrus, Susan | D61: B1 | E61: Citrus, Susan | F61: 1 | G61: 1113 | H61: Duncan Sam | K61: 100000 | L61: 100000 | M61: 100000 | N61: 100000 | O61: USD | P61: 45767 | Q61: 46022 | S61: 1 | T61: 0.2 | U61: 0.2 | V61: 0.2 | W61: 40000 | AB61: 5000 | AC61: Blue | AD61: 36.89 | AE61: Accountant/xxx
A62: 2167 | B62: 2167 | C62: Flavors, Natural | D62: B1 | E62: Flavors, Natural | F62: 1 | G62: 1113 | H62: Duncan Sam | K62: 100000 | L62: 100000 | M62: 100000 | N62: 100000 | O62: USD | P62: 45767 | Q62: 46022 | S62: 1 | T62: 0.2 | U62: 0.2 | V62: 0.2 | W62: 40000 | AB62: 5000 | AC62: Blue | AD62: 37.89 | AE62: Accountant/xxx
A63: 2000 | B63: 2000 | C63: Tompkins, Brian | D63: B1 | E63: Tompkins, Brian | F63: 1 | G63: 1113 | H63: Duncan Sam | K63: 100000 | L63: 100000 | M63: 100000 | N63: 100000 | O63: USD | P63: 45767 | Q63: 46022 | S63: 1 | T63: 0.2 | U63: 0.2 | V63: 0.2 | W63: 40000 | AB63: 5000 | AC63: Blue | AD63: 38.89 | AE63: Accountant/xxx
A64: 2001 | B64: 2001 | C64: Ward Jr, Lloyd | D64: B1 | E64: Ward Jr, Lloyd | F64: 1 | G64: 1113 | H64: Duncan Sam | K64: 100000 | L64: 100000 | M64: 100000 | N64: 100000 | O64: USD | P64: 45767 | Q64: 46022 | S64: 1 | T64: 0.2 | U64: 0.2 | V64: 0.2 | W64: 40000 | X64: 20000 | AB64: 5000 | AC64: Blue | AD64: 39.89 | AE64: Accountant/xxx
A65: 2166 | B65: 2166 | C65: Tea, Green | D65: B1 | E65: Tea, Green | F65: 1 | K65: 100000 | L65: 100000 | M65: 100000 | N65: 100000 | O65: USD | P65: 45767 | Q65: 46022 | S65: 1 | T65: 0.2 | U65: 0.2 | V65: 0.2 | W65: 40000 | AB65: 5000 | AC65: Blue | AD65: 40.89 | AE65: Software engineer/XXXX
A66: 2166 | B66: 2166 | C66: Tea, Green | D66: B1 | E66: Tea, Green | K66: 100000 | L66: 100000 | M66: 100000 | N66: 100000 | O66: USD | P66: 45767 | Q66: 46022 | AB66: 5000 | AC66: Blue | AD66: 41.89

Sheet Employee LTI Plans
A1: Employee Id | B1: Emp Id | C1: Name | D1: Employee Name | E1: Prorated LTI Mult Pct | F1: LTI Plan Name | G1: LTI Base Amt | H1: Currency Code | I1: LTI From Date | J1: LTI To Date | K1: Tgt LTI Opp Pct | L1: LTI Target | M1: Tgt LTI Opp Amt | N1: Mgr Emp Id | O1: Manager Name | P1: Plan Mgr Emp Id | Q1: Plan Mgr Emp Name | S1: LTI Guaranteed Minimum Amt | T1: Prior Grant Shares | U1: Prior Grant Value | V1: Bag Color | W1: Bag No | X1: Shoes Collection | Y1: Hair color | Z1: Sapphire | AA1: LTI Guideline Tgt Amt | AB1: LTI Guideline Min AmtX | AC1: LTI Guideline Max AmtX
A2: 161 | B2: 161 | C2: Butler, Cathy | D2: Butler, Cathy | E2: 1 | F2: L1 | G2: 100000 | H2: AED | I2: 45767 | J2: 46022 | K2: 0.1 | L2: 20000 | M2: 20000 | S2: 35000 | T2: 40 | U2: 10000 | V2: s | W2: 4 | X2: Bata shoes | Y2: 8.5 | Z2: summer collection | AB2: 15000 | AC2: 45000
A3: 167 | B3: 167 | C3: Ramos, Amy | D3: Ramos, Amy | E3: 1 | F3: L1 | G3: 100000 | H3: AED | I3: 45767 | J3: 46022 | K3: 0.1 | L3: 20000 | M3: 20000 | T3: 41 | U3: 10000 | V3: Black | W3: 5 | X3: ECS shoes | Y3: 9.5 | Z3: summer collection | AB3: 15000 | AC3: 45000
A4: 86 | B4: 86 | C4: Rogers, Mary | D4: Rogers, Mary | E4: 1 | F4: L1 | G4: 100000 | H4: USD | I4: 45767 | J4: 46022 | K4: 0.1 | L4: 20000 | M4: 20000 | T4: 45 | U4: 55890 | V4: off white | W4: 9 | X4: ECS shoes | Y4: 13.5 | Z4: summer collection | AB4: 15000 | AC4: 45000
A5: 1121 | B5: 1121 | C5: Masters, Sarah | D5: Masters, Sarah | E5: 1 | F5: L1 | G5: 100000 | H5: USD | I5: 45767 | J5: 46022 | K5: 0.1 | L5: 20000 | M5: 20000 | S5: 25000 | T5: 47 | U5: 55890 | V5: ss | W5: 11 | X5: ECS shoes | Y5: 15.5 | Z5: summer collection | AB5: 15000 | AC5: 45000
A6: 72 | B6: 72 | C6: Davis, Beverly | D6: Davis, Beverly | E6: 1 | F6: L1 | G6: 100000 | H6: USD | I6: 45767 | J6: 46022 | K6: 0.1 | L6: 20000 | M6: 20000 | T6: 48 | U6: 55890 | V6: off white | W6: 12 | X6: ECS shoes | Y6: 16.5 | Z6: summer collection | AB6: 15000 | AC6: 45000
A7: 162 | B7: 162 | C7: Thompson, Calvin | D7: Thompson, Calvin | E7: 1 | F7: L1 | G7: 100000 | H7: CAD | I7: 45767 | J7: 46022 | K7: 0.1 | L7: 20000 | M7: 20000 | S7: 25000 | T7: 55 | U7: 55890 | V7: off white | W7: test | X7: Service shoes | Y7: 23.5 | Z7: summer collection | AB7: 15000 | AC7: 45000
A8: 73 | B8: 73 | C8: Bonamy, James | D8: Bonamy, James | E8: 1 | F8: L1 | G8: 100000 | H8: CAD | I8: 45767 | J8: 46022 | K8: 0.1 | L8: 20000 | M8: 20000 | T8: 50.65 | U8: 55890 | V8: off white | W8: test | X8: Service shoes | Y8: 25.5 | Z8: summer collection | AB8: 15000 | AC8: 45000
A9: 1113 | B9: 1113 | C9: Duncan, Sam | D9: Duncan, Sam | E9: 1 | F9: L1 | G9: 100000 | H9: BRL | I9: 45767 | J9: 46022 | K9: 0.1 | L9: 20000 | M9: 20000 | S9: 30000 | T9: 60123 | U9: 55890 | V9: Black | W9: 10.5 | X9: Heels shoes | Y9: 28.5 | Z9: winter collection | AB9: 15000 | AC9: 45000
A10: 2004 | B10: 2004 | C10: Janish, Betty | D10: Janish, Betty | E10: 1 | F10: L1 | G10: 100000 | H10: BRL | I10: 45767 | J10: 46022 | K10: 0.1 | L10: 20000 | M10: 20000 | N10: 1113 | O10: Duncan Sam | T10: 60123 | U10: 55890 | V10: Black | W10: 10.5 | X10: Heels shoes | Y10: 29.5 | Z10: winter collection | AB10: 15000 | AC10: 45000
A11: 2002 | B11: 2002 | C11: Keeling, Larry | D11: Keeling, Larry | E11: 1 | F11: L1 | G11: 100000 | H11: BRL | I11: 45767 | J11: 46022 | K11: 0.1 | L11: 20000 | M11: 20000 | N11: 1113 | O11: Duncan Sam | S11: 15000 | T11: 60123 | U11: 55890 | V11: Black | W11: s | X11: Heels shoes | Y11: 30.5 | Z11: winter collection | AB11: 15000 | AC11: 45000
A12: 166 | B12: 166 | C12: Montana, Joe | D12: Montana, Joe | E12: 1 | F12: L1 | G12: 100000 | H12: IDR | I12: 45767 | J12: 46022 | K12: 0.1 | L12: 20000 | M12: 20000 | T12: 60123 | U12: 55890 | V12: Black | W12: 10.5 | X12: Heels shoes | Y12: 32.5 | Z12: winter collection | AB12: 15000 | AC12: 45000
A13: 177 | B13: 177 | C13: Pope, Ian | D13: Pope, Ian | F13: L1 | G13: 100000 | H13: IDR | I13: 45767 | J13: 46022 | K13: 0.1 | L13: 20000 | M13: 20000 | S13: 20000 | T13: 60123 | U13: 55890 | V13: Black | W13: 10.5 | X13: Heels shoes | Y13: 10.5 | Z13: winter collection | AB13: 15000 | AC13: 45000
A14: 1115 | B14: 1115 | C14: Ross, Michael | D14: Ross, Michael | F14: L1 | G14: 100000 | H14: USD | I14: 45767 | J14: 46022 | K14: 0.1 | L14: 20000 | M14: 20000 | S14: 70000 | T14: 60 | U14: 55890 | V14: Black | W14: 15.11 | X14: 1 | Y14: 13.5 | Z14: Bridal dress | AB14: 15000 | AC14: 45000
A15: 1114 | B15: 1114 | C15: Sampson, DeDe | D15: Sampson, DeDe | F15: L1 | G15: 100000 | H15: IDR | I15: 45767 | J15: 46022 | K15: 0.1 | L15: 20000 | M15: 20000 | T15: 60 | U15: 55890 | V15: Black | W15: 15.11 | X15: 2 | Y15: 14.5 | Z15: Bridal dress | AB15: 15000 | AC15: 45000
A16: 1012 | B16: 1012 | C16: Sherman, Jack | D16: Sherman, Jack | F16: L1 | G16: 100000 | H16: IDR | I16: 45767 | J16: 46022 | K16: 0.1 | L16: 20000 | M16: 20000 | S16: 45000 | T16: 1 | U16: 55890 | V16: Black | W16: 15.11 | X16: 3 | Y16: 15.5 | Z16: Bridal dress | AB16: 15000 | AC16: 45000
A17: 168 | B17: 168 | C17: Soles, Nedra | D17: Soles, Nedra | F17: L1 | G17: 100000 | H17: IDR | I17: 45767 | J17: 46022 | K17: 0.1 | L17: 20000 | M17: 20000 | T17: 1 | U17: 55890 | V17: Black | W17: 15.11 | X17: 4 | Y17: 16.5 | Z17: Bridal dress | AB17: 15000 | AC17: 45000
A18: 2166 | B18: 2166 | C18: Tea, Green | D18: Tea, Green | E18: 1 | F18: L1 | G18: 100000 | H18: USD | I18: 45767 | J18: 46022 | K18: 0.1 | L18: 20000 | M18: 20000 | T18: 10 | U18: 55890 | V18: Black | W18: 15.11 | X18: stylo | Y18: 17.5 | Z18: Bridal dress | AB18: 15000 | AC18: 45000
A19: 1010 | B19: 1010 | C19: Tucker, Darla | D19: Tucker, Darla | E19: 1 | F19: L1 | G19: 100000 | H19: USD | I19: 45767 | J19: 46022 | K19: 0.1 | L19: 20000 | M19: 20000 | S19: 12000 | T19: 81 | U19: 55890 | V19: Black | W19: ok' | X19: stylo | Y19: 19.5 | Z19: Bridal dress | AB19: 15000 | AC19: 45000
A20: 2001 | B20: 2001 | C20: Ward Jr, Lloyd | D20: Ward Jr, Lloyd | E20: 1 | F20: L1 | G20: 100000 | H20: USD | I20: 45767 | J20: 46022 | K20: 0.1 | L20: 20000 | M20: 20000 | T20: 81 | U20: 55890 | V20: Black | W20: test | X20: stylo | Y20: 20.5 | Z20: Bridal dress | AB20: 15000 | AC20: 45000

Sheet Users
A1: Emp Id | B1: User Name First | C1: User Name Last | D1: User Type | E1: User Principal Name | F1: Login Id | G1: Email Address | H1: User Password | I1: User Time Zone
A2: 72 | B2: Beverly | C2: Davis | D2: Employee | E2: bdavis@dartican.com | F2: bdavis | G2: bdavis@dartican.com | H2: open
A3: 162 | B3: Calvin | C3: Thompson | D3: Employee | E3: calvin@dartican.com | F3: calvin | G3: calvin@dartican.com | H3: open
A4: 166 | B4: Joe | C4: Montana | F4: jmontana | G4: jmontana@dartican.com | H4: open
A5: 168 | B5: Nedra | C5: Soles | F5: nsoles | G5: nsoles@dartican.com | H5: open
A6: 1012 | B6: Jack | C6: Sherman | D6: Employee | E6: jsherman@dartican.com | F6: jsherman | G6: jsherman@dartican.com | H6: open
A7: 1113 | B7: Sam | C7: Duncan | D7: Employee | E7: sduncan@dartican.com | F7: sduncan | G7: sduncan@dartican.com | H7: open
A8: 80 | B8: Charmain | C8: Jackson | D8: Employee | E8: cjackson@dartican.com | F8: cjackson | G8: cjackson@dartican.com | H8: open
A9: 2166 | B9: Green | C9: Tea | D9: Employee | E9: tgreen@dartican.com | F9: tgreen | G9: tgreen@dartican.com | H9: open
A10: 1117 | B10: Richele | C10: Ramsey | D10: Employee | E10: rramsey@dartican.com | F10: rramsey | G10: rramsey@dartican.com | H10: open
A11: 1114 | B11: DeDe | C11: Sampson | D11: Employee | E11: dsampson@dartican.com | F11: dsampson | G11: dsampson@dartican.com | H11: open
A12: 2013 | B12: James | C12: Yokay | D12: Employee | E12: jyokay@dartican.com | F12: jyokay | G12: jyokay@dartican.com | H12: open
A13: 1121 | B13: Sarah | C13: Masters | D13: Employee | E13: msarah@dartican.com | F13: msarah | G13: msarah@dartican.com | H13: open
A14: 1010 | B14: Darla | C14: Tucker | D14: Employee | E14: dtucker@dartican.com | F14: dtucker | G14: dtucker@dartican.com | H14: open
A15: 2001 | B15: Lloyd | C15: Ward Jr | D15: Employee | E15: jward@dartican.com | F15: jward | G15: jward@dartican.com | H15: open

Sheet Jobsss
A1: Job Code | B1: Job Title | C1: Current Position Title | D1: Job Family Code | E1: Job Family Name | F1: Job Discipline Name | G1: Job Level | H1: Grade Level | I1: FLSA | J1: Salary Grade | K1: Structure Region | L1: Structure Item | M1: Display Order | N1: Structure Name
A2: J001 | B2: Certified Doc Aide | C2: Certified Doc Aide | D2: ACC | E2: Accounting | F2: Money out | G2: OK | H2: GRD-E06 | I2: Exempt | J2: E06 | L2: E06 | M2: 1 | N2: Exempt US
A3: J002 | B3: Certified Nurse Aide | C3: Certified Nurse Aide | D3: OPS | E3: Operations | F3: Med | G3: OK | H3: GRD-E06 | I3: Exempt | J3: E06 | L3: E06 | M3: 2 | N3: Exempt US
A4: J003 | B4: LVN | C4: LVN | D4: OPS | E4: Operations | F4: Med | G4: OK | H4: GRD-E10 | I4: Exempt | J4: E10 | L4: E10 | M4: 3 | N4: Exempt US
A5: J004 | B5: RN | C5: RN | D5: OPS | E5: Operations | F5: Med | G5: OK | H5: GRD-E12 | I5: Exempt | J5: E12 | L5: E12 | M5: 4 | N5: Exempt US
A6: J005 | B6: A/P Specialist | C6: A/P Specialist | D6: ACC | E6: Accounting | F6: Money out | G6: OK | H6: GRD-E14 | I6: Exempt | J6: E14 | L6: E14 | M6: 5 | N6: Exempt US
A7: J006 | B7: A/R Specialist-Billing | C7: A/R Specialist-Billing | D7: ACC | E7: Accounting | F7: Money In | G7: OK | H7: GRD-E14 | I7: Exempt | J7: E14 | L7: E14 | M7: 6 | N7: Exempt US
A8: J007 | B8: HR Coordinator | C8: HR Coordinator | D8: HR | E8: Human\ Resources | F8: People | G8: OK | H8: GRD-E14 | I8: Exempt | J8: E14 | L8: E14 | M8: 7 | N8: Exempt US
A9: J008 | B9: HR Coordinator/AA | C9: HR Coordinator/AA | D9: HR | E9: Human Resources | F9: People | G9: OK | H9: GRD-E14 | I9: Exempt | J9: E14 | L9: E14 | M9: 8 | N9: Exempt US
A10: J009 | B10: P/R Specialist | C10: P/R Specialist | D10: OPS | E10: Operations | F10: Work | G10: OK | H10: GRD-E14 | I10: Exempt | J10: E14 | L10: E14 | M10: 9 | N10: Exempt US
A11: J010 | B11: Administrative Assistant I | C11: Administrative Assistant I | D11: Admin | E11: Administration | F11: not real work | G11: OK | H11: GRD-E16 | I11: Exempt | J11: E16 | L11: E16 | M11: 10 | N11: Exempt US
A12: J011 | B12: Administrative Assistant III | C12: Administrative Assistant III | D12: Admin | E12: Administration | F12: not real work | G12: OK | H12: GRD-E18 | I12: Exempt | J12: E18 | L12: E18 | M12: 11 | N12: Exempt US
A13: J012 | B13: Director of Nursing | C13: Director of Nursing | D13: OPS | E13: Operations | F13: Work | G13: OK | H13: GRD-E18 | I13: Exempt | J13: E18 | L13: E18 | M13: 12 | N13: Exempt US
... A21: J020 | B21: Human Resource Manager | C21: Human Resource Manager | D21: HR | E21: Human Resources | F21: People | G21: OK | H21: GRD-E28 | I21: Exempt | J21: E28 | L21: E28 | M21: 20 | N21: Exempt CAD
A22: J021 | B22: Sales/Marketing Manager | C22: Sales/Marketing Manager | F22: Money In | G22: OK | H22: GRD-E29 | I22: Exempt | J22: E29 | L22: E29 | M22: 21 | N22: Exempt CAD
A23: J022 | B23: IT Manager | C23: IT Manager | D23: IT | E23: Technology | F23: Tech | G23: OK | H23: GRD-E32 | I23: Exempt | J23: E20 | K23: Australian | L23: E20 | M23: 22
A24: J023 | B24: Controller | C24: Controller | D24: ACC | E24: Accounting | F24: Money tracker | G24: Up There | H24: GRD-E34 | I24: Exempt | J24: E20 | K24: Australian | L24: E20 | M24: 23
A25: J024 | B25: Director of HR | C25: Director of HR | D25: HR | E25: Human Resources | F25: People | G25: Up There | H25: GRD-E34 | I25: Exempt | J25: E21 | K25: Australian | L25: E21 | M25: 24
A26: J025 | B26: Director of Operations | C26: Director of Operations | D26: OPS | E26: Operations | F26: Work | G26: Up There | H26: GRD-E34 | I26: Exempt | J26: E34 | L26: E34 | M26: 25 | N26: Exempt CAD
A27: J026 | B27: Director of Operations | C27: Director of Operations | D27: ACC | E27: Accounting | F27: Money tracker | G27: Up There | H27: GRD-E38 | I27: Exempt | J27: E38 | L27: E38 | M27: 26 | N27: Exempt CAD
A28: J027 | B28: Director of Operations | C28: Director of Operations | D28: IT | E28: Technology | F28: Tech | G28: Up There | H28: GRD-E38 | I28: Exempt | J28: E38 | L28: E38 | M28: 27 | N28: Exempt CAD
A29: J028 | B29: Director of Operations | C29: Director of Operations | D29: OPS | E29: Operations | F29: Work | G29: Near Top | H29: GRD-E38 | I29: Exempt | J29: E38 | L29: E38 | M29: 28 | N29: Exempt CAD
A30: J029 | B30: Director of Operations | C30: Director of Operations | F30: not real work | G30: Top | H30: GRD-E40 | I30: Exempt | J30: E40 | L30: E40 | M30: 29 | N30: Exempt CAD

Sheet Jobs
A1: Job Code | B1: Job Title | C1: Current Position Title | D1: Job Family Code | E1: Job Family Name | F1: Job Discipline Name | G1: Job Level | H1: Grade Level | I1: FLSA | J1: Salary Grade | K1: Structure Region | L1: Structure Item | M1: Display Order | N1: Structure Name
A2: J001 | B2: Certified Doc Aide | C2: Certified Doc Aide! | D2: ACC | E2: Accounting! | F2: Money out | G2: OK | H2: GRD-E06 | I2: Exempt | J2: E06 | L2: E06 | M2: 1 | N2: Exempt US
A3: J002 | B3: Certified Nurse Aide | C3: Certified Nurse Aide@ | D3: OPS | E3: Operations@ | F3: Med | G3: OK | H3: GRD-E06 | I3: Exempt | J3: E06 | L3: E06 | M3: 2 | N3: Exempt US
A4: J003 | B4: LVN | C4: LVN# | D4: OPS | E4: Operations# | F4: Med | G4: OK | H4: GRD-E10 | I4: Exempt | J4: E10 | L4: E10 | M4: 3 | N4: Exempt US
A5: J004 | B5: RN | C5: RN$ | D5: OPS | E5: Operations$ | F5: Med | G5: OK | H5: GRD-E12 | I5: Exempt | J5: E12 | L5: E12 | M5: 4 | N5: Exempt US
A6: J005 | B6: A/P Specialist | C6: A/P Specialist% | D6: ACC | E6: Accounting% | F6: Money out | G6: OK | H6: GRD-E14 | I6: Exempt | J6: E14 | L6: E14 | M6: 5 | N6: Exempt US
A7: J006 | B7: A/R Specialist-Billing | C7: A/R Specialist-Billing^ | D7: ACC | E7: Accounting^ | F7: Money In | G7: OK | H7: GRD-E14 | I7: Exempt | J7: E14 | L7: E14 | M7: 6 | N7: Exempt US
A8: J007 | B8: HR Coordinator& | C8: HR Coordinator& | D8: HR | E8: Human\ Resources& | F8: People | G8: OK | H8: GRD-E14 | I8: Exempt | J8: E14 | L8: E14 | M8: 7 | N8: Exempt US
A9: J008 | B9: HR Coordinator/AA | C9: HR Coordinator/AA* | D9: HR | E9: Human Resources* | F9: People | G9: OK | H9: GRD-E14 | I9: Exempt | J9: E14 | L9: E14 | M9: 8 | N9: Exempt US
A10: J009 | B10: P/R Specialist | C10: P/R Specialist( | D10: OPS | E10: Operations( | F10: Work | G10: OK | H10: GRD-E14 | I10: Exempt | J10: E14 | L10: E14 | M10: 9 | N10: Exempt US
A11: J010 | B11: Administrative Assistant I | C11: Administrative Assistant I ) | D11: Admin | E11: Administration) | F11: not real work | G11: OK | H11: GRD-E16 | I11: Exempt | J11: E16 | L11: E16 | M11: 10 | N11: Exempt US
A12: J011 | B12: Administrative Assistant III _ | C12: Administrative Assistant III _ | D12: Admin | E12: Administration_ | F12: not real work | G12: OK | H12: GRD-E18 | I12: Exempt | J12: E18 | L12: E18 | M12: 11 | N12: Exempt US
A13: J012 | B13: Director of Nursing - | C13: Director of Nursing - | D13: OPS | E13: Operations- | F13: Work | G13: OK | H13: GRD-E18 | I13: Exempt | J13: E18 | L13: E18 | M13: 12 | N13: Exempt US
... A21: J020 | B21: Human Resource Manager | C21: Human Resource Manager \ | D21: HR | E21: Human Resources\ | F21: People | G21: OK | H21: GRD-E28 | I21: Exempt | J21: E28 | L21: E28 | M21: 20 | N21: Exempt CAD
A22: J021 | B22: Sales/Marketing Manager | C22: Sales/Marketing Manager : | E22: Marketing : | F22: Money In | G22: OK | H22: GRD-E29 | I22: Exempt | J22: E29 | L22: E29 | M22: 21 | N22: Exempt CAD
A23: J022 | B23: IT Manager | C23: IT Manager ; | D23: IT | E23: Technology ; | F23: Tech | G23: OK | H23: GRD-E32 | I23: Exempt | J23: E20 | K23: Australian | L23: E20 | M23: 22
A24: J023 | B24: Controller ' | C24: Controller ' | D24: ACC | E24: Accounting ' | F24: Money tracker | G24: Up There | H24: GRD-E34 | I24: Exempt | J24: E20 | K24: Australian | L24: E20 | M24: 23
A25: J024 | B25: Director of HR | C25: Director of HR " | D25: HR | E25: Human Resources " | F25: People | G25: Up There | H25: GRD-E34 | I25: Exempt | J25: E21 | K25: Australian | L25: E21 | M25: 24
A26: J025 | B26: Director of Operations | C26: Director of Operations < | D26: OPS | E26: Operations < | F26: Work | G26: Up There | H26: GRD-E34 | I26: Exempt | J26: E34 | L26: E34 | M26: 25 | N26: Exempt CAD
A27: J026 | B27: Director of Operations , | C27: Director of Operations , | D27: ACC | E27: Accounting, | F27: Money tracker | G27: Up There | H27: GRD-E38 | I27: Exempt | J27: E38 | L27: E38 | M27: 26 | N27: Exempt CAD
A28: J027 | B28: Director of Operations | C28: Director of Operations > | D28: IT | E28: Technology> | F28: Tech | G28: Up There | H28: GRD-E38 | I28: Exempt | J28: E38 | L28: E38 | M28: 27 | N28: Exempt CAD
A29: J028 | B29: Director of Operations | C29: Director of Operations ? | D29: OPS | E29: Operations? | F29: Work | G29: Near Top | H29: GRD-E38 | I29: Exempt | J29: E38 | L29: E38 | M29: 28 | N29: Exempt CAD
A30: J029 | B30: Director of Operations / | C30: Director of Operations / | E30: Operations / | F30: not real work | G30: Top | H30: GRD-E40 | I30: Exempt | J30: E40 | L30: E40 | M30: 29 | N30: Exempt CAD

Sheet GL Enforce To Minimum
A1: Rating Name | B1: Rating Alpha | C1: Merit Guideline From | D1: Merit Guideline To
B2: 1 | C2: 0 | D2: 0.005
B3: 2 | C3: 0.005 | D3: 0.015
B4: 3 | C4: 0.13 | D4: 0.14
B5: 4 | C5: 0.06 | D5: 0.06
B6: 5 | C6: 0.1 | D6: 0.1

Sheet GL Matrix
A1: Rating Name | B1: Rating Alpha | C1: Q1 From | D1: Q1 To | E1: Q2 From | F1: Q2 To | G1: Q3 From | H1: Q3 To | I1: Q4 From | J1: Q4 To
B2: 1 | C2: 0 | D2: 0 | E2: 0 | F2: 0 | G2: 0 | H2: 0 | I2: 0 | J2: 0
B3: 2 | C3: 0 | D3: 0.02 | E3: 0 | F3: 0.01 | G3: 0 | H3: 0 | I3: 0 | J3: 0
B4: 3 | C4: 0.03 | D4: 0.04 | E4: 0.02 | F4: 0.03 | G4: 0.01 | H4: 0.02 | I4: 0 | J4: 0.01
B5: 4 | C5: 0.035 | D5: 0.055 | E5: 0.025 | F5: 0.045 | G5: 0.015 | H5: 0.035 | I5: 0.005 | J5: 0.025
B6: 5 | C6: 0.05 | D6: 0.07 | E6: 0.04 | F6: 0.06 | G6: 0.03 | H6: 0.05 | I6: 0.02 | J6: 0.04

Sheet GL First
A1: Rating Name | B1: Rating Alpha | C1: Q1 From | D1: Q1 To | E1: Q2 From | F1: Q2 To | G1: Q3 From | H1: Q3 To | I1: Q4 From | J1: Q4 To
B2: 1 | C2: ='GL Matrix'!C2+1%-1% -> 0 | D2: ='GL Matrix'!D2+1%-1% -> 0 | E2: ='GL Matrix'!E2+1%-1% -> 0 | F2: ='GL Matrix'!F2+1%-1% -> 0 | G2: ='GL Matrix'!G2+1%-1% -> 0 | H2: ='GL Matrix'!H2+1%-1% -> 0 | I2: ='GL Matrix'!I2+1%-1% -> 0 | J2: ='GL Matrix'!J2+1%-1% -> 0
B3: 2 | C3: ='GL Matrix'!C3+1%-1% -> 0 | D3: ='GL Matrix'!D3+1%-1% -> 0.02 | E3: ='GL Matrix'!E3+1%-1% -> 0 | F3: ='GL Matrix'!F3+1%-1% -> 0.01 | G3: ='GL Matrix'!G3+1%-1% -> 0 | H3: ='GL Matrix'!H3+1%-1% -> 0 | I3: ='GL Matrix'!I3+1%-1% -> 0 | J3: ='GL Matrix'!J3+1%-1% -> 0
B4: 3 | C4: ='GL Matrix'!C4+1%-1% -> 0.03 | D4: ='GL Matrix'!D4+1%-1% -> 0.04 | E4: ='GL Matrix'!E4+1%-1% -> 0.02 | F4: ='GL Matrix'!F4+1%-1% -> 0.03 | G4: ='GL Matrix'!G4+1%-1% -> 0.01 | H4: ='GL Matrix'!H4+1%-1% -> 0.02 | I4: ='GL Matrix'!I4+1%-1% -> 0 | J4: ='GL Matrix'!J4+1%-1% -> 0.01
B5: 4 | C5: ='GL Matrix'!C5+1%-1% -> 0.035 | D5: ='GL Matrix'!D5+1%-1% -> 0.055 | E5: ='GL Matrix'!E5+1%-1% -> 0.025 | F5: ='GL Matrix'!F5+1%-1% -> 0.045 | G5: ='GL Matrix'!G5+1%-1% -> 0.015 | H5: ='GL Matrix'!H5+1%-1% -> 0.035 | I5: ='GL Matrix'!I5+1%-1% -> 0.005 | J5: ='GL Matrix'!J5+1%-1% -> 0.025
B6: 5 | C6: ='GL Matrix'!C6+1%-1% -> 0.05 | D6: ='GL Matrix'!D6+1%-1% -> 0.07 | E6: ='GL Matrix'!E6+1%-1% -> 0.04 | F6: ='GL Matrix'!F6+1%-1% -> 0.06 | G6: ='GL Matrix'!G6+1%-1% -> 0.03 | H6: ='GL Matrix'!H6+1%-1% -> 0.05 | I6: ='GL Matrix'!I6+1%-1% -> 0.02 | J6: ='GL Matrix'!J6+1%-1% -> 0.04

Sheet GL Second
A1: Rating Name | B1: Rating Alpha | C1: Q1 From | D1: Q1 To | E1: Q2 From | F1: Q2 To | G1: Q3 From | H1: Q3 To | I1: Q4 From | J1: Q4 To
B2: 1 | C2: 0 | D2: 0 | E2: 0 | F2: 0 | G2: 0 | H2: 0 | I2: 0 | J2: 0
B3: 2 | C3: 0 | D3: 2 | E3: 0 | F3: 1 | G3: 0 | H3: 0 | I3: 0 | J3: 0
B4: 3 | C4: 3 | D4: 4 | E4: 2 | F4: 3 | G4: 1 | H4: 2 | I4: 0 | J4: 1
B5: 4 | C5: 3.5 | D5: 5.5 | E5: 2.5 | F5: 4.5 | G5: 1.5 | H5: 3.5 | I5: 0.5 | J5: 2.5
B6: 5 | C6: 5 | D6: 7 | E6: 4 | F6: 6 | G6: 3 | H6: 5 | I6: 2 | J6: 4

Sheet GL Third
A1: Rating Name | B1: Rating Alpha | C1: Q1 From | D1: Q1 To | E1: Q2 From | F1: Q2 To | G1: Q3 From | H1: Q3 To | I1: Q4 From | J1: Q4 To
B2: 1 | C2: ='GL Matrix'!C2*100 -> 0 | D2: ='GL Matrix'!D2*100 -> 0 | E2: ='GL Matrix'!E2*100 -> 0 | F2: ='GL Matrix'!F2*100 -> 0 | G2: ='GL Matrix'!G2*100 -> 0 | H2: ='GL Matrix'!H2*100 -> 0 | I2: ='GL Matrix'!I2*100 -> 0 | J2: ='GL Matrix'!J2*100 -> 0
B3: 2 | C3: ='GL Matrix'!C3*100 -> 0 | D3: ='GL Matrix'!D3*100 -> 2 | E3: ='GL Matrix'!E3*100 -> 0 | F3: ='GL Matrix'!F3*100 -> 1 | G3: ='GL Matrix'!G3*100 -> 0 | H3: ='GL Matrix'!H3*100 -> 0 | I3: ='GL Matrix'!I3*100 -> 0 | J3: ='GL Matrix'!J3*100 -> 0
B4: 3 | C4: ='GL Matrix'!C4*100 -> 3 | D4: ='GL Matrix'!D4*100 -> 4 | E4: ='GL Matrix'!E4*100 -> 2 | F4: ='GL Matrix'!F4*100 -> 3 | G4: ='GL Matrix'!G4*100 -> 1 | H4: ='GL Matrix'!H4*100 -> 2 | I4: ='GL Matrix'!I4*100 -> 0 | J4: ='GL Matrix'!J4*100 -> 1
B5: 4 | C5: ='GL Matrix'!C5*100 -> 3.5 | D5: ='GL Matrix'!D5*100 -> 5.5 | E5: ='GL Matrix'!E5*100 -> 2.5 | F5: ='GL Matrix'!F5*100 -> 4.5 | G5: ='GL Matrix'!G5*100 -> 1.5 | H5: ='GL Matrix'!H5*100 -> 3.5 | I5: ='GL Matrix'!I5*100 -> 0.5 | J5: ='GL Matrix'!J5*100 -> 2.5
B6: 5 | C6: ='GL Matrix'!C6*100 -> 5 | D6: ='GL Matrix'!D6*100 -> 7 | E6: ='GL Matrix'!E6*100 -> 4 | F6: ='GL Matrix'!F6*100 -> 6 | G6: ='GL Matrix'!G6*100 -> 3 | H6: ='GL Matrix'!H6*100 -> 5 | I6: ='GL Matrix'!I6*100 -> 2 | J6: ='GL Matrix'!J6*100 -> 4

Sheet GL Forth
A1: Rating Name | B1: Rating Alpha | C1: A From | D1: A To | E1: B From | F1: B To | G1: C From | H1: C To | I1: D From | J1: D To | K1: E From | L1: E To | M1: F From | N1: F To | O1: G From | P1: G To | Q1: H From | R1: H To | S1: I From | T1: I To
B2: 1 | C2: ='GL First'!C2+0 -> 0 | D2: ='GL First'!D2+0 -> 0 | E2: ='GL First'!E2+0 -> 0 | F2: ='GL First'!F2+0 -> 0 | G2: ='GL First'!G2+0 -> 0 | H2: ='GL First'!H2+0 -> 0 | I2: ='GL First'!I2+0 -> 0 | J2: ='GL First'!J2+0 -> 0 | K2: =J2+0.25% -> 0.0025 | L2: =K2+0.25% -> 0.005 | M2: =L2+0.25% -> 0.0075 | N2: =M2+0.25% -> 0.01 | O2: =N2+0.25% -> 0.0125 | P2: =O2+0.25% -> 0.015 | Q2: =P2+0.25% -> 0.0175 | R2: =Q2+0.25% -> 0.02 | ... T2: =S2+0.25% -> 0.025
B3: 2 | C3: ='GL First'!C3+0 -> 0 | D3: ='GL First'!D3+0 -> 0.02 | E3: ='GL First'!E3+0 -> 0 | F3: ='GL First'!F3+0 -> 0.01 | G3: ='GL First'!G3+0 -> 0 | H3: ='GL First'!H3+0 -> 0 | I3: ='GL First'!I3+0 -> 0 | J3: ='GL First'!J3+0 -> 0 | K3: =J3+0.25% -> 0.0025 | L3: =K3+0.25% -> 0.005 | M3: =L3+0.25% -> 0.0075 | N3: =M3+0.25% -> 0.01 | O3: =N3+0.25% -> 0.0125 | P3: =O3+0.25% -> 0.015 | Q3: =P3+0.25% -> 0.0175 | R3: =Q3+0.25% -> 0.02 | ... T3: =S3+0.25% -> 0.025
B4: 3 | C4: ='GL First'!C4+0 -> 0.03 | D4: ='GL First'!D4+0 -> 0.04 | E4: ='GL First'!E4+0 -> 0.02 | F4: ='GL First'!F4+0 -> 0.03 | G4: ='GL First'!G4+0 -> 0.01 | H4: ='GL First'!H4+0 -> 0.02 | I4: ='GL First'!I4+0 -> 0 | J4: ='GL First'!J4+0 -> 0.01 | K4: =J4+0.25% -> 0.0125 | L4: =K4+0.25% -> 0.015 | M4: =L4+0.25% -> 0.0175 | N4: =M4+0.25% -> 0.02 | O4: =N4+0.25% -> 0.0225 | P4: =O4+0.25% -> 0.025 | Q4: =P4+0.25% -> 0.0275 | R4: =Q4+0.25% -> 0.03 | ... T4: =S4+0.25% -> 0.035
B5: 4 | C5: ='GL First'!C5+0 -> 0.035 | D5: ='GL First'!D5+0 -> 0.055 | E5: ='GL First'!E5+0 -> 0.025 | F5: ='GL First'!F5+0 -> 0.045 | G5: ='GL First'!G5+0 -> 0.015 | H5: ='GL First'!H5+0 -> 0.035 | I5: ='GL First'!I5+0 -> 0.005 | J5: ='GL First'!J5+0 -> 0.025 | K5: =J5+0.25% -> 0.0275 | L5: =K5+0.25% -> 0.03 | M5: =L5+0.25% -> 0.0325 | N5: =M5+0.25% -> 0.035 | O5: =N5+0.25% -> 0.0375 | P5: =O5+0.25% -> 0.04 | Q5: =P5+0.25% -> 0.0425 | R5: =Q5+0.25% -> 0.045 | ... T5: =S5+0.25% -> 0.05
B6: 5 | C6: ='GL First'!C6+0 -> 0.05 | D6: ='GL First'!D6+0 -> 0.07 | E6: ='GL First'!E6+0 -> 0.04 | F6: ='GL First'!F6+0 -> 0.06 | G6: ='GL First'!G6+0 -> 0.03 | H6: ='GL First'!H6+0 -> 0.05 | I6: ='GL First'!I6+0 -> 0.02 | J6: ='GL First'!J6+0 -> 0.04 | K6: =J6+0.25% -> 0.0425 | L6: =K6+0.25% -> 0.045 | M6: =L6+0.25% -> 0.0475 | N6: =M6+0.25% -> 0.05 | O6: =N6+0.25% -> 0.0525 | P6: =O6+0.25% -> 0.055 | Q6: =P6+0.25% -> 0.0575 | R6: =Q6+0.25% -> 0.06 | ... T6: =S6+0.25% -> 0.065

Sheet ok

Sheet Employee Earnings Refresh
A1: Employee Id | B1: Bonus Plan Name | C1: Base Amount
A2: 2009 | B2: B1 | C2: 100
A3: 2004 | B3: B1 | C3: 200
A4: 2002 | B4: B1 | C4: 300
A5: 2008 | B5: B1 | C5: 400
A6: 2005 | B6: B1 | C6: 500
A7: 2010 | B7: B1 | C7: 500
A8: 2007 | B8: B2 | C8: 500
A9: 2006 | B9: B2 | C9: 500
A10: 2003 | B10: B2 | C10: 500
A11: 2011 | B11: B2 | C11: 500
A12: 2012 | B12: B2 | C12: 500
A13: 2013 | B13: B2 | C13: 600
... A65: 2166 | B65: B1 | C65: 100000
B66: B2 | C66: 100000

Sheet Employee Ratings
A1: Employee Id | B1: Name | C1: PMP
A2: 2009 | B2: (Grimm, Briañ) | C2: 1
A3: 2004 | B3: Janish / Betty | C3: 2
A4: 2002 | B4: Keeling, Larry | C4: 2
A5: 2008 | B5: Krendick, Jasoñ | C5: 2
A6: 2005 | B6: Leonard, David | C6: 2
A7: 2010 | B7: McFadden, Sarah | C7: 5
A8: 2007 | B8: Munshausen, Bruce | C8: 3
A9: 2006 | B9: Nelson III, Shawn | C9: 3
A10: 2003 | B10: Thompson, Glenn | C10: 3
A11: 2011 | B11: Van Buskirk, Briañ | C11: 5
A12: 2012 | B12: Waguespack, Briañ | C12: 4
A13: 2013 | B13: Yokay, James | C13: 4
... A65: 2166 | B65: Tea, Green | C65: 4

Sheet Sheet4
A1: Emp Id | B1: User Name First | C1: User Name Last | D1: User Type | E1: Login Id | F1: Email Address | G1: User Password | H1: User Time Zone
A2: 0000000A1 | B2: Michael | C2: Gerthe | D2: Employee | E2: mgerthe | F2: mgerthe@dartican.com | G2: open | H2: North American Central
A3: 10003 | B3: Juan | C3: Garza | D3: Employee | E3: jgarza | F3: jgarza@dartican.com | G3: open | H3: North American Central
A4: 10007 | B4: Steven | C4: Kabak | D4: Employee | E4: skabak | F4: skabak@dartican.com | G4: open | H4: North American Central
A5: 10009 | B5: Stewart | C5: Byrne | D5: Employee | E5: sbyrne | F5: sbyrne@dartican.com | G5: open | H5: North American Central
A6: 10011 | B6: Katie | C6: Smith | D6: Employee | E6: ksmith | F6: ksmith@dartican.com | G6: open | H6: North American Central
A7: 10013 | B7: Edward | C7: Huang | D7: Employee | E7: ehuang | F7: ehuang@dartican.com | G7: open | H7: North American Central
A8: 10015 | B8: Manuel | C8: Amador | D8: Employee | E8: mamador | F8: mamador@dartican.com | G8: open | H8: North American Central
A9: 10019 | B9: Georgia | C9: Harrison | D9: Employee | E9: gharrison | F9: gharrison@dartican.com | G9: open | H9: North American Central
A10: 10020 | B10: Kerri | C10: Berndt | D10: Employee | E10: kberndt | F10: kberndt@dartican.com | G10: open | H10: North American Central
A11: 10030 | B11: Ed | C11: Zimny | D11: Employee | E11: ezimny | F11: ezimny@dartican.com | G11: open | H11: North American Central
A12: 10031 | B12: Bradley | C12: Smith | D12: Employee | E12: bsmith | F12: bsmith@dartican.com | G12: open
A13: 10032 | B13: Rob | C13: Feldman | D13: Employee | E13: rfeldman | F13: rfeldman@dartican.com | G13: open
A14: 10038 | B14: Mike | C14: Stanley | D14: Employee | E14: mstanley | F14: mstanley@dartican.com | G14: open
A15: 10039 | B15: Dianne | C15: Buschmann | D15: Employee | E15: dbuschmann | F15: dbuschmann@dartican.com | G15: open
A16: 10043 | B16: Cathy | C16: Bonwick | D16: Employee | E16: cbonwick | F16: cbonwick@dartican.com | G16: open
A17: 10045 | B17: Ray | C17: Liang | D17: Employee | E17: rliang | F17: rliang@dartican.com | G17: open
A18: 10046 | B18: Jimmy | C18: Shi | D18: Employee | E18: jshi | F18: jshi@dartican.com | G18: open
A19: 10048 | B19: Ye | C19: Song | D19: Employee | E19: ysong | F19: ysong@dartican.com | G19: open
A20: 10049 | B20: Geoffrey | C20: Gao | D20: Employee | E20: ggao | F20: ggao@dartican.com | G20: open
A21: 10052 | B21: Chaitanya | C21: Kancherla | D21: Employee | E21: ckancherla | F21: ckancherla@dartican.com | G21: open
A22: 10054 | B22: Robert | C22: Wright | D22: Employee | E22: rwright | F22: rwright@dartican.com | G22: open
A23: 10055 | B23: Alex | C23: Beynon | D23: Employee | E23: abeynon | F23: abeynon@dartican.com | G23: open
... A300: 11337 | B300: Aurang | C300: Khan | D300: Employee | E300: akhan | F300: akhan@dartican.com | G300: open

Sheet Sheet5

Sheet Sheet6

Sheet Employee Bonus Prepaid
A1: Emp Id | B1: Name | C1: Bonus Plan Name | D1: Bonus From Date | E1: OPA Rec'd $
A2: 2009 | B2: Grimm, Briañ | C2: B1 | E2: 100
A3: 2004 | B3: Janish, Betty | C3: B1 | E3: 100
A4: 2002 | B4: Keeling, Larry | C4: B1 | E4: 100
A5: 2008 | B5: Krendick, Jasoñ | C5: L3 | E5: 100
A6: 2005 | B6: Leonard, David | C6: B1 | E6: 100
A7: 2010 | B7: McFadden, Sarah | C7: B1 | E7: 100
A8: 2007 | B8: Munshausen, Bruce | C8: B2 | E8: 100
A9: 2006 | B9: Nelson III, Shawn | C9: B2 | E9: 100
A10: 2003 | B10: Thompson, Glenn | C10: B2 | E10: 100
A11: 2011 | B11: Van Buskirk, Briañ | C11: B2 | E11: 100
A12: 2012 | B12: Waguespack, Briañ | C12: B2 | E12: 100
A13: 2013 | B13: Yokay, James | C13: B2 | E13: 100
... A57: 166 | B57: Montana, Joe | C57: B1 | E57: 400
A58: 1012 | B58: Sherman, Jack | C58: B1 | E58: safida
A59: 1043 | B59: Burke, Michelle | C59: B1 | E59: 400
A60: 1114 | B60: Sampson, DeDe | C60: B1 | E60: 400
A61: 2168 | B61: Citrus, Susan | C61: B1 | E61: 400
A62: 2167 | B62: Flavors, Natural | C62: B1 | E62: 400
A63: 2000 | B63: Tompkins, Brian | C63: B1 | E63: 400
A64: 2001 | B64: Ward Jr, Lloyd | C64: B1 | E64: 400
A65: 2166 | B65: Tea, Green | C65: B1 | E65: 400
A66: 2166 | B66: Tea, Green | C66: B2 | E66: 400
I74: s

Sheet Employee Salary Actions
A1: Employee Id | B1: Name | C1: Promo Job Title | D1: Range Adj Inc Amt | E1: Lump Sum Amt | F1: Rec Merit Inc Amt | G1: Internal Equity Inc Amt | H1: Promo Eff Date | I1: Promo Inc Amt | J1: Promo Structure Item | K1: Market Adj Pct | L1: Other Inc Amt | M1: Comments | N1: Salary Plan User Def 2 | O1: Salary Plan User Def 1 Amt | P1: Promo Structure Name
A2: 2008 | B2: Krendick, Jasoñ | C2: Bookkeeper | D2: 500 | E2: 100 | F2: 1000 | G2: 500 | H2: 45292 | I2: 1000 | J2: E06 | K2: 0.1 | L2: 5000 | M2: Test | N2: white color | O2: 100 | P2: Exempt US
A3: 2005 | B3: Leonard David | C3: Development Manager | D3: 1000 | E3: 100 | F3: 2000 | G3: 1000 | H3: 45570 | I3: 2000 | J3: E06 | K3: 0.1 | L3: 6000 | M3: oct | N3: white color | O3: 100 | P3: Exempt US
A4: 2010 | B4: McFadden, Sarah | C4: Executive Administrative Assistant | D4: 1500 | E4: 100 | F4: 3000 | G4: 1500 | H4: 45354 | I4: 3000 | J4: E06 | K4: 0.2 | L4: 7000 | M4: salary note | N4: Black color | O4: 100 | P4: Exempt US
A5: 2007 | B5: Munshausen, Bruce | C5: Project Manager | D5: 2000 | E5: 300 | F5: 4000 | G5: 2000 | H5: 45355 | I5: 4000 | J5: E06 | K5: 0.3 | L5: 8000 | M5: A | N5: Green color | O5: 100 | P5: Exempt US
A6: 2006 | B6: Nelson III, Shawn | C6: Sr. Accountant | D6: 3000 | E6: 400 | F6: 5000 | G6: 3000 | H6: 45356 | I6: 5000 | J6: E08 | K6: 0.11 | L6: 9000 | M6: B | N6: red color | O6: 100 | P6: Exempt US
A7: 2003 | B7: Thompson, Glenn | C7: Human Resource Manager | D7: 4000 | E7: 500 | F7: 6000 | G7: 4000 | H7: 45357 | I7: 6000 | J7: E08 | K7: 0.15 | L7: 1000 | M7: C | N7: gray color | O7: 100 | P7: Exempt US
A8: 2011 | B8: Van Buskirk, Briañ | C8: Sales/Marketing Manager | D8: 5000 | E8: 600 | F8: 7000 | G8: 5000 | H8: 45358 | I8: 7000 | J8: E08 | K8: 0.16 | L8: 2000 | M8: D | N8: white color | O8: 100 | P8: Exempt US
A9: 2012 | B9: Waguespack, Briañ | C9: IT Manager | D9: 6000 | E9: 700 | F9: 8000 | G9: 6000 | H9: 45359 | I9: 8000 | J9: E24 | K9: 0.1 | L9: 3000 | M9: E | N9: white color | O9: 100 | P9: Exempt US
A10: 162 | B10: Thompson, Calvin | C10: IT Manager | D10: 6001 | E10: 701 | F10: 8001 | G10: 6001 | H10: 45360 | I10: 8000 | J10: E24 | K10: 1.1 | L10: 3001 | M10: E | N10: white color | O10: 101 | P10: Exempt US
A11: 1121 | B11: Masters, Sarah | C11: IT Manager | D11: 6002 | E11: 702 | F11: 8002 | G11: 6002 | H11: 45361 | I11: 8001 | J11: E24 | K11: 2.1 | L11: 3002 | M11: E | N11: white color | O11: 102 | P11: Exempt US
A12: 1117 | B12: Ramsey, Richele | C12: Human Resource Manager | D12: 6003 | E12: 703 | F12: 8003 | G12: 6003 | H12: 45362 | I12: 8002 | J12: E24 | K12: 3.1 | L12: 3003 | M12: E | N12: white color | O12: 103 | P12: Exempt US
A13: 1115 | B13: Ross, Michael | C13: Human Resource Manager | D13: 6004 | E13: 704 | F13: 8004 | G13: 6004 | H13: 45363 | I13: 8003 | J13: E28 | K13: 4.1 | L13: 3004 | M13: E | N13: white color | O13: 104 | P13: Exempt US
... A16: 70 | B16: Kirklan, Richard | C16: Human Resource Manager | D16: 6007 | E16: 707 | F16: 8007 | G16: 6007 | H16: 45366 | I16: 8006 | J16: E28 | K16: 7.1 | L16: 3007 | M16: E | N16: white color | O16: 107 | P16: Exempt US

Sheet Employee Salary Refresh
A1: Employee Id | B1: Name | C1: Starting Salary Amt | D1: Currency Code | E1: Budget Base Amt
A2: 2009 | B2: (Grimm, Briañ) | C2: 68000 | D2: AUD | E2: 1000
A3: 2004 | B3: Janish / Betty | C3: 70000 | D3: AUD | E3: 2000
A4: 2002 | B4: Keeling, Larry | C4: 80000 | D4: AUD | E4: 3000
A5: 2008 | B5: Krendick, Jasoñ | C5: 66000 | D5: AUD | E5: 4000
A6: 2005 | B6: Leonard, David | C6: 58000 | D6: AUD | E6: 4001
A7: 2010 | B7: McFadden, Sarah | C7: 60000 | D7: AUD | E7: 4002
A8: 2007 | B8: Munshausen, Bruce | C8: 70000 | D8: AUD | E8: 4003
A9: 2006 | B9: Nelson III, Shawn | C9: 48800 | D9: AUD | E9: 4004
A10: 2003 | B10: Thompson, Glenn | C10: 45750 | D10: AUD | E10: 4005
A11: 2011 | B11: Van Buskirk, Briañ | C11: 45750 | D11: AUD | E11: 4006
A12: 2012 | B12: Waguespack, Briañ | C12: 91500 | D12: CAD | E12: 4007
A13: 2013 | B13: Yokay, James | C13: 91500 | D13: CAD | E13: 4008
... A19: 111 | B19: Galvan, Dina | C19: 18720.01 | D19: USD | E19: 4014
A20: 110 | B20: Harrison, Cindy | C20: 12474.01 | D20: USD
A21: 95 | B21: Henshaw, Candice | C21: 18600 | D21: IDR
A22: 80 | B22: Jackson, Charmain | C22: 30125.48 | D22: IDR
A23: 115 | B23: Mathers, Paula | C23: 14757.04 | D23: IDR
A24: 93 | B24: Mott, Michael | C24: 17825.95 | D24: IDR
A25: 101 | B25: Napier, Alex | C25: 15010.12 | D25: IDR
A26: 100 | B26: Rames, Bill | C26: 11987.99 | D26: IDR
A27: 104 | B27: Risner, Elizabeth | C27: 16640.21 | D27: IDR
A28: 86 | B28: Rogers, Mary | C28: 68124.33 | D28: IDR
A29: 89 | B29: White, Gordon | C29: 37845.02 | D29: IDR
A30: 72 | B30: Davis, Beverly | C30: 159017.24 | D30: AED
A31: 162 | B31: Thompson, Calvin | C31: 321512.21 | D31: AED
... A65: 2166 | B65: Tea, Green | C65: 205000 | D65: USD

Sheet Employee Bonus Plansok
A1: Emp Id | B1: Name | C1: Bonus Plan Name | D1: Bonus Calculation Base Amt | E1: Currency | F1: Bonus From Date | G1: Bonus To Date | H1: Prorated Bonus Mult Pct | I1: Tgt Opp Pct | J1: Tgt Opp Amt | K1: Bonus Guar Min Amt | L1: Bonus Guideline Min Amt | M1: Bonus Guideline Tgt Amt | N1: Bonus Guideline Max Amt | O1: Prepaid Amt | P1: Aziz Hair color | Q1: Bonus User Def 1 Amt | R1: Job Title
A2: 2002 | B2: Keeling, Larry | C2: B1 | D2: 100000 | E2: AED | H2: 1 | I2: 0.1 | J2: 10000 | P2: White | Q2: 12 | R2: Software engineer/XXXX
A3: 2008 | B3: Krendick, Jasoñ | C3: B1 | D3: 100000 | E3: AED | H3: 1 | I3: 0.1 | J3: 10000 | P3: White | Q3: 13 | R3: Software engineer/XXXX
A4: 2005 | B4: Leonard, David | C4: B1 | D4: 100000 | E4: AED | H4: 1 | I4: 0.1 | J4: 10000 | P4: White | Q4: 14 | R4: Software engineer/XXXX
A5: 2010 | B5: McFadden, Sarah | C5: B1 | D5: 100000 | E5: AED | H5: 1 | I5: 0.1 | J5: 10000 | P5: White | Q5: 15 | R5: Software engineer/XXXX
A6: 2007 | B6: Munshausen, Bruce | C6: B2 | D6: 100000 | E6: AED | H6: 1 | J6: s | L6: 5000 | M6: 10000 | N6: 25000 | O6: 6000 | P6: White | Q6: 16 | R6: Software engineer/XXXX
A7: 2006 | B7: Nelson III, Shawn | C7: B2 | D7: 100000 | E7: AED | H7: 1 | J7: 20000 | K7: 25000 | L7: 5000 | M7: 10000 | N7: 25000 | P7: White | Q7: 17 | R7: Software engineer/XXXX
A8: 2003 | B8: Thompson, Glenn | C8: B2 | D8: 100000 | E8: USD | H8: 1 | J8: 20000 | L8: 5000 | M8: 10000 | N8: 25000 | P8: White | Q8: 18 | R8: Software engineer/XXXX

Sheet Employee Salary History
A1: Emp Id | B1: Name | C1: Action Date | D1: Action Type | E1: Annual Increase Amt | F1: Annual Increase Pct | G1: Currency Code
A2: 59 | B2: Sanders \ Lynn | C2: 40634 | D2: Merit | E2: 239.60636 | F2: 0.02 | G2: USD
A3: 59 | B3: Sanders, Lynn | C3: 40252 | D3: Merit | E3: 234.9082 | F3: 0.02 | G3: USD
A4: 59 | B4: Sanders, Lynn | C4: 40252 | D4: Is LumpSum | E4: 234.9082 | F4: 0.02 | G4: USD
A5: 59 | B5: Sanders, Lynn | C5: 40252 | D5: Is LumpSum | E5: 234.9082 | F5: 0.02 | G5: USD
A6: 59 | B6: Sanders, Lynn | C6: 40252 | D6: Is LumpSum | E6: 800.5 | F6: 0.02 | G6: USD
A7: 59 | B7: Sanders, Lynn | C7: 40617 | D7: Is Other | E7: 234.9082 | F7: 0.02 | G7: USD
A8: 59 | B8: Sanders, Lynn | C8: 40617 | D8: Is Other | E8: 356.23 | F8: 0.02 | G8: USD
A9: 70 | B9: Kirklan, Richard | C9: 40634 | D9: Merit | E9: 356.23 | F9: 0.02 | G9: USD
A10: 70 | B10: Kirklan, Richard | C10: 40252 | D10: Merit | E10: 240.9022 | F10: 0.02 | G10: USD
A11: 72 | B11: Davis, Beverly | C11: 40634 | D11: Merit | E11: 1606.0741 | F11: 0.01 | G11: USD | H11: S
A12: 72 | B12: Davis, Beverly | C12: 40252 | D12: Merit | E12: 1590.1724 | F12: 0.01 | G12: USD
A13: 73 | B13: Bonamy, James | C13: 40634 | D13: Merit | E13: 1143.8251 | F13: 0.01 | G13: USD
A14: 73 | B14: Bonamy, James | C14: 40252 | D14: Merit | E14: 1132.5001 | F14: 0.01 | G14: USD
A15: 80 | B15: Jackson, Charmain | C15: 40634 | D15: Merit | E15: 1915.9805 | F15: 0.06 | G15: USD
A16: 80 | B16: Jackson, Charmain | C16: 40252 | D16: Merit | E16: 1807.5288 | F16: 0.06 | G16: USD
A17: 86 | B17: Rogers, Mary | C17: 40634 | D17: Merit | E17: 1389.7363 | F17: 0.02 | G17: USD
A18: 86 | B18: Rogers, Mary | C18: 40252 | D18: Merit | E18: 1362.4866 | F18: 0.02 | G18: USD
A19: 88 | B19: Brooks, Wendy | C19: 40634 | D19: Merit | E19: 85.408288 | F19: 0.0025 | G19: USD
A20: 88 | B20: Brooks, Wendy | C20: 40252 | D20: Merit | E20: 85.1953 | F20: 0.0025 | G20: USD
A21: 89 | B21: White, Gordon | C21: 40634 | D21: Merit | E21: 382.2347 | F21: 0.01 | G21: USD
A22: 89 | B22: White, Gordon | C22: 40252 | D22: Merit | E22: 378.4502 | F22: 0.01 | G22: USD
A23: 91 | B23: Brown, Leann | C23: 40634 | D23: Merit | E23: 192.15381 | F23: 0.01 | G23: USD
... A143: 2168 | B143: Citrus, Susan | C143: 40252 | D143: Merit | E143: 10740 | F143: 0.12 | G143: USD

Sheet Employee Bonus History
B1: Emp Id | C1: Name | D1: Bonus Plan Name | E1: Tgt Amount | F1: Tgt Pct | G1: Payout Date | H1: Corp Mult Pct | I1: Bonus Amount | J1: Bonus Pct | K1: Currency Code | L1: Bonus Hist User Def 1 | M1: Bonus Hist User Def 2 | N1: Bonus Hist User Def 3 | O1: Bonus Hist User Def 4 | P1: Bonus Hist User Def 5
A2: =ISEVEN(ROW()) -> TRUE | B2: 59 | C2: Sanders \ Lynn | D2: B1 | E2: 9000 | F2: 0.09 | G2: 43905 | H2: 1.1 | I2: =E2*H2 -> 9900 | J2: 0.09 | K2: USD | L2: BH UD 1 | M2: BH UD 2 | N2: BH UD 3 | O2: BH UD 4 | P2: BH UD 5
A3: =ISEVEN(ROW()) -> FALSE | B3: 59 | C3: Sanders, Lynn | D3: B2 | E3: 9000 | F3: 0.09 | G3: 43905 | H3: 1.1 | I3: =E3*H3 -> 9900 | J3: 0.09 | K3: USD | L3: BH UD 1 | M3: BH UD 2 | N3: BH UD 3 | O3: BH UD 4 | P3: BH UD 5
A4: =ISEVEN(ROW()) -> TRUE | B4: 59 | C4: Sanders, Lynn | D4: B2 | E4: 8000 | F4: 0.08 | G4: 44271 | H4: 95 | I4: 7600 | J4: 0.095 | K4: USD | L4: BH UD 1 | M4: BH UD 2 | N4: BH UD 3 | O4: BH UD 4 | P4: BH UD 5
A5: =ISEVEN(ROW()) -> FALSE | B5: 59 | C5: Sanders, Lynn | D5: B2 | E5: 8000 | F5: 0.08 | G5: 47923 | H5: 95 | I5: 7600 | J5: 0.095 | K5: USD | L5: BH UD 1 | M5: BH UD 2 | N5: BH UD 3 | O5: BH UD 4 | P5: BH UD 5
A6: =ISEVEN(ROW()) -> TRUE | B6: 70 | C6: Kirklan, Richard | D6: B1 | E6: 9000 | F6: 0.09 | G6: 43905 | H6: 1.1 | I6: =E6*H6 -> 9900 | J6: 0.09 | K6: USD | L6: BH UD 1 | M6: BH UD 2 | N6: BH UD 3 | O6: BH UD 4 | P6: BH UD 5
A7: =ISEVEN(ROW()) -> FALSE | B7: 70 | C7: Kirklan, Richard | D7: B1 | E7: 8000 | F7: 0.08 | G7: 44271 | H7: 95 | I7: 7600 | J7: 0.095 | K7: USD | L7: BH UD 1 | M7: BH UD 2 | N7: BH UD 3 | O7: BH UD 4 | P7: BH UD 5
A8: =ISEVEN(ROW()) -> TRUE | B8: 72 | C8: Davis, Beverly | D8: B1 | E8: 9000 | F8: 0.09 | G8: 43905 | H8: 95 | I8: =E8*H8 -> 855000 | J8: 0.09 | K8: USD | L8: BH UD 1 | M8: BH UD 2 | N8: BH UD 3 | O8: BH UD 4 | P8: BH UD 5
A9: =ISEVEN(ROW()) -> FALSE | B9: 72 | C9: Davis, Beverly | D9: B1 | E9: 8000 | F9: 0.08 | G9: 44271 | H9: 95 | I9: 7600 | J9: 0.095 | K9: USD | L9: BH UD 1 | M9: BH UD 2 | N9: BH UD 3 | O9: BH UD 4 | P9: BH UD 5
A10: =ISEVEN(ROW()) -> TRUE | B10: 73 | C10: Bonamy, James | D10: B1 | E10: 9000 | F10: 0.09 | G10: 43905 | H10: 1.1 | I10: =E10*H10 -> 9900 | J10: 0.09 | K10: USD | L10: BH UD 1 | M10: BH UD 2 | N10: BH UD 3 | O10: BH UD 4 | P10: BH UD 5
A11: =ISEVEN(ROW()) -> FALSE | B11: 73 | C11: Bonamy, James | D11: B1 | E11: 8000 | F11: 0.08 | G11: 44271 | H11: 95 | I11: 7600 | J11: 0.095 | K11: USD | L11: BH UD 1 | M11: BH UD 2 | N11: BH UD 3 | O11: BH UD 4 | P11: BH UD 5
A12: =ISEVEN(ROW()) -> TRUE | B12: 80 | C12: Jackson, Charmain | D12: B1 | E12: 9000 | F12: 0.09 | G12: 43905 | H12: 1.1 | I12: =E12*H12 -> 9900 | J12: 0.09 | K12: USD | L12: BH UD 1 | M12: BH UD 2 | N12: BH UD 3 | O12: BH UD 4 | P12: BH UD 5
A13: =ISEVEN(ROW()) -> FALSE | B13: 80 | C13: Jackson, Charmain | D13: B1 | E13: 8000 | F13: 0.08 | G13: 44271 | H13: 95 | I13: 7600 | J13: 0.095 | K13: USD | L13: BH UD 1 | M13: BH UD 2 | N13: BH UD 3 | O13: BH UD 4 | P13: BH UD 5
A14: =ISEVEN(ROW()) -> TRUE | B14: 86 | C14: Rogers, Mary | D14: B1 | E14: 9000 | F14: 0.09 | G14: 43905 | H14: 1.1 | I14: =E14*H14 -> 9900 | J14: 0.09 | K14: USD | L14: BH UD 1 | M14: BH UD 2 | N14: BH UD 3 | O14: BH UD 4 | P14: BH UD 5
A15: =ISEVEN(ROW()) -> FALSE | B15: 86 | C15: Rogers, Mary | D15: B1 | E15: 8000 | F15: 0.08 | G15: 44271 | H15: 95 | I15: 7600 | J15: 0.095 | K15: USD | L15: BH UD 1 | M15: BH UD 2 | N15: BH UD 3 | O15: BH UD 4 | P15: BH UD 5
A16: =ISEVEN(ROW()) -> TRUE | B16: 88 | C16: Brooks, Wendy | D16: B1 | E16: 9000 | F16: 0.09 | G16: 43905 | H16: 1.1 | I16: =E16*H16 -> 9900 | J16: 0.09 | K16: USD | L16: BH UD 1 | M16: BH UD 2 | N16: BH UD 3 | O16: BH UD 4 | P16: BH UD 5
A17: =ISEVEN(ROW()) -> FALSE | B17: 88 | C17: Brooks, Wendy | D17: B1 | E17: 8000 | F17: 0.08 | G17: 44271 | H17: 95 | I17: 7600 | J17: 0.095 | K17: USD | L17: BH UD 1 | M17: BH UD 2 | N17: BH UD 3 | O17: BH UD 4 | P17: BH UD 5
A18: =ISEVEN(ROW()) -> TRUE | B18: 89 | C18: White, Gordon | D18: B1 | E18: 9000 | F18: 0.09 | G18: 43905 | H18: 1.1 | I18: =E18*H18 -> 9900 | J18: 0.09 | K18: USD | L18: BH UD 1 | M18: BH UD 2 | N18: BH UD 3 | O18: BH UD 4 | P18: BH UD 5
A19: =ISEVEN(ROW()) -> FALSE | B19: 89 | C19: White, Gordon | D19: B1 | E19: 8000 | F19: 0.08 | G19: 44271 | H19: 95 | I19: 7600 | J19: 0.095 | K19: USD | L19: BH UD 1 | M19: BH UD 2 | N19: BH UD 3 | O19: BH UD 4 | P19: BH UD 5
A20: =ISEVEN(ROW()) -> TRUE | B20: 91 | C20: Brown, Leann | D20: B1 | E20: 9000 | F20: 0.09 | G20: 43905 | H20: 1.1 | I20: =E20*H20 -> 9900 | J20: 0.09 | K20: USD | L20: BH UD 1 | M20: BH UD 2 | N20: BH UD 3 | O20: BH UD 4 | P20: BH UD 5
A21: =ISEVEN(ROW()) -> FALSE | B21: 91 | C21: Brown, Leann | D21: B1 | E21: 8000 | F21: 0.08 | G21: 44271 | H21: 95 | I21: 7600 | J21: 0.095 | K21: USD | L21: BH UD 1 | M21: BH UD 2 | N21: BH UD 3 | O21: BH UD 4 | P21: BH UD 5
A22: =ISEVEN(ROW()) -> TRUE | B22: 92 | C22: Craven, Liz | D22: B1 | E22: 9000 | F22: 0.09 | G22: 43905 | H22: 1.1 | I22: =E22*H22 -> 9900 | J22: 0.09 | K22: USD | L22: BH UD 1 | M22: BH UD 2 | N22: BH UD 3 | O22: BH UD 4 | P22: BH UD 5
A23: =ISEVEN(ROW()) -> FALSE | B23: 92 | C23: Craven, Liz | D23: B1 | E23: 8000 | F23: 0.08 | G23: 44271 | H23: 95 | I23: 7600 | J23: 0.095 | K23: USD | L23: BH UD 1 | M23: BH UD 2 | N23: BH UD 3 | O23: BH UD 4 | P23: BH UD 5
A24: =ISEVEN(ROW()) -> TRUE | B24: 93 | C24: Mott, Michael | D24: B1 | E24: 9000 | F24: 0.09 | G24: 43905 | H24: 1.1 | I24: =E24*H24 -> 9900 | J24: 0.09 | K24: USD | L24: BH UD 1 | M24: BH UD 2 | N24: BH UD 3 | O24: BH UD 4 | P24: BH UD 5
A25: =ISEVEN(ROW()) -> FALSE | B25: 93 | C25: Mott, Michael | D25: B1 | E25: 8000 | F25: 0.08 | G25: 44271 | H25: 95 | I25: 7600 | J25: 0.095 | K25: USD | L25: BH UD 1 | M25: BH UD 2 | N25: BH UD 3 | O25: BH UD 4 | P25: BH UD 5
A26: =ISEVEN(ROW()) -> TRUE | B26: 94 | C26: Atkinson, Tracey | D26: B1 | E26: 9000 | F26: 0.09 | G26: 43905 | H26: 1.1 | I26: =E26*H26 -> 9900 | J26: 0.09 | K26: USD | L26: BH UD 1 | M26: BH UD 2 | N26: BH UD 3 | O26: BH UD 4 | P26: BH UD 5
A27: =ISEVEN(ROW()) -> FALSE | B27: 94 | C27: Atkinson, Tracey | D27: B1 | E27: 8000 | F27: 0.08 | G27: 44271 | H27: 95 | I27: 7600 | J27: 0.095 | K27: USD | L27: BH UD 1 | M27: BH UD 2 | N27: BH UD 3 | O27: BH UD 4 | P27: BH UD 5
A28: =ISEVEN(ROW()) -> TRUE | B28: 95 | C28: Henshaw, Candice | D28: B1 | E28: 9000 | F28: 0.09 | G28: 43905 | H28: 1.1 | I28: =E28*H28 -> 9900 | J28: 0.09 | K28: USD | L28: BH UD 1 | M28: BH UD 2 | N28: BH UD 3 | O28: BH UD 4 | P28: BH UD 5
A29: =ISEVEN(ROW()) -> FALSE | B29: 95 | C29: Henshaw, Candice | D29: B1 | E29: 8000 | F29: 0.08 | G29: 44271 | H29: 95 | I29: 7600 | J29: 0.095 | K29: USD | L29: BH UD 1 | M29: BH UD 2 | N29: BH UD 3 | O29: BH UD 4 | P29: BH UD 5
A30: =ISEVEN(ROW()) -> TRUE | B30: 100 | C30: Rames, Bill | D30: B1 | E30: 9000 | F30: 0.09 | G30: 43905 | H30: 1.1 | I30: =E30*H30 -> 9900 | J30: 0.09 | K30: USD | L30: BH UD 1 | M30: BH UD 2 | N30: BH UD 3 | O30: BH UD 4 | P30: BH UD 5
A31: =ISEVEN(ROW()) -> FALSE | B31: 100 | C31: Rames, Bill | D31: B1 | E31: 8000 | F31: 0.08 | G31: 44271 | H31: 95 | I31: 7600 | J31: 0.095 | K31: USD | L31: BH UD 1 | M31: BH UD 2 | N31: BH UD 3 | O31: BH UD 4 | P31: BH UD 5
A32: =ISEVEN(ROW()) -> TRUE | B32: 101 | C32: Napier, Alex | D32: B1 | E32: 9000 | F32: 0.09 | G32: 43905 | H32: 1.1 | I32: =E32*H32 -> 9900 | J32: 0.09 | K32: USD | L32: BH UD 1 | M32: BH UD 2 | N32: BH UD 3 | O32: BH UD 4 | P32: BH UD 5
A33: =ISEVEN(ROW()) -> FALSE | B33: 101 | C33: Napier, Alex | D33: B1 | E33: 8000 | F33: 0.08 | G33: 44271 | H33: 95 | I33: 7600 | J33: 0.095 | K33: USD | L33: BH UD 1 | M33: BH UD 2 | N33: BH UD 3 | O33: BH UD 4 | P33: BH UD 5
A34: =ISEVEN(ROW()) -> TRUE | B34: 104 | C34: Risner, Elizabeth | D34: B1 | E34: 9000 | F34: 0.09 | G34: 43905 | H34: 1.1 | I34: =E34*H34 -> 9900 | J34: 0.09 | K34: USD | L34: BH UD 1 | M34: BH UD 2 | N34: BH UD 3 | O34: BH UD 4 | P34: BH UD 5
A35: =ISEVEN(ROW()) -> FALSE | B35: 104 | C35: Risner, Elizabeth | D35: B1 | E35: 8000 | F35: 0.08 | G35: 44271 | H35: 95 | I35: 7600 | J35: 0.095 | K35: USD | L35: BH UD 1 | M35: BH UD 2 | N35: BH UD 3 | O35: BH UD 4 | P35: BH UD 5
A36: =ISEVEN(ROW()) -> TRUE | B36: 110 | C36: Harrison, Cindy | D36: B1 | E36: 9000 | F36: 0.09 | G36: 43905 | H36: 1.1 | I36: =E36*H36 -> 9900 | J36: 0.09 | K36: USD | L36: BH UD 1 | M36: BH UD 2 | N36: BH UD 3 | O36: BH UD 4 | P36: BH UD 5
A37: =ISEVEN(ROW()) -> FALSE | B37: 110 | C37: Harrison, Cindy | D37: B1 | E37: 8000 | F37: 0.08 | G37: 44271 | H37: 95 | I37: 7600 | J37: 0.095 | K37: USD | L37: BH UD 1 | M37: BH UD 2 | N37: BH UD 3 | O37: BH UD 4 | P37: BH UD 5
A38: =ISEVEN(ROW()) -> TRUE | B38: 111 | C38: Galvan, Dina | D38: B1 | E38: 9000 | F38: 0.09 | G38: 43905 | H38: 1.1 | I38: =E38*H38 -> 9900 | J38: 0.09 | K38: USD | L38: BH UD 1 | M38: BH UD 2 | N38: BH UD 3 | O38: BH UD 4 | P38: BH UD 5
A39: =ISEVEN(ROW()) -> FALSE | B39: 111 | C39: Galvan, Dina | D39: B1 | E39: 8000 | F39: 0.08 | G39: 44271 | H39: 95 | I39: 7600 | J39: 0.095 | K39: USD | L39: BH UD 1 | M39: BH UD 2 | N39: BH UD 3 | O39: BH UD 4 | P39: BH UD 5
A40: =ISEVEN(ROW()) -> TRUE | B40: 115 | C40: Mathers, Paula | D40: B1 | E40: 9000 | F40: 0.09 | G40: 43905 | H40: 1.1 | I40: =E40*H40 -> 9900 | J40: 0.09 | K40: USD | L40: BH UD 1 | M40: BH UD 2 | N40: BH UD 3 | O40: BH UD 4 | P40: BH UD 5
A41: =ISEVEN(ROW()) -> FALSE | B41: 115 | C41: Mathers, Paula | D41: B1 | E41: 8000 | F41: 0.08 | G41: 44271 | H41: 95 | I41: 7600 | J41: 0.095 | K41: USD | L41: BH UD 1 | M41: BH UD 2 | N41: BH UD 3 | O41: BH UD 4 | P41: BH UD 5
A42: =ISEVEN(ROW()) -> TRUE | B42: 161 | C42: Butler, Cathy | D42: B1 | E42: 9000 | F42: 0.09 | G42: 43905 | H42: 1.1 | I42: =E42*H42 -> 9900 | J42: 0.09 | K42: USD | L42: BH UD 1 | M42: BH UD 2 | N42: BH UD 3 | O42: BH UD 4 | P42: BH UD 5
A43: =ISEVEN(ROW()) -> FALSE | B43: 161 | C43: Butler, Cathy | D43: B1 | E43: 8000 | F43: 0.08 | G43: 44271 | H43: 95 | I43: 7600 | J43: 0.095 | K43: USD | L43: BH UD 1 | M43: BH UD 2 | N43: BH UD 3 | O43: BH UD 4 | P43: BH UD 5
A44: =ISEVEN(ROW()) -> TRUE | B44: 162 | C44: Thompson, Calvin | D44: B1 | E44: 9000 | F44: 0.09 | G44: 43905 | H44: 1.1 | I44: =E44*H44 -> 9900 | J44: 0.09 | K44: USD | L44: BH UD 1 | M44: BH UD 2 | N44: BH UD 3 | O44: BH UD 4 | P44: BH UD 5
A45: =ISEVEN(ROW()) -> FALSE | B45: 162 | C45: Thompson, Calvin | D45: B1 | E45: 8000 | F45: 0.08 | G45: 44271 | H45: 95 | I45: 7600 | J45: 0.095 | K45: USD | L45: BH UD 1 | M45: BH UD 2 | N45: BH UD 3 | O45: BH UD 4 | P45: BH UD 5
A46: =ISEVEN(ROW()) -> TRUE | B46: 166 | C46: Montana, Joe | D46: B1 | E46: 9000 | F46: 0.09 | G46: 43905 | H46: 1.1 | I46: =E46*H46 -> 9900 | J46: 0.09 | K46: USD | L46: BH UD 1 | M46: BH UD 2 | N46: BH UD 3 | O46: BH UD 4 | P46: BH UD 5
A47: =ISEVEN(ROW()) -> FALSE | B47: 166 | C47: Montana, Joe | D47: B1 | E47: 8000 | F47: 0.08 | G47: 44271 | H47: 95 | I47: 7600 | J47: 0.095 | K47: USD | L47: BH UD 1 | M47: BH UD 2 | N47: BH UD 3 | O47: BH UD 4 | P47: BH UD 5
A48: =ISEVEN(ROW()) -> TRUE | B48: 167 | C48: Ramos, Amy | D48: B1 | E48: 9000 | F48: 0.09 | G48: 43905 | H48: 1.1 | I48: =E48*H48 -> 9900 | J48: 0.09 | K48: USD | L48: BH UD 1 | M48: BH UD 2 | N48: BH UD 3 | O48: BH UD 4 | P48: BH UD 5
A49: =ISEVEN(ROW()) -> FALSE | B49: 167 | C49: Ramos, Amy | D49: B1 | E49: 8000 | F49: 0.08 | G49: 44271 | H49: 95 | I49: 7600 | J49: 0.095 | K49: USD | L49: BH UD 1 | M49: BH UD 2 | N49: BH UD 3 | O49: BH UD 4 | P49: BH UD 5
A50: =ISEVEN(ROW()) -> TRUE | B50: 168 | C50: Soles, Nedra | D50: B1 | E50: 9000 | F50: 0.09 | G50: 43905 | H50: 1.1 | I50: =E50*H50 -> 9900 | J50: 0.09 | K50: USD | L50: BH UD 1 | M50: BH UD 2 | N50: BH UD 3 | O50: BH UD 4 | P50: BH UD 5
A51: =ISEVEN(ROW()) -> FALSE | B51: 168 | C51: Soles, Nedra | D51: B1 | E51: 8000 | F51: 0.08 | G51: 44271 | H51: 95 | I51: 7600 | J51: 0.095 | K51: USD | L51: BH UD 1 | M51: BH UD 2 | N51: BH UD 3 | O51: BH UD 4 | P51: BH UD 5
A52: =ISEVEN(ROW()) -> TRUE | B52: 170 | C52: Carter, Frank | D52: B1 | E52: 9000 | F52: 0.09 | G52: 43905 | H52: 1.1 | I52: =E52*H52 -> 9900 | J52: 0.09 | K52: USD | L52: BH UD 1 | M52: BH UD 2 | N52: BH UD 3 | O52: BH UD 4 | P52: BH UD 5
A53: =ISEVEN(ROW()) -> FALSE | B53: 170 | C53: Carter, Frank | D53: B1 | E53: 8000 | F53: 0.08 | G53: 44271 | H53: 95 | I53: 7600 | J53: 0.095 | K53: USD | L53: BH UD 1 | M53: BH UD 2 | N53: BH UD 3 | O53: BH UD 4 | P53: BH UD 5
A54: =ISEVEN(ROW()) -> TRUE | B54: 172 | C54: Burke, Mia | D54: B1 | E54: 9000 | F54: 0.09 | G54: 43905 | H54: 1.1 | I54: =E54*H54 -> 9900 | J54: 0.09 | K54: USD | L54: BH UD 1 | M54: BH UD 2 | N54: BH UD 3 | O54: BH UD 4 | P54: BH UD 5
A55: =ISEVEN(ROW()) -> FALSE | B55: 172 | C55: Burke, Mia | D55: B1 | E55: 8000 | F55: 0.08 | G55: 44271 | H55: 95 | I55: 7600 | J55: 0.095 | K55: USD | L55: BH UD 1 | M55: BH UD 2 | N55: BH UD 3 | O55: BH UD 4 | P55: BH UD 5
A56: =ISEVEN(ROW()) -> TRUE | B56: 174 | C56: Carillo, Frank | D56: B1 | E56: 9000 | F56: 0.09 | G56: 43905 | H56: 1.1 | I56: =E56*H56 -> 9900 | J56: 0.09 | K56: USD | L56: BH UD 1 | M56: BH UD 2 | N56: BH UD 3 | O56: BH UD 4 | P56: BH UD 5
A57: =ISEVEN(ROW()) -> FALSE | B57: 174 | C57: Carillo, Frank | D57: B1 | E57: 8000 | F57: 0.08 | G57: 44271 | H57: 95 | I57: 7600 | J57: 0.095 | K57: USD | L57: BH UD 1 | M57: BH UD 2 | N57: BH UD 3 | O57: BH UD 4 | P57: BH UD 5
A58: =ISEVEN(ROW()) -> TRUE | B58: 175 | C58: Anderson, Ann | D58: B1 | E58: 9000 | F58: 0.09 | G58: 43905 | H58: 1.1 | I58: =E58*H58 -> 9900 | J58: 0.09 | K58: USD | L58: BH UD 1 | M58: BH UD 2 | N58: BH UD 3 | O58: BH UD 4 | P58: BH UD 5
A59: =ISEVEN(ROW()) -> FALSE | B59: 175 | C59: Anderson, Ann | D59: B1 | E59: 8000 | F59: 0.08 | G59: 44271 | H59: 95 | I59: 7600 | J59: 0.095 | K59: USD | L59: BH UD 1 | M59: BH UD 2 | N59: BH UD 3 | O59: BH UD 4 | P59: BH UD 5
A60: =ISEVEN(ROW()) -> TRUE | B60: 176 | C60: Bishop, Julie | D60: B1 | E60: 9000 | F60: 0.09 | G60: 43905 | H60: 1.1 | I60: =E60*H60 -> 9900 | J60: 0.09 | K60: USD | L60: BH UD 1 | M60: BH UD 2 | N60: BH UD 3 | O60: BH UD 4 | P60: BH UD 5
A61: =ISEVEN(ROW()) -> FALSE | B61: 176 | C61: Bishop, Julie | D61: B1 | E61: 8000 | F61: 0.08 | G61: 44271 | H61: 95 | I61: 7600 | J61: 0.095 | K61: USD | L61: BH UD 1 | M61: BH UD 2 | N61: BH UD 3 | O61: BH UD 4 | P61: BH UD 5
A62: =ISEVEN(ROW()) -> TRUE | B62: 177 | C62: Pope, Ian | D62: B1 | E62: 9000 | F62: 0.09 | G62: 43905 | H62: 1.1 | I62: =E62*H62 -> 9900 | J62: 0.09 | K62: USD | L62: BH UD 1 | M62: BH UD 2 | N62: BH UD 3 | O62: BH UD 4 | P62: BH UD 5
A63: =ISEVEN(ROW()) -> FALSE | B63: 177 | C63: Pope, Ian | D63: B1 | E63: 8000 | F63: 0.08 | G63: 44271 | H63: 95 | I63: 7600 | J63: 0.095 | K63: USD | L63: BH UD 1 | M63: BH UD 2 | N63: BH UD 3 | O63: BH UD 4 | P63: BH UD 5
A64: =ISEVEN(ROW()) -> TRUE | B64: 1010 | C64: Tucker, Darla | D64: B1 | E64: 9000 | F64: 0.09 | G64: 43905 | H64: 1.1 | I64: =E64*H64 -> 9900 | J64: 0.09 | K64: USD | L64: BH UD 1 | M64: BH UD 2 | N64: BH UD 3 | O64: BH UD 4 | P64: BH UD 5
A65: =ISEVEN(ROW()) -> FALSE | B65: 1010 | C65: Tucker, Darla | D65: B1 | E65: 8000 | F65: 0.08 | G65: 44271 | H65: 95 | I65: 7600 | J65: 0.095 | K65: USD | L65: BH UD 1 | M65: BH UD 2 | N65: BH UD 3 | O65: BH UD 4 | P65: BH UD 5
A66: =ISEVEN(ROW()) -> TRUE | B66: 1012 | C66: Sherman, Jack | D66: B1 | E66: 9000 | F66: 0.09 | G66: 43905 | H66: 1.1 | I66: =E66*H66 -> 9900 | J66: 0.09 | K66: USD | L66: BH UD 1 | M66: BH UD 2 | N66: BH UD 3 | O66: BH UD 4 | P66: BH UD 5
A67: =ISEVEN(ROW()) -> FALSE | B67: 1012 | C67: Sherman, Jack | D67: B1 | E67: 8000 | F67: 0.08 | G67: 44271 | H67: 95 | I67: 7600 | J67: 0.095 | K67: USD | L67: BH UD 1 | M67: BH UD 2 | N67: BH UD 3 | O67: BH UD 4 | P67: BH UD 5
A68: =ISEVEN(ROW()) -> TRUE | B68: 1028 | C68: Resendez, MiMi | D68: B1 | E68: 9000 | F68: 0.09 | G68: 43905 | H68: 1.1 | I68: =E68*H68 -> 9900 | J68: 0.09 | K68: USD | L68: BH UD 1 | M68: BH UD 2 | N68: BH UD 3 | O68: BH UD 4 | P68: BH UD 5
A69: =ISEVEN(ROW()) -> FALSE | B69: 1028 | C69: Resendez, MiMi | D69: B1 | E69: 8000 | F69: 0.08 | G69: 44271 | H69: 95 | I69: 7600 | J69: 0.095 | K69: USD | L69: BH UD 1 | M69: BH UD 2 | N69: BH UD 3 | O69: BH UD 4 | P69: BH UD 5
A70: =ISEVEN(ROW()) -> TRUE | B70: 1043 | C70: Burke, Michelle | D70: B1 | E70: 9000 | F70: 0.09 | G70: 43905 | H70: 1.1 | I70: =E70*H70 -> 9900 | J70: 0.09 | K70: USD | L70: BH UD 1 | M70: BH UD 2 | N70: BH UD 3 | O70: BH UD 4 | P70: BH UD 5
A71: =ISEVEN(ROW()) -> FALSE | B71: 1043 | C71: Burke, Michelle | D71: B1 | E71: 8000 | F71: 0.08 | G71: 44271 | H71: 95 | I71: 7600 | J71: 0.095 | K71: USD | L71: BH UD 1 | M71: BH UD 2 | N71: BH UD 3 | O71: BH UD 4 | P71: BH UD 5
A72: =ISEVEN(ROW()) -> TRUE | B72: 1113 | C72: Duncan, Sam | D72: B1 | E72: 9000 | F72: 0.09 | G72: 43905 | H72: 1.1 | I72: =E72*H72 -> 9900 | J72: 0.09 | K72: USD | L72: BH UD 1 | M72: BH UD 2 | N72: BH UD 3 | O72: BH UD 4 | P72: BH UD 5
A73: =ISEVEN(ROW()) -> FALSE | B73: 1113 | C73: Duncan, Sam | D73: B1 | E73: 8000 | F73: 0.08 | G73: 44271 | H73: 95 | I73: 7600 | J73: 0.095 | K73: USD | L73: BH UD 1 | M73: BH UD 2 | N73: BH UD 3 | O73: BH UD 4 | P73: BH UD 5
A74: =ISEVEN(ROW()) -> TRUE | B74: 1114 | C74: Sampson, DeDe | D74: B1 | E74: 9000 | F74: 0.09 | G74: 43905 | H74: 1.1 | I74: =E74*H74 -> 9900 | J74: 0.09 | K74: USD | L74: BH UD 1 | M74: BH UD 2 | N74: BH UD 3 | O74: BH UD 4 | P74: BH UD 5
A75: =ISEVEN(ROW()) -> FALSE | B75: 1114 | C75: Sampson, DeDe | D75: B1 | E75: 8000 | F75: 0.08 | G75: 44271 | H75: 95 | I75: 7600 | J75: 0.095 | K75: USD | L75: BH UD 1 | M75: BH UD 2 | N75: BH UD 3 | O75: BH UD 4 | P75: BH UD 5
A76: =ISEVEN(ROW()) -> TRUE | B76: 1115 | C76: Ross, Michael | D76: B1 | E76: 9000 | F76: 0.09 | G76: 43905 | H76: 1.1 | I76: =E76*H76 -> 9900 | J76: 0.09 | K76: USD | L76: BH UD 1 | M76: BH UD 2 | N76: BH UD 3 | O76: BH UD 4 | P76: BH UD 5
A77: =ISEVEN(ROW()) -> FALSE | B77: 1115 | C77: Ross, Michael | D77: B1 | E77: 8000 | F77: 0.08 | G77: 44271 | H77: 95 | I77: 7600 | J77: 0.095 | K77: USD | L77: BH UD 1 | M77: BH UD 2 | N77: BH UD 3 | O77: BH UD 4 | P77: BH UD 5
A78: =ISEVEN(ROW()) -> TRUE | B78: 1117 | C78: Ramsey, Richele | D78: B1 | E78: 9000 | F78: 0.09 | G78: 43905 | H78: 1.1 | I78: =E78*H78 -> 9900 | J78: 0.09 | K78: USD | L78: BH UD 1 | M78: BH UD 2 | N78: BH UD 3 | O78: BH UD 4 | P78: BH UD 5
A79: =ISEVEN(ROW()) -> FALSE | B79: 1117 | C79: Ramsey, Richele | D79: B1 | E79: 8000 | F79: 0.08 | G79: 44271 | H79: 95 | I79: 7600 | J79: 0.095 | K79: USD | L79: BH UD 1 | M79: BH UD 2 | N79: BH UD 3 | O79: BH UD 4 | P79: BH UD 5
A80: =ISEVEN(ROW()) -> TRUE | B80: 1118 | C80: Perez, Leila | D80: B1 | E80: 9000 | F80: 0.09 | G80: 43905 | H80: 1.1 | I80: =E80*H80 -> 9900 | J80: 0.09 | K80: USD | L80: BH UD 1 | M80: BH UD 2 | N80: BH UD 3 | O80: BH UD 4 | P80: BH UD 5
A81: =ISEVEN(ROW()) -> FALSE | B81: 1118 | C81: Perez, Leila | D81: B1 | E81: 8000 | F81: 0.08 | G81: 44271 | H81: 95 | I81: 7600 | J81: 0.095 | K81: USD | L81: BH UD 1 | M81: BH UD 2 | N81: BH UD 3 | O81: BH UD 4 | P81: BH UD 5
A82: =ISEVEN(ROW()) -> TRUE | B82: 1119 | C82: Mills, Gavin | D82: B1 | E82: 9000 | F82: 0.09 | G82: 43905 | H82: 1.1 | I82: =E82*H82 -> 9900 | J82: 0.09 | K82: USD | L82: BH UD 1 | M82: BH UD 2 | N82: BH UD 3 | O82: BH UD 4 | P82: BH UD 5
A83: =ISEVEN(ROW()) -> FALSE | B83: 1119 | C83: Mills, Gavin | D83: B1 | E83: 8000 | F83: 0.08 | G83: 44271 | H83: 95 | I83: 7600 | J83: 0.095 | K83: USD | L83: BH UD 1 | M83: BH UD 2 | N83: BH UD 3 | O83: BH UD 4 | P83: BH UD 5
A84: =ISEVEN(ROW()) -> TRUE | B84: 1121 | C84: Masters, Sarah | D84: B1 | E84: 9000 | F84: 0.09 | G84: 43905 | H84: 1.1 | I84: =E84*H84 -> 9900 | J84: 0.09 | K84: USD | L84: BH UD 1 | M84: BH UD 2 | N84: BH UD 3 | O84: BH UD 4 | P84: BH UD 5
A85: =ISEVEN(ROW()) -> FALSE | B85: 1121 | C85: Masters, Sarah | D85: B1 | E85: 8000 | F85: 0.08 | G85: 44271 | H85: 95 | I85: 7600 | J85: 0.095 | K85: USD | L85: BH UD 1 | M85: BH UD 2 | N85: BH UD 3 | O85: BH UD 4 | P85: BH UD 5
A86: =ISEVEN(ROW()) -> TRUE | B86: 1123 | C86: Jackson, Leah | D86: B1 | E86: 9000 | F86: 0.09 | G86: 43905 | H86: 1.1 | I86: =E86*H86 -> 9900 | J86: 0.09 | K86: USD | L86: BH UD 1 | M86: BH UD 2 | N86: BH UD 3 | O86: BH UD 4 | P86: BH UD 5
A87: =ISEVEN(ROW()) -> FALSE | B87: 1123 | C87: Jackson, Leah | D87: B1 | E87: 8000 | F87: 0.08 | G87: 44271 | H87: 95 | I87: 7600 | J87: 0.095 | K87: USD | L87: BH UD 1 | M87: BH UD 2 | N87: BH UD 3 | O87: BH UD 4 | P87: BH UD 5
A88: =ISEVEN(ROW()) -> TRUE | B88: 1125 | C88: Weddle, Valoria | D88: B1 | E88: 9000 | F88: 0.09 | G88: 43905 | H88: 1.1 | I88: =E88*H88 -> 9900 | J88: 0.09 | K88: USD | L88: BH UD 1 | M88: BH UD 2 | N88: BH UD 3 | O88: BH UD 4 | P88: BH UD 5
A89: =ISEVEN(ROW()) -> FALSE | B89: 1125 | C89: Weddle, Valoria | D89: B1 | E89: 8000 | F89: 0.08 | G89: 44271 | H89: 95 | I89: 7600 | J89: 0.095 | K89: USD | L89: BH UD 1 | M89: BH UD 2 | N89: BH UD 3 | O89: BH UD 4 | P89: BH UD 5
A90: =ISEVEN(ROW()) -> TRUE | B90: 1126 | C90: Ungaba, Naomi | D90: B1 | E90: 9000 | F90: 0.09 | G90: 43905 | H90: 1.1 | I90: =E90*H90 -> 9900 | J90: 0.09 | K90: USD | L90: BH UD 1 | M90: BH UD 2 | N90: BH UD 3 | O90: BH UD 4 | P90: BH UD 5
A91: =ISEVEN(ROW()) -> FALSE | B91: 1126 | C91: Ungaba, Naomi | D91: B1 | E91: 8000 | F91: 0.08 | G91: 44271 | H91: 95 | I91: 7600 | J91: 0.095 | K91: USD | L91: BH UD 1 | M91: BH UD 2 | N91: BH UD 3 | O91: BH UD 4 | P91: BH UD 5
A92: =ISEVEN(ROW()) -> TRUE | B92: 1127 | C92: Tanya Field | D92: B1 | E92: 9000 | F92: 0.09 | G92: 43905 | H92: 1.1 | I92: =E92*H92 -> 9900 | J92: 0.09 | K92: USD | L92: BH UD 1 | M92: BH UD 2 | N92: BH UD 3 | O92: BH UD 4 | P92: BH UD 5
A93: =ISEVEN(ROW()) -> FALSE | B93: 1127 | C93: Tanya Field | D93: B1 | E93: 8000 | F93: 0.08 | G93: 44271 | H93: 95 | I93: 7600 | J93: 0.095 | K93: USD | L93: BH UD 1 | M93: BH UD 2 | N93: BH UD 3 | O93: BH UD 4 | P93: BH UD 5
A94: =ISEVEN(ROW()) -> TRUE | B94: 1128 | C94: Hinze, Drea | D94: B1 | E94: 9000 | F94: 0.09 | G94: 43905 | H94: 1.1 | I94: =E94*H94 -> 9900 | J94: 0.09 | K94: USD | L94: BH UD 1 | M94: BH UD 2 | N94: BH UD 3 | O94: BH UD 4 | P94: BH UD 5
A95: =ISEVEN(ROW()) -> FALSE | B95: 1128 | C95: Hinze, Drea | D95: B1 | E95: 8000 | F95: 0.08 | G95: 44271 | H95: 95 | I95: 7600 | J95: 0.095 | K95: USD | L95: BH UD 1 | M95: BH UD 2 | N95: BH UD 3 | O95: BH UD 4 | P95: BH UD 5
A96: =ISEVEN(ROW()) -> TRUE | B96: 1132 | C96: Tso, Ann | D96: B1 | E96: 9000 | F96: 0.09 | G96: 43905 | H96: 1.1 | I96: =E96*H96 -> 9900 | J96: 0.09 | K96: USD | L96: BH UD 1 | M96: BH UD 2 | N96: BH UD 3 | O96: BH UD 4 | P96: BH UD 5
A97: =ISEVEN(ROW()) -> FALSE | B97: 1132 | C97: Tso, Ann | D97: B1 | E97: 8000 | F97: 0.08 | G97: 44271 | H97: 95 | I97: 7600 | J97: 0.095 | K97: USD | L97: BH UD 1 | M97: BH UD 2 | N97: BH UD 3 | O97: BH UD 4 | P97: BH UD 5
A98: =ISEVEN(ROW()) -> TRUE | B98: 2000 | C98: Tompkins, Brian | D98: B1 | E98: 9000 | F98: 0.09 | G98: 43905 | H98: 1.1 | I98: =E98*H98 -> 9900 | J98: 0.09 | K98: USD | L98: BH UD 1 | M98: BH UD 2 | N98: BH UD 3 | O98: BH UD 4 | P98: BH UD 5
A99: =ISEVEN(ROW()) -> FALSE | B99: 2000 | C99: Tompkins, Brian | D99: B1 | E99: 8000 | F99: 0.08 | G99: 44271 | H99: 95 | I99: 7600 | J99: 0.095 | K99: USD | L99: BH UD 1 | M99: BH UD 2 | N99: BH UD 3 | O99: BH UD 4 | P99: BH UD 5
A100: =ISEVEN(ROW()) -> TRUE | B100: 2001 | C100: Ward Jr, Lloyd | D100: B1 | E100: 9000 | F100: 0.09 | G100: 43905 | H100: 1.1 | I100: =E100*H100 -> 9900 | J100: 0.09 | K100: USD | L100: BH UD 1 | M100: BH UD 2 | N100: BH UD 3 | O100: BH UD 4 | P100: BH UD 5
...

Sheet Employee LTI History
A1: Emp Id | B1: Name | C1: LTI Plan Name | D1: LTI Base Amt | E1: Currency Code | F1: LTI Grant Date | G1: Tgt LTI Opp Amt | H1: Number Of Sharesxx | I1: Share Pricexx | J1: Tgt LTI Opp Pct | K1: Total LTI Payout Amt
A2: 59 | B2: Sanders Lynn | C2: L1 | D2: 30930 | E2: USD | F2: 42809 | G2: 3093 | H2: =INT(G2/I2) -> 140 | I2: 22 | J2: =K2/D2 -> 0.099579696 | K2: =H2*I2 -> 3080
A3: 59 | B3: Sanders, Lynn | C3: L2 | D3: 30930 | E3: USD | F3: 42809 | G3: 3093 | H3: =INT(G3/I3) -> 140 | I3: 22 | J3: =K3/D3 -> 0.099579696 | K3: =H3*I3 -> 3080
A4: 59 | B4: Sanders, Lynn | C4: L2 | D4: 30930 | E4: USD | F4: 43174 | G4: 3093 | H4: =INT(G4/I4) -> 140 | I4: 22 | J4: =K4/D4 -> 0.099579696 | K4: =H4*I4 -> 3080
A5: 59 | B5: Sanders, Lynn | C5: L2 | D5: 30930 | E5: USD | F5: 42809 | G5: 3093 | H5: =INT(G5/I5) -> 140 | I5: 22 | J5: =K5/D5 -> 0.099579696 | K5: =H5*I5 -> 3080
A6: 70 | B6: Kirklan, Richard | C6: L2 | D6: 28750 | E6: USD | F6: 42809 | G6: 2875 | H6: =INT(G6/I6) -> 130 | I6: 22 | J6: =K6/D6 -> 0.099478261 | K6: =H6*I6 -> 2860
A7: 72 | B7: Davis, Beverly | C7: L1 | D7: 38015 | E7: USD | F7: 42809 | G7: 7603 | H7: =INT(G7/I7) -> 345 | I7: 22 | J7: =K7/D7 -> 0.19965803 | K7: =H7*I7 -> 7590
A8: 73 | B8: Bonamy, James | C8: L1 | D8: 11030 | E8: USD | F8: 42809 | G8: 2206 | H8: =INT(G8/I8) -> 100 | I8: 22 | J8: =K8/D8 -> 0.19945603 | K8: =H8*I8 -> 2200
A9: 73 | B9: Bonamy, James | C9: L1 | D9: 11030 | E9: USD | F9: 43174 | G9: 2206 | H9: =INT(G9/I9) -> 100 | I9: 22 | J9: =K9/D9 -> 0.19945603 | K9: =H9*I9 -> 2200
A10: 80 | B10: Jackson, Charmain | C10: L1 | D10: 13810 | E10: USD | F10: 42809 | G10: 1381 | H10: =INT(G10/I10) -> 62 | I10: 22 | J10: =K10/D10 -> 0.098769008 | K10: =H10*I10 -> 1364
A11: 86 | B11: Rogers, Mary | C11: L1 | D11: 17220 | E11: USD | F11: 42809 | G11: 3444 | H11: =INT(G11/I11) -> 156 | I11: 22 | J11: =K11/D11 -> 0.19930314 | K11: =H11*I11 -> 3432
A12: 88 | B12: Brooks, Wendy | C12: L1 | D12: 27720 | E12: USD | F12: 42809 | G12: 2772 | H12: =INT(G12/I12) -> 126 | I12: 22 | J12: =K12/D12 -> 0.1 | K12: =H12*I12 -> 2772
A13: 88 | B13: Brooks, Wendy | C13: L1 | D13: 27720 | E13: USD | F13: 43174 | G13: 2772 | H13: =INT(G13/I13) -> 126 | I13: 22 | J13: =K13/D13 -> 0.1 | K13: =H13*I13 -> 2772
... A74: 2168 | B74: Citrus, Susan | C74: L1 | D74: 176200 | E74: CAD | F74: 42809 | G74: 17620 | H74: =INT(G74/I74) -> 800 | I74: 22 | J74: =K74/D74 -> 0.099886493 | K74: =H74*I74 -> 17600

Sheet Usersvalid
A1: Emp Id | B1: User Name First | C1: User Name Last | D1: User Type | E1: User Principal Name | F1: Login Id | G1: Email Address | H1: User Password
A2: 72 | B2: Beverly | C2: Davis | D2: Employee | E2: =G2 -> bDavis@dartican.com | F2: bdavis | G2: bDavis@dartican.com | H2: Open
A3: 162 | B3: Calvin | C3: Thompson | D3: Employee | E3: =G3 -> Calvin@dartican.com | F3: Calvin | G3: Calvin@dartican.com | H3: Open
A4: 166 | B4: Joe | C4: Montana | D4: Employee | E4: =G4 -> JMontana@dartican.com | F4: JMontana | G4: JMontana@dartican.com | H4: Open
A5: 168 | B5: Nedra | C5: Soles | D5: Employee | E5: =G5 -> Nsoles@dartican.com | F5: Nsoles | G5: Nsoles@dartican.com | H5: Open
A6: 1012 | B6: Jack | C6: Sherman | D6: Employee | E6: =G6 -> Jsherman@dartican.com | F6: Jsherman | G6: Jsherman@dartican.com | H6: Open
A7: 1113 | B7: Sam | C7: Duncan | D7: Employee | E7: =G7 -> sDuncan@dartican.com | F7: sduncan | G7: sDuncan@dartican.com | H7: Open
A8: 80 | B8: Charmain | C8: Jackson | D8: Employee | E8: =G8 -> cjackson@dartican.com | F8: cjackson | G8: cjackson@dartican.com | H8: Open
A9: 2166 | B9: Green | C9: Tea | D9: Employee | E9: =G9 -> tgreen@dartican.com | F9: Tgreen | G9: tgreen@dartican.com | H9: Open
A10: 1117 | B10: Richele | C10: Ramsey | D10: Employee | E10: =G10 -> rramsey@dartican.com | F10: rramsey | G10: rramsey@dartican.com | H10: Open
A11: 1114 | B11: DeDe | C11: Sampson | D11: Employee | E11: =G11 -> dsampson@dartican.com | F11: dsampson | G11: dsampson@dartican.com | H11: Open
A12: 2013 | B12: James | C12: Yokay | D12: Employee | E12: =G12 -> jyokay@dartican.com | F12: jyokay | G12: jyokay@dartican.com | H12: Open
A13: 110 | B13: Atif | C13: sheikh | D13: Employee | E13: atif@dartican.com | F13: 110 | G13: atif@dartican.com | H13: Open
A14: 1121 | B14: Masters | C14: Sarah | D14: Employee | E14: Smasters@dartican.com | F14: Msarah | G14: Smasters@dartican.com | H14: Open

Sheet Usersxxx
A1: Employee ID | B1: User Name First | C1: User Name Last | D1: User Type | E1: Login Id | F1: Email Address | G1: User Password | H1: User Time Zone
A2: 0000000A1 | B2: Michael | C2: Gerthe | D2: Employee | E2: mgerthe | F2: mgerthe@dartican.com | G2: open | H2: North American Central
A3: 10003 | B3: Juan | C3: Garza | D3: Employee | E3: jgarza | F3: jgarza@dartican.com | G3: open | H3: North American Central
A4: 10007 | B4: Steven | C4: Kabak | D4: Employee | E4: skabak | F4: skabak@dartican.com | G4: open | H4: North American Central
A5: 10009 | B5: Stewart | C5: Byrne | D5: Employee | E5: sbyrne | F5: sbyrne@dartican.com | G5: open | H5: North American Central
A6: 10011 | B6: Katie | C6: Smith | D6: Employee | E6: ksmith | F6: ksmith@dartican.com | G6: open | H6: North American Central
A7: 10013 | B7: Edward | C7: Huang | D7: Employee | E7: ehuang | F7: ehuang@dartican.com | G7: open | H7: North American Central
A8: 10015 | B8: Manuel | C8: Amador | D8: Employee | E8: mamador | F8: mamador@dartican.com | G8: open | H8: North American Central
A9: 10019 | B9: Georgia | C9: Harrison | D9: Employee | E9: gharrison | F9: gharrison@dartican.com | G9: open | H9: North American Central
A10: 10020 | B10: Kerri | C10: Berndt | D10: Employee | E10: kberndt | F10: kberndt@dartican.com | G10: open | H10: North American Central
A11: 10030 | B11: Ed | C11: Zimny | D11: Employee | E11: ezimny | F11: ezimny@dartican.com | G11: open | H11: North American Central
A12: 10031 | B12: Bradley | C12: Smith | D12: Employee | E12: bsmith | F12: bsmith@dartican.com | G12: open | H12: North American Central
A13: 10032 | B13: Rob | C13: Feldman | D13: Employee | E13: rfeldman | F13: rfeldman@dartican.com | G13: open
A14: 10038 | B14: Mike | C14: Stanley | D14: Employee | E14: mstanley | F14: mstanley@dartican.com | G14: open
A15: 10039 | B15: Dianne | C15: Buschmann | D15: Employee | E15: dbuschmann | F15: dbuschmann@dartican.com | G15: open
A16: 10043 | B16: Cathy | C16: Bonwick | D16: Employee | E16: cbonwick | F16: cbonwick@dartican.com | G16: open
A17: 10045 | B17: Ray | C17: Liang | D17: Employee | E17: rliang | F17: rliang@dartican.com | G17: open
A18: 10046 | B18: Jimmy | C18: Shi | D18: Employee | E18: jshi | F18: jshi@dartican.com | G18: open
A19: 10048 | B19: Ye | C19: Song | D19: Employee | E19: ysong | F19: ysong@dartican.com | G19: open
A20: 10049 | B20: Geoffrey | C20: Gao | D20: Employee | E20: ggao | F20: ggao@dartican.com | G20: open
A21: 10052 | B21: Chaitanya | C21: Kancherla | D21: Employee | E21: ckancherla | F21: ckancherla@dartican.com | G21: open
A22: 10054 | B22: Robert | C22: Wright | D22: Employee | E22: rwright | F22: rwright@dartican.com | G22: open
A23: 10055 | B23: Alex | C23: Beynon | D23: Employee | E23: abeynon | F23: abeynon@dartican.com | G23: open
A24: 10064 | B24: Oksana | C24: Maslak | D24: Employee | E24: omaslak | F24: omaslak@dartican.com | G24: open
... A300: 11337 | B300: Aurang | C300: Khan | D300: Employee | E300: akhan | F300: akhan@dartican.com | G300: open

Sheet Sheet2
A1: Mgr Emp Id | B1: Mgr Name
A2: 72 | B2: Davis, Beverly
A3: 72 | B3: Davis, Beverly
A4: 72 | B4: Davis, Beverly
A5: 72 | B5: Davis, Beverly
A6: 72 | B6: Davis, Beverly
A7: 72 | B7: Davis, Beverly
A8: 72 | B8: Davis, Beverly
A9: 72 | B9: Davis, Beverly
A10: 72 | B10: Davis, Beverly
A11: 72 | B11: Davis, Beverly
A12: 72 | B12: Davis, Beverly

Sheet TEST
